Workbook
Name TimeSeries: 'SSI cola for the year'!$B$3

Sheet Portfolio Drawdown
A2: Combined liquid portfolio @62 | B2: 1000000
A3: Rate of Return (from Main) | B3: =Main!B14 -> 0.04
A4: Desired Annual spending based at 62 | B4: 100000
A5: CPI | B5: =Main!E12 -> 0.03263964
A10: Age | B10: Year | C10: Desired Annual Spending | D10: Social Security at 62 | E10: Portfolio withdrawal if claiming at 62 | F10: Portfolio balance if claiming at 62 | G10: Social Security at 67 | H10: Portfoilo withdrawal if claiming at 67 | I10: Portfolio Balance if claiming at 67 | J10: Social Security at 70 | K10: Portfolio withdrawal if claiing at 70 | L10: Portfoilo balace if claiming at 70
A11: 62 | C11: =B4 -> 100000 | D11: =Main!B78 -> 23704.8 | E11: =MAX(0,C11-D11) -> 76295.2 | F11: =B2-E11 -> 923704.8 | G11: 0 | H11: =C11-G11 -> 100000 | I11: =B2-H11 -> 900000 | J11: 0 | K11: =C11-J11 -> 100000 | L11: =B2-K11 -> 900000
A12: 63 | C12: =C11*(1+$B$5) -> 103263.96 | D12: =Main!B79 -> 24297.42 | E12: =MAX(0,C12-D12) -> 78966.544 | F12: =F11*(1+$B$3)-E12 -> 881686.45 | G12: 0 | H12: =C12-G12 -> 103263.96 | I12: =I11*(1+$B$3)-H12 -> 832736.04 | J12: 0 | K12: =C12-J12 -> 103263.96 | L12: =L11*(1+$B$3)-K12 -> 832736.04
A13: 64 | C13: =C12*(1+$B$5) -> 106634.46 | D13: =Main!B80 -> 24904.855 | E13: =MAX(0,C13-D13) -> 81729.607 | F13: =F12*(1+$B$3)-E13 -> 835224.3 | G13: 0 | H13: =C13-G13 -> 106634.46 | I13: =I12*(1+$B$3)-H13 -> 759411.01 | J13: 0 | K13: =C13-J13 -> 106634.46 | L13: =L12*(1+$B$3)-K13 -> 759411.01
A14: 65 | C14: =C13*(1+$B$5) -> 110114.97 | D14: =Main!B81 -> 25527.477 | E14: =MAX(0,C14-D14) -> 84587.496 | F14: =F13*(1+$B$3)-E14 -> 784045.77 | G14: 0 | H14: =C14-G14 -> 110114.97 | I14: =I13*(1+$B$3)-H14 -> 679672.48 | J14: 0 | K14: =C14-J14 -> 110114.97 | L14: =L13*(1+$B$3)-K14 -> 679672.48
A15: 66 | C15: =C14*(1+$B$5) -> 113709.09 | D15: =Main!B82 -> 26165.664 | E15: =MAX(0,C15-D15) -> 87543.422 | F15: =F14*(1+$B$3)-E15 -> 727864.18 | G15: 0 | H15: =C15-G15 -> 113709.09 | I15: =I14*(1+$B$3)-H15 -> 593150.3 | J15: 0 | K15: =C15-J15 -> 113709.09 | L15: =L14*(1+$B$3)-K15 -> 593150.3
A16: 67 | C16: =C15*(1+$B$5) -> 117420.51 | D16: =Main!B83 -> 26819.805 | E16: =MAX(0,C16-D16) -> 90600.704 | F16: =F15*(1+$B$3)-E16 -> 666378.05 | G16: =Main!D83 -> 38314.008 | H16: =C16-G16 -> 79106.502 | I16: =I15*(1+$B$3)-H16 -> 537769.81 | J16: 0 | K16: =C16-J16 -> 117420.51 | L16: =L15*(1+$B$3)-K16 -> 499455.8
A17: 68 | C17: =C16*(1+$B$5) -> 121253.07 | D17: =Main!B84 -> 27490.301 | E17: =MAX(0,C17-D17) -> 93762.772 | F17: =F16*(1+$B$3)-E17 -> 599270.4 | G17: =Main!D84 -> 39271.858 | H17: =C17-G17 -> 81981.215 | I17: =I16*(1+$B$3)-H17 -> 477299.38 | J17: 0 | K17: =C17-J17 -> 121253.07 | L17: =L16*(1+$B$3)-K17 -> 398180.96
A18: 69 | C18: =C17*(1+$B$5) -> 125210.73 | D18: =Main!B85 -> 28177.558 | E18: =MAX(0,C18-D18) -> 97033.171 | F18: =F17*(1+$B$3)-E18 -> 526208.04 | G18: =Main!D85 -> 40253.654 | H18: =C18-G18 -> 84957.075 | I18: =I17*(1+$B$3)-H18 -> 411434.28 | J18: 0 | K18: =C18-J18 -> 125210.73 | L18: =L17*(1+$B$3)-K18 -> 288897.47
A19: 70 | C19: =C18*(1+$B$5) -> 129297.56 | D19: =Main!B86 -> 28881.997 | E19: =MAX(0,C19-D19) -> 100415.57 | F19: =F18*(1+$B$3)-E19 -> 446840.8 | G19: =Main!D86 -> 41259.996 | H19: =C19-G19 -> 88037.567 | I19: =I18*(1+$B$3)-H19 -> 339854.09 | J19: =Main!F86 -> 51162.395 | K19: =C19-J19 -> 78135.168 | L19: =L18*(1+$B$3)-K19 -> 222318.2
A20: 71 | C20: =C19*(1+$B$5) -> 133517.79 | D20: =Main!B87 -> 29604.047 | E20: =MAX(0,C20-D20) -> 103913.74 | F20: =F19*(1+$B$3)-E20 -> 360800.69 | G20: =Main!D87 -> 42291.496 | H20: =C20-G20 -> 91226.293 | I20: =I19*(1+$B$3)-H20 -> 262221.96 | J20: =Main!F87 -> 52441.455 | K20: =C20-J20 -> 81076.334 | L20: =L19*(1+$B$3)-K20 -> 150134.59
A21: 72 | C21: =C20*(1+$B$5) -> 137875.76 | D21: =Main!B88 -> 30344.148 | E21: =MAX(0,C21-D21) -> 107531.61 | F21: =F20*(1+$B$3)-E21 -> 267701.1 | G21: =Main!D88 -> 43348.783 | H21: =C21-G21 -> 94526.978 | I21: =I20*(1+$B$3)-H21 -> 178183.86 | J21: =Main!F88 -> 53752.491 | K21: =C21-J21 -> 84123.27 | L21: =L20*(1+$B$3)-K21 -> 72016.705
A22: 73 | C22: =C21*(1+$B$5) -> 142375.98 | D22: =Main!B89 -> 31102.752 | E22: =MAX(0,C22-D22) -> 111273.22 | F22: =F21*(1+$B$3)-E22 -> 167135.92 | G22: =Main!D89 -> 44432.503 | H22: =C22-G22 -> 97943.473 | I22: =I21*(1+$B$3)-H22 -> 87367.741 | J22: =Main!F89 -> 55096.303 | K22: =C22-J22 -> 87279.673 | L22: =L21*(1+$B$3)-K22 -> -12382.299
A23: 74 | C23: =C22*(1+$B$5) -> 147023.08 | D23: =Main!B90 -> 31880.321 | E23: =MAX(0,C23-D23) -> 115142.76 | F23: =F22*(1+$B$3)-E23 -> 58678.604 | G23: =Main!D90 -> 45543.315 | H23: =C23-G23 -> 101479.76 | I23: =I22*(1+$B$3)-H23 -> -10617.311 | J23: =Main!F90 -> 56473.711 | K23: =C23-J23 -> 90549.366 | L23: =L22*(1+$B$3)-K23 -> -103426.96
A24: 75 | C24: =C23*(1+$B$5) -> 151821.86 | D24: =Main!B91 -> 32677.329 | E24: =MAX(0,C24-D24) -> 119144.53 | F24: =F23*(1+$B$3)-E24 -> -58118.78 | G24: =Main!D91 -> 46681.898 | H24: =C24-G24 -> 105139.96 | I24: =I23*(1+$B$3)-H24 -> -116181.96 | J24: =Main!F91 -> 57885.554 | K24: =C24-J24 -> 93936.303 | L24: =L23*(1+$B$3)-K24 -> -201500.34
A25: 76 | C25: =C24*(1+$B$5) -> 156777.27 | D25: =Main!B92 -> 33494.262 | E25: =MAX(0,C25-D25) -> 123283.01 | F25: =F24*(1+$B$3)-E25 -> -183726.54 | G25: =Main!D92 -> 47848.945 | H25: =C25-G25 -> 108928.32 | I25: =I24*(1+$B$3)-H25 -> -229757.56 | J25: =Main!F92 -> 59332.692 | K25: =C25-J25 -> 97444.575 | L25: =L24*(1+$B$3)-K25 -> -307004.93
A26: 77 | C26: =C25*(1+$B$5) -> 161894.42 | D26: =Main!B93 -> 34331.618 | E26: =MAX(0,C26-D26) -> 127562.8 | F26: =F25*(1+$B$3)-E26 -> -318638.4 | G26: =Main!D93 -> 49045.169 | H26: =C26-G26 -> 112849.25 | I26: =I25*(1+$B$3)-H26 -> -351797.12 | J26: =Main!F93 -> 60816.01 | K26: =C26-J26 -> 101078.41 | L26: =L25*(1+$B$3)-K26 -> -420363.53
A27: 78 | C27: =C26*(1+$B$5) -> 167178.6 | D27: =Main!B94 -> 35189.909 | E27: =MAX(0,C27-D27) -> 131988.69 | F27: =F26*(1+$B$3)-E27 -> -463372.62 | G27: =Main!D94 -> 50271.298 | H27: =C27-G27 -> 116907.3 | I27: =I26*(1+$B$3)-H27 -> -482776.3 | J27: =Main!F94 -> 62336.41 | K27: =C27-J27 -> 104842.19 | L27: =L26*(1+$B$3)-K27 -> -542020.26
A28: 79 | C28: =C27*(1+$B$5) -> 172635.25 | D28: =Main!B95 -> 36069.657 | E28: =MAX(0,C28-D28) -> 136565.59 | F28: =F27*(1+$B$3)-E28 -> -618473.12 | G28: =Main!D95 -> 51528.081 | H28: =C28-G28 -> 121107.16 | I28: =I27*(1+$B$3)-H28 -> -623194.52 | J28: =Main!F95 -> 63894.82 | K28: =C28-J28 -> 108740.43 | L28: =L27*(1+$B$3)-K28 -> -672441.5
A29: 80 | C29: =C28*(1+$B$5) -> 178270 | D29: =Main!B96 -> 36971.398 | E29: =MAX(0,C29-D29) -> 141298.6 | F29: =F28*(1+$B$3)-E29 -> -784510.64 | G29: =Main!D96 -> 52816.283 | H29: =C29-G29 -> 125453.71 | I29: =I28*(1+$B$3)-H29 -> -773576.01 | J29: =Main!F96 -> 65492.191 | K29: =C29-J29 -> 112777.81 | L29: =L28*(1+$B$3)-K29 -> -812116.97
A30: 81 | C30: =C29*(1+$B$5) -> 184088.67 | D30: =Main!B97 -> 37895.683 | E30: =MAX(0,C30-D30) -> 146192.98 | F30: =F29*(1+$B$3)-E30 -> -962084.05 | G30: =Main!D97 -> 54136.69 | H30: =C30-G30 -> 129951.98 | I30: =I29*(1+$B$3)-H30 -> -934471.03 | J30: =Main!F97 -> 67129.495 | K30: =C30-J30 -> 116959.17 | L30: =L29*(1+$B$3)-K30 -> -961560.81
... A49: 100 | C49: =C48*(1+$B$5) -> 338886.37 | D49: =Main!B116 -> 60581.941 | E49: =MAX(0,C49-D49) -> 278304.43 | F49: =F48*(1+$B$3)-E49 -> -7580023.4 | G49: =Main!D116 -> 86545.629 | H49: =C49-G49 -> 252340.74 | I49: =I48*(1+$B$3)-H49 -> -6957846.6 | J49: =Main!F116 -> 107316.58 | K49: =C49-J49 -> 231569.79 | L49: =L48*(1+$B$3)-K49 -> -6563720.4

Sheet Main
A11: Full Retirement Age Benefit | B11: 2822 | D11: Average Cola since 1975 = | E11: ='SS Benefit Cal'!F3 -> 3.7294118 | N11: Breakeven Age | X11: Breakeven Age
A12: Life Expectancy | B12: 22 | D12: Average CPI since 1914 | E12: =Inflation!P123 -> 0.03263964 | N12: {=INDEX(A86:A116,MATCH(1,INDEX(--(G86:G116>=C86:C116),0),0))} -> 78 | X12: {=_xlfn.XLOOKUP(TRUE,C123:C161<=E123:E161,A123:A161,"No crossover")} -> 85
A13: Cola | B13: 0.025
A14: Rate of Return | B14: 0.04
A15: Discount Rate | B15: 0.04
A16: Retirement Funds | B16: 250000
A19: AGE | B19: Monthly benefit | C19: % change | D19: year2year change
A20: 62 | B20: =$B$11*C20 -> 1975.4 | C20: 0.7
A21: 63 | B21: =$B$11*C21 -> 2116.5 | C21: 0.75 | D21: =(B21-B20)/B20 -> 0.071428571
A22: 64 | B22: =$B$11*C22 -> 2257.6 | C22: 0.8 | D22: =(B22-B21)/B21 -> 0.066666667
A23: 65 | B23: =$B$11*C23 -> 2446.674 | C23: 0.867 | D23: =(B23-B22)/B22 -> 0.08375
A24: 66 | B24: =$B$11*C24 -> 2632.926 | C24: 0.933 | D24: =(B24-B23)/B23 -> 0.076124567
A25: 67 | B25: =$B$11*C25 -> 2822 | C25: 1 | D25: =(B25-B24)/B24 -> 0.071811361
A26: 68 | B26: =$B$11*C26 -> 3047.76 | C26: 1.08 | D26: =(B26-B25)/B25 -> 0.08
A27: 69 | B27: =$B$11*C27 -> 3273.52 | C27: 1.16 | D27: =(B27-B26)/B26 -> 0.074074074
A28: 70 | B28: =$B$11*C28 -> 3499.28 | C28: 1.24 | D28: =(B28-B27)/B27 -> 0.068965517
A32: AGE | B32: Monthy Benefit taken at 62 (Cola) | C32: Monthly Benefit taken at 67 (cola) | D32: Monthly Benefit taken at 70 (cola)
A33: 62 | B33: =B20 -> 1975.4 | F33: ="Monthly benefit with " & B13*100 & "% Cola " -> Monthly benefit with 2.5% Cola
A34: 63 | B34: =B33*(1+$B$13) -> 2024.785
A35: 64 | B35: =B34*(1+$B$13) -> 2075.4046
A36: 65 | B36: =B35*(1+$B$13) -> 2127.2897
A37: 66 | B37: =B36*(1+$B$13) -> 2180.472
A38: 67 | B38: =B37*(1+$B$13) -> 2234.9838 | C38: =B25*(1+B13)^(A25-A20) -> 3192.834
A39: 68 | B39: =B38*(1+$B$13) -> 2290.8584 | C39: =C38*(1+$B$13) -> 3272.6548
A40: 69 | B40: =B39*(1+$B$13) -> 2348.1298 | C40: =C39*(1+$B$13) -> 3354.4712
A41: 70 | B41: =B40*(1+$B$13) -> 2406.8331 | C41: =C40*(1+$B$13) -> 3438.333 | D41: =B28*(1+$B$13)^(A41-A33) -> 4263.5329
A42: 71 | B42: =B41*(1+$B$13) -> 2467.0039 | C42: =C41*(1+$B$13) -> 3524.2913 | D42: =D41*(1+$B$13) -> 4370.1212
A43: 72 | B43: =B42*(1+$B$13) -> 2528.679 | C43: =C42*(1+$B$13) -> 3612.3986 | D43: =D42*(1+$B$13) -> 4479.3742
A44: 73 | B44: =B43*(1+$B$13) -> 2591.896 | C44: =C43*(1+$B$13) -> 3702.7085 | D44: =D43*(1+$B$13) -> 4591.3586
A45: 74 | B45: =B44*(1+$B$13) -> 2656.6934 | C45: =C44*(1+$B$13) -> 3795.2763 | D45: =D44*(1+$B$13) -> 4706.1426
A46: 75 | B46: =B45*(1+$B$13) -> 2723.1107 | C46: =C45*(1+$B$13) -> 3890.1582 | D46: =D45*(1+$B$13) -> 4823.7961
A47: 76 | B47: =B46*(1+$B$13) -> 2791.1885 | C47: =C46*(1+$B$13) -> 3987.4121 | D47: =D46*(1+$B$13) -> 4944.391
A48: 77 | B48: =B47*(1+$B$13) -> 2860.9682 | C48: =C47*(1+$B$13) -> 4087.0974 | D48: =D47*(1+$B$13) -> 5068.0008
A49: 78 | B49: =B48*(1+$B$13) -> 2932.4924 | C49: =C48*(1+$B$13) -> 4189.2749 | D49: =D48*(1+$B$13) -> 5194.7008
A50: 79 | B50: =B49*(1+$B$13) -> 3005.8047 | C50: =C49*(1+$B$13) -> 4294.0067 | D50: =D49*(1+$B$13) -> 5324.5683
A51: 80 | B51: =B50*(1+$B$13) -> 3080.9498 | C51: =C50*(1+$B$13) -> 4401.3569 | D51: =D50*(1+$B$13) -> 5457.6826
A52: 81 | B52: =B51*(1+$B$13) -> 3157.9736 | C52: =C51*(1+$B$13) -> 4511.3908 | D52: =D51*(1+$B$13) -> 5594.1246
A53: 82 | B53: =B52*(1+$B$13) -> 3236.9229 | C53: =C52*(1+$B$13) -> 4624.1756 | D53: =D52*(1+$B$13) -> 5733.9777
... A71: 100 | B71: =B70*(1+$B$13) -> 5048.495 | C71: =C70*(1+$B$13) -> 7212.1358 | D71: =D70*(1+$B$13) -> 8943.0484
F73: Crossover Age
D74: ="Total payout with Cola of " & B13*100 & "% Rate of Return = " & 0*100 &" %, Breakeven Age "&F74 -> Total payout with Cola of 2.5% Rate of Return = 0 %, Breakeven Age 78 | F74: {=_xlfn.XLOOKUP(TRUE,G86:G116>=C86:C116,A86:A116,"No crossover")} -> 78
A77: Age | B77: 62 yearly benefit | C77: 62 total with Cola | D77: 67 yearly benefit w Cola | E77: 67 total with Cola | F77: 70 yearly benefit w Cola | G77: 70 total w cola | H77: 62 yearly todays $'s | I77: 67 yearly in todays $ | J77: 70 yearly in todays $ | K77: 62 total in todays $ | L77: 67 total in todays $ | M77: 70 total in todays $'S | N77: Discount rate = 4 % | O77: Rate of return = 4 %
A78: 62 | B78: =B33*12 -> 23704.8 | C78: =B78 -> 23704.8 | D78: 0 | E78: 0 | F78: 0 | G78: 0 | H78: =C78 -> 23704.8 | K78: =H78 -> 23704.8 | M78: 0 | N78: 1000 | O78: =1000 -> 1000
A79: 63 | B79: =B34*12 -> 24297.42 | C79: =C78+B79 -> 48002.22 | D79: 0 | E79: 0 | F79: 0 | G79: 0 | H79: =B79/(1+$B$15)^(A79-$A$78) -> 23362.904 | K79: =K78+H79 -> 47067.704 | M79: 0 | N79: =$N$78/(1+$B$15)^(A79-$A$78) -> 961.53846 | O79: =$O$78*(1+$B$14)^(A79-$A$78) -> 1040
A80: 64 | B80: =B35*12 -> 24904.855 | C80: =C79+B80 -> 72907.075 | D80: 0 | E80: 0 | F80: 0 | G80: 0 | H80: =B80/(1+$B$15)^(A80-$A$78) -> 23025.939 | K80: =K79+H80 -> 70093.643 | M80: 0 | N80: =$N$78/(1+$B$15)^(A80-$A$78) -> 924.55621 | O80: =$O$78*(1+$B$14)^(A80-$A$78) -> 1081.6
A81: 65 | B81: =B36*12 -> 25527.477 | C81: =C80+B81 -> 98434.552 | D81: 0 | E81: 0 | F81: 0 | G81: 0 | H81: =B81/(1+$B$15)^(A81-$A$78) -> 22693.834 | K81: =K80+H81 -> 92787.477 | M81: 0 | N81: =$N$78/(1+$B$15)^(A81-$A$78) -> 888.99636 | O81: =$O$78*(1+$B$14)^(A81-$A$78) -> 1124.864
A82: 66 | B82: =B37*12 -> 26165.664 | C82: =C81+B82 -> 124600.22 | D82: 0 | E82: 0 | F82: 0 | G82: 0 | H82: =B82/(1+$B$15)^(A82-$A$78) -> 22366.519 | K82: =K81+H82 -> 115154 | M82: 0 | N82: =$N$78/(1+$B$15)^(A82-$A$78) -> 854.80419 | O82: =$O$78*(1+$B$14)^(A82-$A$78) -> 1169.8586
A83: 67 | B83: =B38*12 -> 26819.805 | C83: =C82+B83 -> 151420.02 | D83: =C38*12 -> 38314.008 | E83: =D83 -> 38314.008 | F83: 0 | G83: 0 | H83: =B83/(1+$B$15)^(A83-$A$78) -> 22043.925 | I83: =D83/(1+$B$15)^(A83-$A$78) -> 31491.322 | K83: =K82+H83 -> 137197.92 | L83: =I83 -> 31491.322 | M83: 0 | N83: =$N$78/(1+$B$15)^(A83-$A$78) -> 821.92711 | O83: =$O$78*(1+$B$14)^(A83-$A$78) -> 1216.6529
A84: 68 | B84: =B39*12 -> 27490.301 | C84: =C83+B84 -> 178910.32 | D84: =C39*12 -> 39271.858 | E84: =E83+D84 -> 77585.866 | F84: 0 | G84: 0 | H84: =B84/(1+$B$15)^(A84-$A$78) -> 21725.984 | I84: =D84/(1+$B$15)^(A84-$A$78) -> 31037.12 | K84: =K83+H84 -> 158923.9 | L84: =L83+I84 -> 62528.441 | M84: 0 | N84: =$N$78/(1+$B$15)^(A84-$A$78) -> 790.31453 | O84: =$O$78*(1+$B$14)^(A84-$A$78) -> 1265.319
A85: 69 | B85: =B40*12 -> 28177.558 | C85: =C84+B85 -> 207087.88 | D85: =C40*12 -> 40253.654 | E85: =E84+D85 -> 117839.52 | F85: 0 | G85: 0 | H85: =B85/(1+$B$15)^(A85-$A$78) -> 21412.628 | I85: =D85/(1+$B$15)^(A85-$A$78) -> 30589.469 | K85: =K84+H85 -> 180336.53 | L85: =L84+I85 -> 93117.91 | M85: 0 | N85: =$N$78/(1+$B$15)^(A85-$A$78) -> 759.91781 | O85: =$O$78*(1+$B$14)^(A85-$A$78) -> 1315.9318
A86: 70 | B86: =B41*12 -> 28881.997 | C86: =C85+B86 -> 235969.88 | D86: =C41*12 -> 41259.996 | E86: =E85+D86 -> 159099.52 | F86: =D41*12 -> 51162.395 | G86: =F86 -> 51162.395 | H86: =B86/(1+$B$15)^(A86-$A$78) -> 21103.792 | I86: =D86/(1+$B$15)^(A86-$A$78) -> 30148.275 | J86: =F86/(1+$B$15)^(A86-$A$78) -> 37383.861 | K86: =K85+H86 -> 201440.33 | L86: =L85+I86 -> 123266.19 | M86: =J86 -> 37383.861 | N86: =$N$78/(1+$B$15)^(A86-$A$78) -> 730.69021 | O86: =$O$78*(1+$B$14)^(A86-$A$78) -> 1368.5691
A87: 71 | B87: =B42*12 -> 29604.047 | C87: =C86+B87 -> 265573.92 | D87: =C42*12 -> 42291.496 | E87: =E86+D87 -> 201391.01 | F87: =D42*12 -> 52441.455 | G87: =G86+F87 -> 103603.85 | H87: =B87/(1+$B$15)^(A87-$A$78) -> 20799.411 | I87: =D87/(1+$B$15)^(A87-$A$78) -> 29713.444 | J87: =F87/(1+$B$15)^(A87-$A$78) -> 36844.67 | K87: =K86+H87 -> 222239.74 | L87: =L86+I87 -> 152979.63 | M87: =M86+J87 -> 74228.531 | N87: =$N$78/(1+$B$15)^(A87-$A$78) -> 702.58674 | O87: =$O$78*(1+$B$14)^(A87-$A$78) -> 1423.3118
A88: 72 | B88: =B43*12 -> 30344.148 | C88: =C87+B88 -> 295918.07 | D88: =C43*12 -> 43348.783 | E88: =E87+D88 -> 244739.79 | F88: =D43*12 -> 53752.491 | G88: =G87+F88 -> 157356.34 | H88: =B88/(1+$B$15)^(A88-$A$78) -> 20499.419 | I88: =D88/(1+$B$15)^(A88-$A$78) -> 29284.885 | J88: =F88/(1+$B$15)^(A88-$A$78) -> 36313.257 | K88: =K87+H88 -> 242739.16 | L88: =L87+I88 -> 182264.51 | M88: =M87+J88 -> 110541.79 | N88: =$N$78/(1+$B$15)^(A88-$A$78) -> 675.56417 | O88: =$O$78*(1+$B$14)^(A88-$A$78) -> 1480.2443
A89: 73 | B89: =B44*12 -> 31102.752 | C89: =C88+B89 -> 327020.82 | D89: =C44*12 -> 44432.503 | E89: =E88+D89 -> 289172.3 | F89: =D44*12 -> 55096.303 | G89: =G88+F89 -> 212452.64 | H89: =B89/(1+$B$15)^(A89-$A$78) -> 20203.754 | I89: =D89/(1+$B$15)^(A89-$A$78) -> 28862.506 | J89: =F89/(1+$B$15)^(A89-$A$78) -> 35789.508 | K89: =K88+H89 -> 262942.91 | L89: =L88+I89 -> 211127.02 | M89: =M88+J89 -> 146331.3 | N89: =$N$78/(1+$B$15)^(A89-$A$78) -> 649.58093 | O89: =$O$78*(1+$B$14)^(A89-$A$78) -> 1539.4541
A90: 74 | B90: =B45*12 -> 31880.321 | C90: =C89+B90 -> 358901.14 | D90: =C45*12 -> 45543.315 | E90: =E89+D90 -> 334715.61 | F90: =D45*12 -> 56473.711 | G90: =G89+F90 -> 268926.35 | H90: =B90/(1+$B$15)^(A90-$A$78) -> 19912.354 | I90: =D90/(1+$B$15)^(A90-$A$78) -> 28446.22 | J90: =F90/(1+$B$15)^(A90-$A$78) -> 35273.313 | K90: =K89+H90 -> 282855.26 | L90: =L89+I90 -> 239573.24 | M90: =M89+J90 -> 181604.61 | N90: =$N$78/(1+$B$15)^(A90-$A$78) -> 624.59705 | O90: =$O$78*(1+$B$14)^(A90-$A$78) -> 1601.0322
A91: 75 | B91: =B46*12 -> 32677.329 | C91: =C90+B91 -> 391578.47 | D91: =C46*12 -> 46681.898 | E91: =E90+D91 -> 381397.51 | F91: =D46*12 -> 57885.554 | G91: =G90+F91 -> 326811.91 | H91: =B91/(1+$B$15)^(A91-$A$78) -> 19625.157 | I91: =D91/(1+$B$15)^(A91-$A$78) -> 28035.938 | J91: =F91/(1+$B$15)^(A91-$A$78) -> 34764.563 | K91: =K90+H91 -> 302480.42 | L91: =L90+I91 -> 267609.18 | M91: =M90+J91 -> 216369.17 | N91: =$N$78/(1+$B$15)^(A91-$A$78) -> 600.57409 | O91: =$O$78*(1+$B$14)^(A91-$A$78) -> 1665.0735
A92: 76 | B92: =B47*12 -> 33494.262 | C92: =C91+B92 -> 425072.74 | D92: =C47*12 -> 47848.945 | E92: =E91+D92 -> 429246.46 | F92: =D47*12 -> 59332.692 | G92: =G91+F92 -> 386144.6 | H92: =B92/(1+$B$15)^(A92-$A$78) -> 19342.102 | I92: =D92/(1+$B$15)^(A92-$A$78) -> 27631.574 | J92: =F92/(1+$B$15)^(A92-$A$78) -> 34263.151 | K92: =K91+H92 -> 321822.52 | L92: =L91+I92 -> 295240.75 | M92: =M91+J92 -> 250632.32 | N92: =$N$78/(1+$B$15)^(A92-$A$78) -> 577.47508 | O92: =$O$78*(1+$B$14)^(A92-$A$78) -> 1731.6764
A93: 77 | B93: =B48*12 -> 34331.618 | C93: =C92+B93 -> 459404.35 | D93: =C48*12 -> 49045.169 | E93: =E92+D93 -> 478291.62 | F93: =D48*12 -> 60816.01 | G93: =G92+F93 -> 446960.61 | H93: =B93/(1+$B$15)^(A93-$A$78) -> 19063.129 | I93: =D93/(1+$B$15)^(A93-$A$78) -> 27233.041 | J93: =F93/(1+$B$15)^(A93-$A$78) -> 33768.971 | K93: =K92+H93 -> 340885.65 | L93: =L92+I93 -> 322473.79 | M93: =M92+J93 -> 284401.3 | N93: =$N$78/(1+$B$15)^(A93-$A$78) -> 555.2645 | O93: =$O$78*(1+$B$14)^(A93-$A$78) -> 1800.9435
A94: 78 | B94: =B49*12 -> 35189.909 | C94: =C93+B94 -> 494594.26 | D94: =C49*12 -> 50271.298 | E94: =E93+D94 -> 528562.92 | F94: =D49*12 -> 62336.41 | G94: =G93+F94 -> 509297.02 | H94: =B94/(1+$B$15)^(A94-$A$78) -> 18788.18 | I94: =D94/(1+$B$15)^(A94-$A$78) -> 26840.257 | J94: =F94/(1+$B$15)^(A94-$A$78) -> 33281.919 | K94: =K93+H94 -> 359673.83 | L94: =L93+I94 -> 349314.05 | M94: =M93+J94 -> 317683.21 | N94: =$N$78/(1+$B$15)^(A94-$A$78) -> 533.90818 | O94: =$O$78*(1+$B$14)^(A94-$A$78) -> 1872.9812
A95: 79 | B95: =B50*12 -> 36069.657 | C95: =C94+B95 -> 530663.92 | D95: =C50*12 -> 51528.081 | E95: =E94+D95 -> 580091 | F95: =D50*12 -> 63894.82 | G95: =G94+F95 -> 573191.84 | H95: =B95/(1+$B$15)^(A95-$A$78) -> 18517.197 | I95: =D95/(1+$B$15)^(A95-$A$78) -> 26453.138 | J95: =F95/(1+$B$15)^(A95-$A$78) -> 32801.891 | K95: =K94+H95 -> 378191.03 | L95: =L94+I95 -> 375767.19 | M95: =M94+J95 -> 350485.11 | N95: =$N$78/(1+$B$15)^(A95-$A$78) -> 513.37325 | O95: =$O$78*(1+$B$14)^(A95-$A$78) -> 1947.9005
A96: 80 | B96: =B51*12 -> 36971.398 | C96: =C95+B96 -> 567635.32 | D96: =C51*12 -> 52816.283 | E96: =E95+D96 -> 632907.29 | F96: =D51*12 -> 65492.191 | G96: =G95+F96 -> 638684.03 | H96: =B96/(1+$B$15)^(A96-$A$78) -> 18250.122 | I96: =D96/(1+$B$15)^(A96-$A$78) -> 26071.602 | J96: =F96/(1+$B$15)^(A96-$A$78) -> 32328.787 | K96: =K95+H96 -> 396441.15 | L96: =L95+I96 -> 401838.79 | M96: =M95+J96 -> 382813.89 | N96: =$N$78/(1+$B$15)^(A96-$A$78) -> 493.62812 | O96: =$O$78*(1+$B$14)^(A96-$A$78) -> 2025.8165
A97: 81 | B97: =B52*12 -> 37895.683 | C97: =C96+B97 -> 605531 | D97: =C52*12 -> 54136.69 | E97: =E96+D97 -> 687043.98 | F97: =D52*12 -> 67129.495 | G97: =G96+F97 -> 705813.53 | H97: =B97/(1+$B$15)^(A97-$A$78) -> 17986.899 | I97: =D97/(1+$B$15)^(A97-$A$78) -> 25695.57 | J97: =F97/(1+$B$15)^(A97-$A$78) -> 31862.506 | K97: =K96+H97 -> 414428.05 | L97: =L96+I97 -> 427534.36 | M97: =M96+J97 -> 414676.4 | N97: =$N$78/(1+$B$15)^(A97-$A$78) -> 474.64242 | O97: =$O$78*(1+$B$14)^(A97-$A$78) -> 2106.8492
A98: 82 | B98: =B53*12 -> 38843.075 | C98: =C97+B98 -> 644374.07 | D98: =C53*12 -> 55490.107 | E98: =E97+D98 -> 742534.08 | F98: =D53*12 -> 68807.733 | G98: =G97+F98 -> 774621.26 | H98: =B98/(1+$B$15)^(A98-$A$78) -> 17727.472 | I98: =D98/(1+$B$15)^(A98-$A$78) -> 25324.961 | J98: =F98/(1+$B$15)^(A98-$A$78) -> 31402.951 | K98: =K97+H98 -> 432155.52 | L98: =L97+I98 -> 452859.32 | M98: =M97+J98 -> 446079.35 | N98: =$N$78/(1+$B$15)^(A98-$A$78) -> 456.38695 | O98: =$O$78*(1+$B$14)^(A98-$A$78) -> 2191.1231
... A116: 100 | B116: =B71*12 -> 60581.941 | C116: =C115+B116 -> 1535667.6 | D116: =C71*12 -> 86545.629 | E116: =E115+D116 -> 2015810.5 | F116: =D71*12 -> 107316.58 | G116: =G115+F116 -> 2353484 | H116: =B116/(1+$B$15)^(A116-$A$78) -> 13648.229 | I116: =D116/(1+$B$15)^(A116-$A$78) -> 19497.469 | J116: =F116/(1+$B$15)^(A116-$A$78) -> 24176.862 | K116: =K115+H116 -> 710903.85 | L116: =L115+I116 -> 851071.22 | M116: =M115+J116 -> 939862.1 | N116: =$N$78/(1+$B$15)^(A116-$A$78) -> 225.28543 | O116: =$O$78*(1+$B$14)^(A116-$A$78) -> 4438.8135
L118: ="Total payout with yearly cost of delaying, Cola of " & B13*100 & "% Rate of Return = 0 %, Breakeven Age "&X12 -> Total payout with yearly cost of delaying, Cola of 2.5% Rate of Return = 0 %, Breakeven Age 85
A122: Age | B122: 62, yearly benefit with cola | C122: 62, benefit->total | D122: 67, cola, total | E122: 70, cola, invest total
A123: 62 | B123: =B78 -> 23704.8 | C123: =B123 -> 23704.8 | D123: =-B123 -> -23704.8 | E123: =-B123 -> -23704.8
A124: 63 | B124: =B79 -> 24297.42 | C124: =C123+B124 -> 48002.22 | D124: =-B124+D123 -> -48002.22 | E124: =E123-B124 -> -48002.22
A125: 64 | B125: =B80 -> 24904.855 | C125: =C124+B125 -> 72907.075 | D125: =-B125+D124 -> -72907.075 | E125: =E124-B125 -> -72907.075
A126: 65 | B126: =B81 -> 25527.477 | C126: =C125+B126 -> 98434.552 | D126: =-B126+D125 -> -98434.552 | E126: =E125-B126 -> -98434.552
A127: 66 | B127: =B82 -> 26165.664 | C127: =C126+B127 -> 124600.22 | D127: =-B127+D126 -> -124600.22 | E127: =E126-B127 -> -124600.22
A128: 67 | B128: =B83 -> 26819.805 | C128: =C127+B128 -> 151420.02 | D128: =D83+D127 -> -86286.208 | E128: =E127-B128 -> -151420.02
A129: 68 | B129: =B84 -> 27490.301 | C129: =C128+B129 -> 178910.32 | D129: =D84+D128 -> -47014.351 | E129: =E128-B129 -> -178910.32
A130: 69 | B130: =B85 -> 28177.558 | C130: =C129+B130 -> 207087.88 | D130: =D85+D129 -> -6760.6962 | E130: =E129-B130 -> -207087.88
A131: 70 | B131: =B86 -> 28881.997 | C131: =C130+B131 -> 235969.88 | D131: =D86+D130 -> 34499.3 | E131: =E130+F86 -> -155925.49
A132: 71 | B132: =B87 -> 29604.047 | C132: =C131+B132 -> 265573.92 | D132: =D87+D131 -> 76790.795 | E132: =E131+F87 -> -103484.03
A133: 72 | B133: =B88 -> 30344.148 | C133: =C132+B133 -> 295918.07 | D133: =D88+D132 -> 120139.58 | E133: =E132+F88 -> -49731.54
A134: 73 | B134: =B89 -> 31102.752 | C134: =C133+B134 -> 327020.82 | D134: =D89+D133 -> 164572.08 | E134: =E133+F89 -> 5364.7632
A135: 74 | B135: =B90 -> 31880.321 | C135: =C134+B135 -> 358901.14 | D135: =D90+D134 -> 210115.4 | E135: =E134+F90 -> 61838.474
A136: 75 | B136: =B91 -> 32677.329 | C136: =C135+B136 -> 391578.47 | D136: =D91+D135 -> 256797.29 | E136: =E135+F91 -> 119724.03
A137: 76 | B137: =B92 -> 33494.262 | C137: =C136+B137 -> 425072.74 | D137: =D92+D136 -> 304646.24 | E137: =E136+F92 -> 179056.72
A138: 77 | B138: =B93 -> 34331.618 | C138: =C137+B138 -> 459404.35 | D138: =D93+D137 -> 353691.41 | E138: =E137+F93 -> 239872.73
A139: 78 | B139: =B94 -> 35189.909 | C139: =C138+B139 -> 494594.26 | D139: =D94+D138 -> 403962.71 | E139: =E138+F94 -> 302209.14
A140: 79 | B140: =B95 -> 36069.657 | C140: =C139+B140 -> 530663.92 | D140: =D95+D139 -> 455490.79 | E140: =E139+F95 -> 366103.96
A141: 80 | B141: =B96 -> 36971.398 | C141: =C140+B141 -> 567635.32 | D141: =D96+D140 -> 508307.07 | E141: =E140+F96 -> 431596.15
A142: 81 | B142: =B97 -> 37895.683 | C142: =C141+B142 -> 605531 | D142: =D97+D141 -> 562443.76 | E142: =E141+F97 -> 498725.65
... A161: 100 | B161: =B116 -> 60581.941 | C161: =C160+B161 -> 1535667.6 | D161: =D116+D160 -> 1891210.3 | E161: =E160+F116 -> 2146396.1
A166: Age | B166: 62, yearly benefit with cola | C166: 62, benefit->total | D166: 67, cola, total | E166: 70, cola, invest total
A167: 62 | B167: =B78 -> 23704.8 | C167: =B16*(1+$B$14) -> 260000 | D167: =(B16-B167)*(1+B14) -> 235347.01 | E167: =(B16-B167)*(1+B14) -> 235347.01
A168: 63 | B168: =B79 -> 24297.42 | C168: =C167*(1+$B$14) -> 270400 | D168: =(D167-B168)*(1+$B$14) -> 219491.57 | E168: =(E167-B168)*(1+$B$14) -> 219491.57
A169: 64 | B169: =B80 -> 24904.855 | C169: =C168*(1+$B$14) -> 281216 | D169: =(D168-B169)*(1+$B$14) -> 202370.18 | E169: =(E168-B169)*(1+$B$14) -> 202370.18
A170: 65 | B170: =B81 -> 25527.477 | C170: =C169*(1+$B$14) -> 292464.64 | D170: =(D169-B170)*(1+$B$14) -> 183916.42 | E170: =(E169-B170)*(1+$B$14) -> 183916.42
A171: 66 | B171: =B82 -> 26165.664 | C171: =C170*(1+$B$14) -> 304163.23 | D171: =(D170-B171)*(1+$B$14) -> 164060.78 | E171: =(E170-B171)*(1+$B$14) -> 164060.78
A172: 67 | B172: =B83 -> 26819.805 | C172: =C171*(1+$B$14) -> 316329.75 | D172: =(D171)*(1+$B$14)+(D83-B172) -> 182117.42 | E172: =(E171-B172)*(1+$B$14) -> 142730.62
A173: 68 | B173: =B84 -> 27490.301 | C173: =C172*(1+$B$14) -> 328982.94 | D173: =(D172)*(1+$B$14)+(D84-B173) -> 201183.67 | E173: =(E172-B173)*(1+$B$14) -> 119849.93
A174: 69 | B174: =B85 -> 28177.558 | C174: =C173*(1+$B$14) -> 342142.26 | D174: =(D173)*(1+$B$14)+(D85-B174) -> 221307.11 | E174: =(E173-B174)*(1+$B$14) -> 95339.265
A175: 70 | B175: =B86 -> 28881.997 | C175: =C174*(1+$B$14) -> 355827.95 | D175: =(D174)*(1+$B$14)+(D86-B175) -> 242537.4 | E175: =(E174)*(1+$B$14)+(F86-B175) -> 121433.23
A176: 71 | B176: =B87 -> 29604.047 | C176: =C175*(1+$B$14) -> 370061.07 | D176: =(D175)*(1+$B$14)+(D87-B176) -> 264926.34 | E176: =(E175)*(1+$B$14)+(F87-B176) -> 149127.97
A177: 72 | B177: =B88 -> 30344.148 | C177: =C176*(1+$B$14) -> 384863.51 | D177: =(D176)*(1+$B$14)+(D88-B177) -> 288528.03 | E177: =(E176)*(1+$B$14)+(F88-B177) -> 178501.43
A178: 73 | B178: =B89 -> 31102.752 | C178: =C177*(1+$B$14) -> 400258.05 | D178: =(D177)*(1+$B$14)+(D89-B178) -> 313398.9 | E178: =(E177)*(1+$B$14)+(F89-B178) -> 209635.04
...

Sheet Frank and Bill
A2: Full Retirment Age Benefit | B2: =Main!B11 -> 2822
A3: Life Expectancy | B3: =Main!B12 -> 22
A4: Cola | B4: =Main!B13 -> 0.025 | D4: Average since 1975 = | E4: ='SS Benefit Cal'!F3 -> 3.7294118 | G4: Starting retirement funds to draw from = | H4: 250000
A5: Rate of Return | B5: 0.04 | D5: AverageCPI since 1914 | E5: =Main!E12 -> 0.03263964 | G5: Married Frank and Bill age of death | H5: 80
A6: Discount Rate | B6: =Main!B15 -> 0.04
A7: Spouse Full retirement Benefit | B7: 2500 | G7: =L7 -> Single Break even Age @ Rate of Return = 4 % | H7: {=_xlfn.XLOOKUP(TRUE,N26:N64<=O26:O64,A26:A64,"No crossover")} -> 81 | L7: ="Single Break even Age @ Rate of Return = " & $B$5*100 & " %" -> Single Break even Age @ Rate of Return = 4 %
A9: Yearly expense | B9: 23704
G11: Spouse
A12: AGE | B12: Monthy benefit | C12: % change | D12: year2year change | F12: AGE | G12: Monthy benefit | H12: % change | I12: year2year change | L12: ="Compare Saving of single Frank and Bill at rate of return of " & B5*100 & "% and Cola of " & B4*100 & "% " & "Initial Yearly Expenses = $" & B9 -> Compare Saving of single Frank and Bill at rate of return of 4% and Cola of 2.5% Initial Yearly Expenses = $23704
A13: 62 | B13: =$B$2*C13 -> 1975.4 | C13: 0.7 | F13: 62 | G13: =$B$7*H13 -> 1750 | H13: 0.7
A14: 63 | B14: =$B$2*C14 -> 2116.5 | C14: 0.75 | D14: =(B14-B13)/B13 -> 0.071428571 | F14: 63 | G14: =$B$7*H14 -> 1875 | H14: 0.75 | I14: =(G14-G13)/G13 -> 0.071428571
A15: 64 | B15: =$B$2*C15 -> 2257.6 | C15: 0.8 | D15: =(B15-B14)/B14 -> 0.066666667 | F15: 64 | G15: =$B$7*H15 -> 2000 | H15: 0.8 | I15: =(G15-G14)/G14 -> 0.066666667
A16: 65 | B16: =$B$2*C16 -> 2446.674 | C16: 0.867 | D16: =(B16-B15)/B15 -> 0.08375 | F16: 65 | G16: =$B$7*H16 -> 2167.5 | H16: 0.867 | I16: =(G16-G15)/G15 -> 0.08375
A17: 66 | B17: =$B$2*C17 -> 2632.926 | C17: 0.933 | D17: =(B17-B16)/B16 -> 0.076124567 | F17: 66 | G17: =$B$7*H17 -> 2332.5 | H17: 0.933 | I17: =(G17-G16)/G16 -> 0.076124567
A18: 67 | B18: =$B$2*C18 -> 2822 | C18: 1 | D18: =(B18-B17)/B17 -> 0.071811361 | F18: 67 | G18: =B7 -> 2500 | H18: 1 | I18: =(G18-G17)/G17 -> 0.071811361
A19: 68 | B19: =$B$2*C19 -> 3047.76 | C19: 1.08 | D19: =(B19-B18)/B18 -> 0.08 | F19: 68 | G19: =$B$7*H19 -> 2700 | H19: 1.08 | I19: =(G19-G18)/G18 -> 0.08
A20: 69 | B20: =$B$2*C20 -> 3273.52 | C20: 1.16 | D20: =(B20-B19)/B19 -> 0.074074074 | F20: 69 | G20: =$B$7*H20 -> 2900 | H20: 1.16 | I20: =(G20-G19)/G19 -> 0.074074074
A21: 70 | B21: =$B$2*C21 -> 3499.28 | C21: 1.24 | D21: =(B21-B20)/B20 -> 0.068965517 | F21: 70 | G21: =$B$7*H21 -> 3100 | H21: 1.24 | I21: =(G21-G20)/G20 -> 0.068965517
A24: Frank | G24: Bill | N24: Frank | O24: Bill
A25: Age | B25: Monthly benefit | C25: Yearly Benefit | D25: Yearly Expenses | E25: expense vs income | F25: Savings | G25: Age | H25: Monthly benefit | I25: Yearly Benefit | J25: Yearly Expenses | K25: Change to savings | L25: Saving | M25: Age | N25: Savings | O25: Savings
A26: 62 | B26: =B13 -> 1975.4 | C26: =B26*12 -> 23704.8 | D26: =B9 -> 23704 | E26: =C26-D26 -> 0.8 | F26: =$H$4*(1+$B$5) -> 260000 | G26: 62 | H26: 0 | I26: =H26*12 -> 0 | J26: =B9 -> 23704 | K26: =I26-J26 -> -23704 | L26: =($H$4)*(1+$B$5)+K26 -> 236296 | M26: 62 | N26: =F26 -> 260000 | O26: =L26 -> 236296
A27: 63 | B27: =B26*(1+$B$4) -> 2024.785 | C27: =B27*12 -> 24297.42 | D27: =D26*(1+$B$4) -> 24296.6 | E27: =C27-D27 -> 0.82 | F27: =F26*(1+$B$5)+E27 -> 270400.82 | G27: 63 | H27: 0 | I27: =H27*12 -> 0 | J27: =J26*(1+$B$4) -> 24296.6 | K27: =I27-J27 -> -24296.6 | L27: =(L26)*(1+$B$5)+K27 -> 221451.24 | M27: 63 | N27: =F27 -> 270400.82 | O27: =L27 -> 221451.24
A28: 64 | B28: =B27*(1+$B$4) -> 2075.4046 | C28: =B28*12 -> 24904.855 | D28: =D27*(1+$B$4) -> 24904.015 | E28: =C28-D28 -> 0.8405 | F28: =F27*(1+$B$5)+E28 -> 281217.69 | G28: 64 | H28: 0 | I28: =H28*12 -> 0 | J28: =J27*(1+$B$4) -> 24904.015 | K28: =I28-J28 -> -24904.015 | L28: =(L27)*(1+$B$5)+K28 -> 205405.27 | M28: 64 | N28: =F28 -> 281217.69 | O28: =L28 -> 205405.27
A29: 65 | B29: =B28*(1+$B$4) -> 2127.2897 | C29: =B29*12 -> 25527.477 | D29: =D28*(1+$B$4) -> 25526.615 | E29: =C29-D29 -> 0.8615125 | F29: =F28*(1+$B$5)+E29 -> 292467.26 | G29: 65 | H29: 0 | I29: =H29*12 -> 0 | J29: =J28*(1+$B$4) -> 25526.615 | K29: =I29-J29 -> -25526.615 | L29: =(L28)*(1+$B$5)+K29 -> 188094.87 | M29: 65 | N29: =F29 -> 292467.26 | O29: =L29 -> 188094.87
A30: 66 | B30: =B29*(1+$B$4) -> 2180.472 | C30: =B30*12 -> 26165.664 | D30: =D29*(1+$B$4) -> 26164.781 | E30: =C30-D30 -> 0.88305031 | F30: =F29*(1+$B$5)+E30 -> 304166.84 | G30: 66 | H30: 0 | I30: =H30*12 -> 0 | J30: =J29*(1+$B$4) -> 26164.781 | K30: =I30-J30 -> -26164.781 | L30: =(L29)*(1+$B$5)+K30 -> 169453.88 | M30: 66 | N30: =F30 -> 304166.84 | O30: =L30 -> 169453.88
A31: 67 | B31: =B30*(1+$B$4) -> 2234.9838 | C31: =B31*12 -> 26819.805 | D31: =D30*(1+$B$4) -> 26818.9 | E31: =C31-D31 -> 0.90512657 | F31: =F30*(1+$B$5)+E31 -> 316334.41 | G31: 67 | H31: 0 | I31: =H31*12 -> 0 | J31: =J30*(1+$B$4) -> 26818.9 | K31: =I31-J31 -> -26818.9 | L31: =(L30)*(1+$B$5)+K31 -> 149413.14 | M31: 67 | N31: =F31 -> 316334.41 | O31: =L31 -> 149413.14
A32: 68 | B32: =B31*(1+$B$4) -> 2290.8584 | C32: =B32*12 -> 27490.301 | D32: =D31*(1+$B$4) -> 27489.373 | E32: =C32-D32 -> 0.92775473 | F32: =F31*(1+$B$5)+E32 -> 328988.72 | G32: 68 | H32: 0 | I32: =H32*12 -> 0 | J32: =J31*(1+$B$4) -> 27489.373 | K32: =I32-J32 -> -27489.373 | L32: =(L31)*(1+$B$5)+K32 -> 127900.29 | M32: 68 | N32: =F32 -> 328988.72 | O32: =L32 -> 127900.29
A33: 69 | B33: =B32*(1+$B$4) -> 2348.1298 | C33: =B33*12 -> 28177.558 | D33: =D32*(1+$B$4) -> 28176.607 | E33: =C33-D33 -> 0.9509486 | F33: =F32*(1+$B$5)+E33 -> 342149.22 | G33: 69 | H33: 0 | I33: =H33*12 -> 0 | J33: =J32*(1+$B$4) -> 28176.607 | K33: =I33-J33 -> -28176.607 | L33: =(L32)*(1+$B$5)+K33 -> 104839.7 | M33: 69 | N33: =F33 -> 342149.22 | O33: =L33 -> 104839.7
A34: 70 | B34: =B33*(1+$B$4) -> 2406.8331 | C34: =B34*12 -> 28881.997 | D34: =D33*(1+$B$4) -> 28881.022 | E34: =C34-D34 -> 0.97472232 | F34: =F33*(1+$B$5)+E34 -> 355836.16 | G34: 70 | H34: =B21*(1+B4)^(70-62) -> 4263.5329 | I34: =H34*12 -> 51162.395 | J34: =J33*(1+$B$4) -> 28881.022 | K34: =I34-J34 -> 22281.372 | L34: =(L33)*(1+$B$5)+K34 -> 131314.66 | M34: 70 | N34: =F34 -> 355836.16 | O34: =L34 -> 131314.66
A35: 71 | B35: =B34*(1+$B$4) -> 2467.0039 | C35: =B35*12 -> 29604.047 | D35: =D34*(1+$B$4) -> 29603.048 | E35: =C35-D35 -> 0.99909038 | F35: =F34*(1+$B$5)+E35 -> 370070.61 | G35: 71 | H35: =H34*(1+$B$4) -> 4370.1212 | I35: =H35*12 -> 52441.455 | J35: =J34*(1+$B$4) -> 29603.048 | K35: =I35-J35 -> 22838.407 | L35: =(L34)*(1+$B$5)+K35 -> 159405.65 | M35: 71 | N35: =F35 -> 370070.61 | O35: =L35 -> 159405.65
A36: 72 | B36: =B35*(1+$B$4) -> 2528.679 | C36: =B36*12 -> 30344.148 | D36: =D35*(1+$B$4) -> 30343.124 | E36: =C36-D36 -> 1.0240676 | F36: =F35*(1+$B$5)+E36 -> 384874.46 | G36: 72 | H36: =H35*(1+$B$4) -> 4479.3742 | I36: =H36*12 -> 53752.491 | J36: =J35*(1+$B$4) -> 30343.124 | K36: =I36-J36 -> 23409.367 | L36: =(L35)*(1+$B$5)+K36 -> 189191.24 | M36: 72 | N36: =F36 -> 384874.46 | O36: =L36 -> 189191.24
A37: 73 | B37: =B36*(1+$B$4) -> 2591.896 | C37: =B37*12 -> 31102.752 | D37: =D36*(1+$B$4) -> 31101.702 | E37: =C37-D37 -> 1.0496693 | F37: =F36*(1+$B$5)+E37 -> 400270.48 | G37: 73 | H37: =H36*(1+$B$4) -> 4591.3586 | I37: =H37*12 -> 55096.303 | J37: =J36*(1+$B$4) -> 31101.702 | K37: =I37-J37 -> 23994.601 | L37: =(L36)*(1+$B$5)+K37 -> 220753.49 | M37: 73 | N37: =F37 -> 400270.48 | O37: =L37 -> 220753.49
A38: 74 | B38: =B37*(1+$B$4) -> 2656.6934 | C38: =B38*12 -> 31880.321 | D38: =D37*(1+$B$4) -> 31879.245 | E38: =C38-D38 -> 1.0759111 | F38: =F37*(1+$B$5)+E38 -> 416282.38 | G38: 74 | H38: =H37*(1+$B$4) -> 4706.1426 | I38: =H38*12 -> 56473.711 | J38: =J37*(1+$B$4) -> 31879.245 | K38: =I38-J38 -> 24594.466 | L38: =(L37)*(1+$B$5)+K38 -> 254178.1 | M38: 74 | N38: =F38 -> 416282.38 | O38: =L38 -> 254178.1
A39: 75 | B39: =B38*(1+$B$4) -> 2723.1107 | C39: =B39*12 -> 32677.329 | D39: =D38*(1+$B$4) -> 32676.226 | E39: =C39-D39 -> 1.1028088 | F39: =F38*(1+$B$5)+E39 -> 432934.78 | G39: 75 | H39: =H38*(1+$B$4) -> 4823.7961 | I39: =H39*12 -> 57885.554 | J39: =J38*(1+$B$4) -> 32676.226 | K39: =I39-J39 -> 25209.328 | L39: =(L38)*(1+$B$5)+K39 -> 289554.55 | M39: 75 | N39: =F39 -> 432934.78 | O39: =L39 -> 289554.55
A40: 76 | B40: =B39*(1+$B$4) -> 2791.1885 | C40: =B40*12 -> 33494.262 | D40: =D39*(1+$B$4) -> 33493.131 | E40: =C40-D40 -> 1.1303791 | F40: =F39*(1+$B$5)+E40 -> 450253.3 | G40: 76 | H40: =H39*(1+$B$4) -> 4944.391 | I40: =H40*12 -> 59332.692 | J40: =J39*(1+$B$4) -> 33493.131 | K40: =I40-J40 -> 25839.561 | L40: =(L39)*(1+$B$5)+K40 -> 326976.29 | M40: 76 | N40: =F40 -> 450253.3 | O40: =L40 -> 326976.29
A41: 77 | B41: =B40*(1+$B$4) -> 2860.9682 | C41: =B41*12 -> 34331.618 | D41: =D40*(1+$B$4) -> 34330.46 | E41: =C41-D41 -> 1.1586385 | F41: =F40*(1+$B$5)+E41 -> 468264.59 | G41: 77 | H41: =H40*(1+$B$4) -> 5068.0008 | I41: =H41*12 -> 60816.01 | J41: =J40*(1+$B$4) -> 34330.46 | K41: =I41-J41 -> 26485.55 | L41: =(L40)*(1+$B$5)+K41 -> 366540.9 | M41: 77 | N41: =F41 -> 468264.59 | O41: =L41 -> 366540.9
A42: 78 | B42: =B41*(1+$B$4) -> 2932.4924 | C42: =B42*12 -> 35189.909 | D42: =D41*(1+$B$4) -> 35188.721 | E42: =C42-D42 -> 1.1876045 | F42: =F41*(1+$B$5)+E42 -> 486996.36 | G42: 78 | H42: =H41*(1+$B$4) -> 5194.7008 | I42: =H42*12 -> 62336.41 | J42: =J41*(1+$B$4) -> 35188.721 | K42: =I42-J42 -> 27147.689 | L42: =(L41)*(1+$B$5)+K42 -> 408350.22 | M42: 78 | N42: =F42 -> 486996.36 | O42: =L42 -> 408350.22
A43: 79 | B43: =B42*(1+$B$4) -> 3005.8047 | C43: =B43*12 -> 36069.657 | D43: =D42*(1+$B$4) -> 36068.439 | E43: =C43-D43 -> 1.2172946 | F43: =F42*(1+$B$5)+E43 -> 506477.43 | G43: 79 | H43: =H42*(1+$B$4) -> 5324.5683 | I43: =H43*12 -> 63894.82 | J43: =J42*(1+$B$4) -> 36068.439 | K43: =I43-J43 -> 27826.381 | L43: =(L42)*(1+$B$5)+K43 -> 452510.61 | M43: 79 | N43: =F43 -> 506477.43 | O43: =L43 -> 452510.61
A44: 80 | B44: =B43*(1+$B$4) -> 3080.9498 | C44: =B44*12 -> 36971.398 | D44: =D43*(1+$B$4) -> 36970.15 | E44: =C44-D44 -> 1.247727 | F44: =F43*(1+$B$5)+E44 -> 526737.78 | G44: 80 | H44: =H43*(1+$B$4) -> 5457.6826 | I44: =H44*12 -> 65492.191 | J44: =J43*(1+$B$4) -> 36970.15 | K44: =I44-J44 -> 28522.04 | L44: =(L43)*(1+$B$5)+K44 -> 499133.08 | M44: 80 | N44: =F44 -> 526737.78 | O44: =L44 -> 499133.08
A45: 81 | B45: =B44*(1+$B$4) -> 3157.9736 | C45: =B45*12 -> 37895.683 | D45: =D44*(1+$B$4) -> 37894.404 | E45: =C45-D45 -> 1.2789201 | F45: =F44*(1+$B$5)+E45 -> 547808.57 | G45: 81 | H45: =H44*(1+$B$4) -> 5594.1246 | I45: =H45*12 -> 67129.495 | J45: =J44*(1+$B$4) -> 37894.404 | K45: =I45-J45 -> 29235.091 | L45: =(L44)*(1+$B$5)+K45 -> 548333.49 | M45: 81 | N45: =F45 -> 547808.57 | O45: =L45 -> 548333.49
A46: 82 | B46: =B45*(1+$B$4) -> 3236.9229 | C46: =B46*12 -> 38843.075 | D46: =D45*(1+$B$4) -> 38841.764 | E46: =C46-D46 -> 1.3108932 | F46: =F45*(1+$B$5)+E46 -> 569722.22 | G46: 82 | H46: =H45*(1+$B$4) -> 5733.9777 | I46: =H46*12 -> 68807.733 | J46: =J45*(1+$B$4) -> 38841.764 | K46: =I46-J46 -> 29965.969 | L46: =(L45)*(1+$B$5)+K46 -> 600232.8 | M46: 82 | N46: =F46 -> 569722.22 | O46: =L46 -> 600232.8
... A64: 100 | B64: =B63*(1+$B$4) -> 5048.495 | C64: =B64*12 -> 60581.941 | D64: =D63*(1+$B$4) -> 60579.896 | E64: =C64-D64 -> 2.0445459 | F64: =F63*(1+$B$5)+E64 -> 1154194.4 | G64: 100 | H64: =H63*(1+$B$4) -> 8943.0484 | I64: =H64*12 -> 107316.58 | J64: =J63*(1+$B$4) -> 60579.896 | K64: =I64-J64 -> 46736.684 | L64: =(L63)*(1+$B$5)+K64 -> 2170501 | M64: 100 | N64: =F64 -> 1154194.4 | O64: =L64 -> 2170501
A75: Frank | J75: Bill
A76: Age | B76: Montly benefit | C76: Yearly Benefit | D76: Spouse Montly benefit | E76: Spouse Yearly Benefit | F76: Yearly Expenses | G76: expenses vs invome | H76: Saving | J76: Age | K76: Montly benefit | L76: Yearly Benefit | M76: Spouse Monthly Benefit | N76: Spouse Yearly Benefit | O76: Yearly Expenses | P76: Expenses vs Income | Q76: Saving
A77: 62 | B77: =B13 -> 1975.4 | C77: =B26*12 -> 23704.8 | D77: =$G$16 -> 2167.5 | E77: =D77*12 -> 26010 | F77: =$B$9 -> 23704 | G77: =(E77+C77)-F77 -> 26010.8 | H77: =$H$4*(1+$B$5)+G77 -> 286010.8 | J77: 62 | K77: 0 | L77: =K77*12 -> 0 | M77: =D77 -> 2167.5 | N77: =M77*12 -> 26010 | O77: =B9 -> 23704 | P77: =(L77+N77)-O77 -> 2306 | Q77: =($H$4)*(1+$B$5)+N77+P77-C77 -> 264611.2 | X77: ="Compare Saving of Married Frank and Bill at rate of return of " & B5*100 & "% and Cola of " & B4*100 & "% " & "Yearly Expenses = $" & B9 -> Compare Saving of Married Frank and Bill at rate of return of 4% and Cola of 2.5% Yearly Expenses = $23704
A78: 63 | B78: =B77*(1+$B$4) -> 2024.785 | C78: =B27*12 -> 24297.42 | D78: =D77*(1+$B$4) -> 2221.6875 | E78: =D78*12 -> 26660.25 | F78: =F77*(1+$B$4) -> 24296.6 | G78: =(E78+C78)-F78 -> 26661.07 | H78: =H77*(1+$B$5)+G78 -> 324112.3 | J78: 63 | K78: 0 | L78: =K78*12 -> 0 | M78: =M77*(1+$B$4) -> 2221.6875 | N78: =M78*12 -> 26660.25 | O78: =O77*(1+$B$4) -> 24296.6 | P78: =(L78+N78)-O78 -> 2363.65 | Q78: =Q77*(1+$B$5)+P78 -> 277559.3
A79: 64 | B79: =B78*(1+$B$4) -> 2075.4046 | C79: =B28*12 -> 24904.855 | D79: =D78*(1+$B$4) -> 2277.2297 | E79: =D79*12 -> 27326.756 | F79: =F78*(1+$B$4) -> 24904.015 | G79: =(E79+C79)-F79 -> 27327.597 | H79: =H78*(1+$B$5)+G79 -> 364404.39 | J79: 64 | K79: 0 | L79: =K79*12 -> 0 | M79: =M78*(1+$B$4) -> 2277.2297 | N79: =M79*12 -> 27326.756 | O79: =O78*(1+$B$4) -> 24904.015 | P79: =(L79+N79)-O79 -> 2422.7413 | Q79: =Q78*(1+$B$5)+P79 -> 291084.41
A80: 65 | B80: =B79*(1+$B$4) -> 2127.2897 | C80: =B29*12 -> 25527.477 | D80: =D79*(1+$B$4) -> 2334.1604 | E80: =D80*12 -> 28009.925 | F80: =F79*(1+$B$4) -> 25526.615 | G80: =(E80+C80)-F80 -> 28010.787 | H80: =H79*(1+$B$5)+G80 -> 406991.35 | J80: 65 | K80: 0 | L80: =K80*12 -> 0 | M80: =M79*(1+$B$4) -> 2334.1604 | N80: =M80*12 -> 28009.925 | O80: =O79*(1+$B$4) -> 25526.615 | P80: =(L80+N80)-O80 -> 2483.3098 | Q80: =Q79*(1+$B$5)+P80 -> 305211.1
A81: 66 | B81: =B80*(1+$B$4) -> 2180.472 | C81: =B30*12 -> 26165.664 | D81: =D80*(1+$B$4) -> 2392.5144 | E81: =D81*12 -> 28710.173 | F81: =F80*(1+$B$4) -> 26164.781 | G81: =(E81+C81)-F81 -> 28711.056 | H81: =H80*(1+$B$5)+G81 -> 451982.06 | J81: 66 | K81: 0 | L81: =K81*12 -> 0 | M81: =M80*(1+$B$4) -> 2392.5144 | N81: =M81*12 -> 28710.173 | O81: =O80*(1+$B$4) -> 26164.781 | P81: =(L81+N81)-O81 -> 2545.3925 | Q81: =Q80*(1+$B$5)+P81 -> 319964.93
A82: 67 | B82: =B81*(1+$B$4) -> 2234.9838 | C82: =B31*12 -> 26819.805 | D82: =D81*(1+$B$4) -> 2452.3273 | E82: =D82*12 -> 29427.928 | F82: =F81*(1+$B$4) -> 26818.9 | G82: =(E82+C82)-F82 -> 29428.833 | H82: =H81*(1+$B$5)+G82 -> 499490.18 | J82: 67 | K82: 0 | L82: =K82*12 -> 0 | M82: =M81*(1+$B$4) -> 2452.3273 | N82: =M82*12 -> 29427.928 | O82: =O81*(1+$B$4) -> 26818.9 | P82: =(L82+N82)-O82 -> 2609.0273 | Q82: =Q81*(1+$B$5)+P82 -> 335372.56
A83: 68 | B83: =B82*(1+$B$4) -> 2290.8584 | C83: =B32*12 -> 27490.301 | D83: =D82*(1+$B$4) -> 2513.6355 | E83: =D83*12 -> 30163.626 | F83: =F82*(1+$B$4) -> 27489.373 | G83: =(E83+C83)-F83 -> 30164.554 | H83: =H82*(1+$B$5)+G83 -> 549634.34 | J83: 68 | K83: 0 | L83: =K83*12 -> 0 | M83: =M82*(1+$B$4) -> 2513.6355 | N83: =M83*12 -> 30163.626 | O83: =O82*(1+$B$4) -> 27489.373 | P83: =(L83+N83)-O83 -> 2674.253 | Q83: =Q82*(1+$B$5)+P83 -> 351461.71
A84: 69 | B84: =B83*(1+$B$4) -> 2348.1298 | C84: =B33*12 -> 28177.558 | D84: =D83*(1+$B$4) -> 2576.4764 | E84: =D84*12 -> 30917.716 | F84: =F83*(1+$B$4) -> 28176.607 | G84: =(E84+C84)-F84 -> 30918.667 | H84: =H83*(1+$B$5)+G84 -> 602538.38 | J84: 69 | K84: 0 | L84: =K84*12 -> 0 | M84: =M83*(1+$B$4) -> 2576.4764 | N84: =M84*12 -> 30917.716 | O84: =O83*(1+$B$4) -> 28176.607 | P84: =(L84+N84)-O84 -> 2741.1093 | Q84: =Q83*(1+$B$5)+P84 -> 368261.29
A85: 70 | B85: =B84*(1+$B$4) -> 2406.8331 | C85: =B34*12 -> 28881.997 | D85: =D84*(1+$B$4) -> 2640.8883 | E85: =D85*12 -> 31690.659 | F85: =F84*(1+$B$4) -> 28881.022 | G85: =(E85+C85)-F85 -> 31691.634 | H85: =H84*(1+$B$5)+G85 -> 658331.55 | J85: 70 | K85: =B21 -> 3499.28 | L85: =K85*12 -> 41991.36 | M85: =M84*(1+$B$4) -> 2640.8883 | N85: =M85*12 -> 31690.659 | O85: =O84*(1+$B$4) -> 28881.022 | P85: =(L85+N85)-O85 -> 44800.997 | Q85: =Q84*(1+$B$5)+P85 -> 427792.74
A86: 71 | B86: =B85*(1+$B$4) -> 2467.0039 | C86: =B35*12 -> 29604.047 | D86: =D85*(1+$B$4) -> 2706.9105 | E86: =D86*12 -> 32482.926 | F86: =F85*(1+$B$4) -> 29603.048 | G86: =(E86+C86)-F86 -> 32483.925 | H86: =H85*(1+$B$5)+G86 -> 717148.74 | J86: 71 | K86: =K85*(1+$B$4) -> 3586.762 | L86: =K86*12 -> 43041.144 | M86: =M85*(1+$B$4) -> 2706.9105 | N86: =M86*12 -> 32482.926 | O86: =O85*(1+$B$4) -> 29603.048 | P86: =(L86+N86)-O86 -> 45921.022 | Q86: =Q85*(1+$B$5)+P86 -> 490825.47
A87: 72 | B87: =B86*(1+$B$4) -> 2528.679 | C87: =B36*12 -> 30344.148 | D87: =D86*(1+$B$4) -> 2774.5832 | E87: =D87*12 -> 33294.999 | F87: =F86*(1+$B$4) -> 30343.124 | G87: =(E87+C87)-F87 -> 33296.023 | H87: =H86*(1+$B$5)+G87 -> 779130.71 | J87: 72 | K87: =K86*(1+$B$4) -> 3676.431 | L87: =K87*12 -> 44117.173 | M87: =M86*(1+$B$4) -> 2774.5832 | N87: =M87*12 -> 33294.999 | O87: =O86*(1+$B$4) -> 30343.124 | P87: =(L87+N87)-O87 -> 47069.048 | Q87: =Q86*(1+$B$5)+P87 -> 557527.54
A88: 73 | B88: =B87*(1+$B$4) -> 2591.896 | C88: =B37*12 -> 31102.752 | D88: =D87*(1+$B$4) -> 2843.9478 | E88: =D88*12 -> 34127.374 | F88: =F87*(1+$B$4) -> 31101.702 | G88: =(E88+C88)-F88 -> 34128.424 | H88: =H87*(1+$B$5)+G88 -> 844424.36 | J88: 73 | K88: =K87*(1+$B$4) -> 3768.3418 | L88: =K88*12 -> 45220.102 | M88: =M87*(1+$B$4) -> 2843.9478 | N88: =M88*12 -> 34127.374 | O88: =O87*(1+$B$4) -> 31101.702 | P88: =(L88+N88)-O88 -> 48245.774 | Q88: =Q87*(1+$B$5)+P88 -> 628074.41
A89: 74 | B89: =B88*(1+$B$4) -> 2656.6934 | C89: =B38*12 -> 31880.321 | D89: =D88*(1+$B$4) -> 2915.0465 | E89: =D89*12 -> 34980.558 | F89: =F88*(1+$B$4) -> 31879.245 | G89: =(E89+C89)-F89 -> 34981.634 | H89: =H88*(1+$B$5)+G89 -> 913182.97 | J89: 74 | K89: =K88*(1+$B$4) -> 3862.5504 | L89: =K89*12 -> 46350.604 | M89: =M88*(1+$B$4) -> 2915.0465 | N89: =M89*12 -> 34980.558 | O89: =O88*(1+$B$4) -> 31879.245 | P89: =(L89+N89)-O89 -> 49451.918 | Q89: =Q88*(1+$B$5)+P89 -> 702649.31
A90: 75 | B90: =B89*(1+$B$4) -> 2723.1107 | C90: =B39*12 -> 32677.329 | D90: =D89*(1+$B$4) -> 2987.9227 | E90: =D90*12 -> 35855.072 | F90: =F89*(1+$B$4) -> 32676.226 | G90: =(E90+C90)-F90 -> 35856.175 | H90: =H89*(1+$B$5)+G90 -> 985566.46 | J90: 75 | K90: =K89*(1+$B$4) -> 3959.1141 | L90: =K90*12 -> 47509.37 | M90: =M89*(1+$B$4) -> 2987.9227 | N90: =M90*12 -> 35855.072 | O90: =O89*(1+$B$4) -> 32676.226 | P90: =(L90+N90)-O90 -> 50688.216 | Q90: =Q89*(1+$B$5)+P90 -> 781443.5
A91: 76 | B91: =B90*(1+$B$4) -> 2791.1885 | C91: =B40*12 -> 33494.262 | D91: =D90*(1+$B$4) -> 3062.6208 | E91: =D91*12 -> 36751.449 | F91: =F90*(1+$B$4) -> 33493.131 | G91: =(E91+C91)-F91 -> 36752.579 | H91: =H90*(1+$B$5)+G91 -> 1061741.7 | J91: 76 | K91: =K90*(1+$B$4) -> 4058.092 | L91: =K91*12 -> 48697.104 | M91: =M90*(1+$B$4) -> 3062.6208 | N91: =M91*12 -> 36751.449 | O91: =O90*(1+$B$4) -> 33493.131 | P91: =(L91+N91)-O91 -> 51955.421 | Q91: =Q90*(1+$B$5)+P91 -> 864656.66
A92: 77 | B92: =B91*(1+$B$4) -> 2860.9682 | C92: =B41*12 -> 34331.618 | D92: =D91*(1+$B$4) -> 3139.1863 | E92: =D92*12 -> 37670.235 | F92: =F91*(1+$B$4) -> 34330.46 | G92: =(E92+C92)-F92 -> 37671.394 | H92: =H91*(1+$B$5)+G92 -> 1141882.8 | J92: 77 | K92: =K91*(1+$B$4) -> 4159.5443 | L92: =K92*12 -> 49914.531 | M92: =M91*(1+$B$4) -> 3139.1863 | N92: =M92*12 -> 37670.235 | O92: =O91*(1+$B$4) -> 34330.46 | P92: =(L92+N92)-O92 -> 53254.307 | Q92: =Q91*(1+$B$5)+P92 -> 952497.23
A93: 78 | B93: =B92*(1+$B$4) -> 2932.4924 | C93: =B42*12 -> 35189.909 | D93: =D92*(1+$B$4) -> 3217.6659 | E93: =D93*12 -> 38611.991 | F93: =F92*(1+$B$4) -> 35188.721 | G93: =(E93+C93)-F93 -> 38613.179 | H93: =H92*(1+$B$5)+G93 -> 1226171.3 | J93: 78 | K93: =K92*(1+$B$4) -> 4263.5329 | L93: =K93*12 -> 51162.395 | M93: =M92*(1+$B$4) -> 3217.6659 | N93: =M93*12 -> 38611.991 | O93: =O92*(1+$B$4) -> 35188.721 | P93: =(L93+N93)-O93 -> 54585.665 | Q93: =Q92*(1+$B$5)+P93 -> 1045182.8
A94: 79 | B94: =B93*(1+$B$4) -> 3005.8047 | C94: =B43*12 -> 36069.657 | D94: =D93*(1+$B$4) -> 3298.1076 | E94: =D94*12 -> 39577.291 | F94: =F93*(1+$B$4) -> 36068.439 | G94: =(E94+C94)-F94 -> 39578.508 | H94: =H93*(1+$B$5)+G94 -> 1314796.6 | J94: 79 | K94: =K93*(1+$B$4) -> 4370.1212 | L94: =K94*12 -> 52441.455 | M94: =M93*(1+$B$4) -> 3298.1076 | N94: =M94*12 -> 39577.291 | O94: =O93*(1+$B$4) -> 36068.439 | P94: =(L94+N94)-O94 -> 55950.306 | Q94: =Q93*(1+$B$5)+P94 -> 1142940.4
A95: 80 | B95: =B94*(1+$B$4) -> 3080.9498 | C95: =B44*12 -> 36971.398 | D95: =D94*(1+$B$4) -> 3380.5603 | E95: =D95*12 -> 40566.723 | F95: =F94*(1+$B$4) -> 36970.15 | G95: =(E95+C95)-F95 -> 40567.971 | H95: =H94*(1+$B$5)+G95 -> 1407956.4 | J95: 80 | K95: =K94*(1+$B$4) -> 4479.3742 | L95: =K95*12 -> 53752.491 | M95: =M94*(1+$B$4) -> 3380.5603 | N95: =M95*12 -> 40566.723 | O95: =O94*(1+$B$4) -> 36970.15 | P95: =(L95+N95)-O95 -> 57349.064 | Q95: =Q94*(1+$B$5)+P95 -> 1246007.1
A96: 81 | B96: =B95*(1+$B$4) -> 3157.9736 | C96: =B45*12 -> 37895.683 | D96: =D95*(1+$B$4) -> 3465.0743 | E96: =D96*12 -> 41580.891 | F96: =F95*(1+$B$4) -> 37894.404 | G96: =(E96+C96)-F96 -> 41582.17 | H96: =H95*(1+$B$5)+G96 -> 1505856.9 | J96: 81 | K96: =K95*(1+$B$4) -> 4591.3586 | L96: =K96*12 -> 55096.303 | M96: =M95*(1+$B$4) -> 3465.0743 | N96: =M96*12 -> 41580.891 | O96: =O95*(1+$B$4) -> 37894.404 | P96: =(L96+N96)-O96 -> 58782.791 | Q96: =Q95*(1+$B$5)+P96 -> 1354630.2
A97: 82 | B97: =B96*(1+$B$4) -> 3236.9229 | C97: =B46*12 -> 38843.075 | D97: =D96*(1+$B$4) -> 3551.7011 | E97: =D97*12 -> 42620.414 | F97: =F96*(1+$B$4) -> 38841.764 | G97: =(E97+C97)-F97 -> 42621.725 | H97: =H96*(1+$B$5)+G97 -> 1608712.9 | J97: 82 | K97: =K96*(1+$B$4) -> 4706.1426 | L97: =K97*12 -> 56473.711 | M97: =M96*(1+$B$4) -> 3551.7011 | N97: =M97*12 -> 42620.414 | O97: =O96*(1+$B$4) -> 38841.764 | P97: =(L97+N97)-O97 -> 60252.36 | Q97: =Q96*(1+$B$5)+P97 -> 1469067.7
... A115: 100 | B115: =B114*(1+$B$4) -> 5048.495 | C115: =B64*12 -> 60581.941 | D115: =D114*(1+$B$4) -> 5539.4416 | E115: =D115*12 -> 66473.3 | F115: =F114*(1+$B$4) -> 60579.896 | G115: =(E115+C115)-F115 -> 66475.344 | H115: =H114*(1+$B$5)+G115 -> 4616634.5 | J115: 100 | K115: =K114*(1+$B$4) -> 7339.9763 | L115: =K115*12 -> 88079.715 | M115: =M114*(1+$B$4) -> 5539.4416 | N115: =M115*12 -> 66473.3 | O115: =O114*(1+$B$4) -> 60579.896 | P115: =(L115+N115)-O115 -> 93973.119 | Q115: =Q114*(1+$B$5)+P115 -> 4895347.3
A124: Frank | J124: Bill
A125: Age | B125: Montly benefit | C125: Yearly Benefit | D125: 90% of Franks Yearly benefit | E125: Spouse Montly benefit | F125: Spouse Yearly Benefit | G125: Yearly Expenses | H125: expenses vs income | I125: Saving | K125: Age | L125: Montly benefit | M125: Yearly Benefit | N125: 90% of Bills Yearly Benefit | O125: Spouse Monthly Benefit | P125: Spouse Yearly Benefit | Q125: Yearly Expenses | R125: Expenses vs Income | S125: Saving
A126: 62 | B126: =B13 -> 1975.4 | C126: =B126*12 -> 23704.8 | D126: =C126*0.9 -> 21334.32 | E126: =$G$16 -> 2167.5 | F126: =IF(A126<=$H$4,E126*12,D126) -> 26010 | G126: =$B$9 -> 23704 | H126: =(F126+C126)-G126 -> 26010.8 | I126: =$H$4*(1+$B$5)+H126 -> 286010.8 | K126: 62 | L126: 0 | M126: =L126*12 -> 0 | N126: =M126*$B$4 -> 0 | O126: =E126 -> 2167.5 | P126: =O126*12 -> 26010 | Q126: =$B$9 -> 23704 | R126: =IF(K126<=$H$6,(M126+P126)-Q126,(IF(P126>=N126,P126-Q126,N126-G127))) -> 2306 | S126: =($H$4)*(1+$B$5)+P126+R126-C126 -> 264611.2
A127: 63 | B127: =B126*(1+$B$4) -> 2024.785 | C127: =B127*12 -> 24297.42 | D127: =C127*0.9 -> 21867.678 | E127: =E126*(1+$B$4) -> 2221.6875 | F127: =E127*12 -> 26660.25 | G127: =G126*(1+$B$4) -> 24296.6 | H127: =IF(A127<=$H$5,C127+F127-G127,(IF(F127>=D127,F127-G127,D126-G127))) -> 26661.07 | I127: =I126*(1+$B$5)+H127 -> 324112.3 | K127: 63 | L127: 0 | M127: =L127*12 -> 0 | N127: =M127*$B$4 -> 0 | O127: =O126*(1+$B$4) -> 2221.6875 | P127: =O127*12 -> 26660.25 | Q127: =Q126*(1+$B$4) -> 24296.6 | R127: =IF(K127<=$H$5,(M127+P127)-Q127,(IF(P127>=N127,P127-Q127,N127-Q127))) -> 2363.65 | S127: =S126*(1+$B$5)+R127 -> 277559.3
A128: 64 | B128: =B127*(1+$B$4) -> 2075.4046 | C128: =B128*12 -> 24904.855 | D128: =C128*0.9 -> 22414.37 | E128: =E127*(1+$B$4) -> 2277.2297 | F128: =E128*12 -> 27326.756 | G128: =G127*(1+$B$4) -> 24904.015 | H128: =IF(A128<=$H$5,C128+F128-G128,(IF(F128>=D128,F128-G128,D127-G128))) -> 27327.597 | I128: =I127*(1+$B$5)+H128 -> 364404.39 | K128: 64 | L128: 0 | M128: =L128*12 -> 0 | N128: =M128*$B$4 -> 0 | O128: =O127*(1+$B$4) -> 2277.2297 | P128: =O128*12 -> 27326.756 | Q128: =Q127*(1+$B$4) -> 24904.015 | R128: =IF(K128<=$H$5,(M128+P128)-Q128,(IF(P128>=N128,P128-Q128,N128-Q128))) -> 2422.7413 | S128: =S127*(1+$B$5)+R128 -> 291084.41
A129: 65 | B129: =B128*(1+$B$4) -> 2127.2897 | C129: =B129*12 -> 25527.477 | D129: =C129*0.9 -> 22974.729 | E129: =E128*(1+$B$4) -> 2334.1604 | F129: =E129*12 -> 28009.925 | G129: =G128*(1+$B$4) -> 25526.615 | H129: =IF(A129<=$H$5,C129+F129-G129,(IF(F129>=D129,F129-G129,D128-G129))) -> 28010.787 | I129: =I128*(1+$B$5)+H129 -> 406991.35 | K129: 65 | L129: 0 | M129: =L129*12 -> 0 | N129: =M129*$B$4 -> 0 | O129: =O128*(1+$B$4) -> 2334.1604 | P129: =O129*12 -> 28009.925 | Q129: =Q128*(1+$B$4) -> 25526.615 | R129: =IF(K129<=$H$5,(M129+P129)-Q129,(IF(P129>=N129,P129-Q129,N129-Q129))) -> 2483.3098 | S129: =S128*(1+$B$5)+R129 -> 305211.1
A130: 66 | B130: =B129*(1+$B$4) -> 2180.472 | C130: =B130*12 -> 26165.664 | D130: =C130*0.9 -> 23549.097 | E130: =E129*(1+$B$4) -> 2392.5144 | F130: =E130*12 -> 28710.173 | G130: =G129*(1+$B$4) -> 26164.781 | H130: =IF(A130<=$H$5,C130+F130-G130,(IF(F130>=D130,F130-G130,D129-G130))) -> 28711.056 | I130: =I129*(1+$B$5)+H130 -> 451982.06 | K130: 66 | L130: 0 | M130: =L130*12 -> 0 | N130: =M130*$B$4 -> 0 | O130: =O129*(1+$B$4) -> 2392.5144 | P130: =O130*12 -> 28710.173 | Q130: =Q129*(1+$B$4) -> 26164.781 | R130: =IF(K130<=$H$5,(M130+P130)-Q130,(IF(P130>=N130,P130-Q130,N130-Q130))) -> 2545.3925 | S130: =S129*(1+$B$5)+R130 -> 319964.93
A131: 67 | B131: =B130*(1+$B$4) -> 2234.9838 | C131: =B131*12 -> 26819.805 | D131: =C131*0.9 -> 24137.825 | E131: =E130*(1+$B$4) -> 2452.3273 | F131: =E131*12 -> 29427.928 | G131: =G130*(1+$B$4) -> 26818.9 | H131: =IF(A131<=$H$5,C131+F131-G131,(IF(F131>=D131,F131-G131,D130-G131))) -> 29428.833 | I131: =I130*(1+$B$5)+H131 -> 499490.18 | K131: 67 | L131: 0 | M131: =L131*12 -> 0 | N131: =M131*$B$4 -> 0 | O131: =O130*(1+$B$4) -> 2452.3273 | P131: =O131*12 -> 29427.928 | Q131: =Q130*(1+$B$4) -> 26818.9 | R131: =IF(K131<=$H$5,(M131+P131)-Q131,(IF(P131>=N131,P131-Q131,N131-Q131))) -> 2609.0273 | S131: =S130*(1+$B$5)+R131 -> 335372.56
A132: 68 | B132: =B131*(1+$B$4) -> 2290.8584 | C132: =B132*12 -> 27490.301 | D132: =C132*0.9 -> 24741.27 | E132: =E131*(1+$B$4) -> 2513.6355 | F132: =E132*12 -> 30163.626 | G132: =G131*(1+$B$4) -> 27489.373 | H132: =IF(A132<=$H$5,C132+F132-G132,(IF(F132>=D132,F132-G132,D131-G132))) -> 30164.554 | I132: =I131*(1+$B$5)+H132 -> 549634.34 | K132: 68 | L132: 0 | M132: =L132*12 -> 0 | N132: =M132*$B$4 -> 0 | O132: =O131*(1+$B$4) -> 2513.6355 | P132: =O132*12 -> 30163.626 | Q132: =Q131*(1+$B$4) -> 27489.373 | R132: =IF(K132<=$H$5,(M132+P132)-Q132,(IF(P132>=N132,P132-Q132,N132-Q132))) -> 2674.253 | S132: =S131*(1+$B$5)+R132 -> 351461.71
A133: 69 | B133: =B132*(1+$B$4) -> 2348.1298 | C133: =B133*12 -> 28177.558 | D133: =C133*0.9 -> 25359.802 | E133: =E132*(1+$B$4) -> 2576.4764 | F133: =E133*12 -> 30917.716 | G133: =G132*(1+$B$4) -> 28176.607 | H133: =IF(A133<=$H$5,C133+F133-G133,(IF(F133>=D133,F133-G133,D132-G133))) -> 30918.667 | I133: =I132*(1+$B$5)+H133 -> 602538.38 | K133: 69 | L133: 0 | M133: =L133*12 -> 0 | N133: =M133*$B$4 -> 0 | O133: =O132*(1+$B$4) -> 2576.4764 | P133: =O133*12 -> 30917.716 | Q133: =Q132*(1+$B$4) -> 28176.607 | R133: =IF(K133<=$H$5,(M133+P133)-Q133,(IF(P133>=N133,P133-Q133,N133-Q133))) -> 2741.1093 | S133: =S132*(1+$B$5)+R133 -> 368261.29
A134: 70 | B134: =B133*(1+$B$4) -> 2406.8331 | C134: =B134*12 -> 28881.997 | D134: =C134*0.9 -> 25993.797 | E134: =E133*(1+$B$4) -> 2640.8883 | F134: =E134*12 -> 31690.659 | G134: =G133*(1+$B$4) -> 28881.022 | H134: =IF(A134<=$H$5,C134+F134-G134,(IF(F134>=D134,F134-G134,D133-G134))) -> 31691.634 | I134: =I133*(1+$B$5)+H134 -> 658331.55 | K134: 70 | L134: =B21 -> 3499.28 | M134: =L134*12 -> 41991.36 | N134: =M134*0.9 -> 37792.224 | O134: =O133*(1+$B$4) -> 2640.8883 | P134: =O134*12 -> 31690.659 | Q134: =Q133*(1+$B$4) -> 28881.022 | R134: =IF(K134<=$H$5,(M134+P134)-Q134,(IF(P134>=N134,P134-Q134,N134-Q134))) -> 44800.997 | S134: =S133*(1+$B$5)+R134 -> 427792.74
A135: 71 | B135: =B134*(1+$B$4) -> 2467.0039 | C135: =B135*12 -> 29604.047 | D135: =C135*0.9 -> 26643.642 | E135: =E134*(1+$B$4) -> 2706.9105 | F135: =E135*12 -> 32482.926 | G135: =G134*(1+$B$4) -> 29603.048 | H135: =IF(A135<=$H$5,C135+F135-G135,(IF(F135>=D135,F135-G135,D134-G135))) -> 32483.925 | I135: =I134*(1+$B$5)+H135 -> 717148.74 | K135: 71 | L135: =L134*(1+$B$4) -> 3586.762 | M135: =L135*12 -> 43041.144 | N135: =M135*0.9 -> 38737.03 | O135: =O134*(1+$B$4) -> 2706.9105 | P135: =O135*12 -> 32482.926 | Q135: =Q134*(1+$B$4) -> 29603.048 | R135: =IF(K135<=$H$5,(M135+P135)-Q135,(IF(P135>=N135,P135-Q135,N135-Q135))) -> 45921.022 | S135: =S134*(1+$B$5)+R135 -> 490825.47
A136: 72 | B136: =B135*(1+$B$4) -> 2528.679 | C136: =B136*12 -> 30344.148 | D136: =C136*0.9 -> 27309.733 | E136: =E135*(1+$B$4) -> 2774.5832 | F136: =E136*12 -> 33294.999 | G136: =G135*(1+$B$4) -> 30343.124 | H136: =IF(A136<=$H$5,C136+F136-G136,(IF(F136>=D136,F136-G136,D135-G136))) -> 33296.023 | I136: =I135*(1+$B$5)+H136 -> 779130.71 | K136: 72 | L136: =L135*(1+$B$4) -> 3676.431 | M136: =L136*12 -> 44117.173 | N136: =M136*0.9 -> 39705.455 | O136: =O135*(1+$B$4) -> 2774.5832 | P136: =O136*12 -> 33294.999 | Q136: =Q135*(1+$B$4) -> 30343.124 | R136: =IF(K136<=$H$5,(M136+P136)-Q136,(IF(P136>=N136,P136-Q136,N136-Q136))) -> 47069.048 | S136: =S135*(1+$B$5)+R136 -> 557527.54
A137: 73 | B137: =B136*(1+$B$4) -> 2591.896 | C137: =B137*12 -> 31102.752 | D137: =C137*0.9 -> 27992.477 | E137: =E136*(1+$B$4) -> 2843.9478 | F137: =E137*12 -> 34127.374 | G137: =G136*(1+$B$4) -> 31101.702 | H137: =IF(A137<=$H$5,C137+F137-G137,(IF(F137>=D137,F137-G137,D136-G137))) -> 34128.424 | I137: =I136*(1+$B$5)+H137 -> 844424.36 | K137: 73 | L137: =L136*(1+$B$4) -> 3768.3418 | M137: =L137*12 -> 45220.102 | N137: =M137*0.9 -> 40698.092 | O137: =O136*(1+$B$4) -> 2843.9478 | P137: =O137*12 -> 34127.374 | Q137: =Q136*(1+$B$4) -> 31101.702 | R137: =IF(K137<=$H$5,(M137+P137)-Q137,(IF(P137>=N137,P137-Q137,N137-Q137))) -> 48245.774 | S137: =S136*(1+$B$5)+R137 -> 628074.41
A138: 74 | B138: =B137*(1+$B$4) -> 2656.6934 | C138: =B138*12 -> 31880.321 | D138: =C138*0.9 -> 28692.289 | E138: =E137*(1+$B$4) -> 2915.0465 | F138: =E138*12 -> 34980.558 | G138: =G137*(1+$B$4) -> 31879.245 | H138: =IF(A138<=$H$5,C138+F138-G138,(IF(F138>=D138,F138-G138,D137-G138))) -> 34981.634 | I138: =I137*(1+$B$5)+H138 -> 913182.97 | K138: 74 | L138: =L137*(1+$B$4) -> 3862.5504 | M138: =L138*12 -> 46350.604 | N138: =M138*0.9 -> 41715.544 | O138: =O137*(1+$B$4) -> 2915.0465 | P138: =O138*12 -> 34980.558 | Q138: =Q137*(1+$B$4) -> 31879.245 | R138: =IF(K138<=$H$5,(M138+P138)-Q138,(IF(P138>=N138,P138-Q138,N138-Q138))) -> 49451.918 | S138: =S137*(1+$B$5)+R138 -> 702649.31 | Y138: ="Compare Saving of Married Frank and Bill at rate of return of " & B5*100 & "% and Cola of " & B4*100 & "% " & "Yearly Expenses = $" & B9 & " Frank and Bill pass at age " & H5 -> Compare Saving of Married Frank and Bill at rate of return of 4% and Cola of 2.5% Yearly Expenses = $23704 Frank and Bill pass at age 80
A139: 75 | B139: =B138*(1+$B$4) -> 2723.1107 | C139: =B139*12 -> 32677.329 | D139: =C139*0.9 -> 29409.596 | E139: =E138*(1+$B$4) -> 2987.9227 | F139: =E139*12 -> 35855.072 | G139: =G138*(1+$B$4) -> 32676.226 | H139: =IF(A139<=$H$5,C139+F139-G139,(IF(F139>=D139,F139-G139,D138-G139))) -> 35856.175 | I139: =I138*(1+$B$5)+H139 -> 985566.46 | K139: 75 | L139: =L138*(1+$B$4) -> 3959.1141 | M139: =L139*12 -> 47509.37 | N139: =M139*0.9 -> 42758.433 | O139: =O138*(1+$B$4) -> 2987.9227 | P139: =O139*12 -> 35855.072 | Q139: =Q138*(1+$B$4) -> 32676.226 | R139: =IF(K139<=$H$5,(M139+P139)-Q139,(IF(P139>=N139,P139-Q139,N139-Q139))) -> 50688.216 | S139: =S138*(1+$B$5)+R139 -> 781443.5
A140: 76 | B140: =B139*(1+$B$4) -> 2791.1885 | C140: =B140*12 -> 33494.262 | D140: =C140*0.9 -> 30144.836 | E140: =E139*(1+$B$4) -> 3062.6208 | F140: =E140*12 -> 36751.449 | G140: =G139*(1+$B$4) -> 33493.131 | H140: =IF(A140<=$H$5,C140+F140-G140,(IF(F140>=D140,F140-G140,D139-G140))) -> 36752.579 | I140: =I139*(1+$B$5)+H140 -> 1061741.7 | K140: 76 | L140: =L139*(1+$B$4) -> 4058.092 | M140: =L140*12 -> 48697.104 | N140: =M140*0.9 -> 43827.393 | O140: =O139*(1+$B$4) -> 3062.6208 | P140: =O140*12 -> 36751.449 | Q140: =Q139*(1+$B$4) -> 33493.131 | R140: =IF(K140<=$H$5,(M140+P140)-Q140,(IF(P140>=N140,P140-Q140,N140-Q140))) -> 51955.421 | S140: =S139*(1+$B$5)+R140 -> 864656.66
A141: 77 | B141: =B140*(1+$B$4) -> 2860.9682 | C141: =B141*12 -> 34331.618 | D141: =C141*0.9 -> 30898.457 | E141: =E140*(1+$B$4) -> 3139.1863 | F141: =E141*12 -> 37670.235 | G141: =G140*(1+$B$4) -> 34330.46 | H141: =IF(A141<=$H$5,C141+F141-G141,(IF(F141>=D141,F141-G141,D140-G141))) -> 37671.394 | I141: =I140*(1+$B$5)+H141 -> 1141882.8 | K141: 77 | L141: =L140*(1+$B$4) -> 4159.5443 | M141: =L141*12 -> 49914.531 | N141: =M141*0.9 -> 44923.078 | O141: =O140*(1+$B$4) -> 3139.1863 | P141: =O141*12 -> 37670.235 | Q141: =Q140*(1+$B$4) -> 34330.46 | R141: =IF(K141<=$H$5,(M141+P141)-Q141,(IF(P141>=N141,P141-Q141,N141-Q141))) -> 53254.307 | S141: =S140*(1+$B$5)+R141 -> 952497.23
A142: 78 | B142: =B141*(1+$B$4) -> 2932.4924 | C142: =B142*12 -> 35189.909 | D142: =C142*0.9 -> 31670.918 | E142: =E141*(1+$B$4) -> 3217.6659 | F142: =E142*12 -> 38611.991 | G142: =G141*(1+$B$4) -> 35188.721 | H142: =IF(A142<=$H$5,C142+F142-G142,(IF(F142>=D142,F142-G142,D141-G142))) -> 38613.179 | I142: =I141*(1+$B$5)+H142 -> 1226171.3 | K142: 78 | L142: =L141*(1+$B$4) -> 4263.5329 | M142: =L142*12 -> 51162.395 | N142: =M142*0.9 -> 46046.155 | O142: =O141*(1+$B$4) -> 3217.6659 | P142: =O142*12 -> 38611.991 | Q142: =Q141*(1+$B$4) -> 35188.721 | R142: =IF(K142<=$H$5,(M142+P142)-Q142,(IF(P142>=N142,P142-Q142,N142-Q142))) -> 54585.665 | S142: =S141*(1+$B$5)+R142 -> 1045182.8
A143: 79 | B143: =B142*(1+$B$4) -> 3005.8047 | C143: =B143*12 -> 36069.657 | D143: =C143*0.9 -> 32462.691 | E143: =E142*(1+$B$4) -> 3298.1076 | F143: =E143*12 -> 39577.291 | G143: =G142*(1+$B$4) -> 36068.439 | H143: =IF(A143<=$H$5,C143+F143-G143,(IF(F143>=D143,F143-G143,D142-G143))) -> 39578.508 | I143: =I142*(1+$B$5)+H143 -> 1314796.6 | K143: 79 | L143: =L142*(1+$B$4) -> 4370.1212 | M143: =L143*12 -> 52441.455 | N143: =M143*0.9 -> 47197.309 | O143: =O142*(1+$B$4) -> 3298.1076 | P143: =O143*12 -> 39577.291 | Q143: =Q142*(1+$B$4) -> 36068.439 | R143: =IF(K143<=$H$5,(M143+P143)-Q143,(IF(P143>=N143,P143-Q143,N143-Q143))) -> 55950.306 | S143: =S142*(1+$B$5)+R143 -> 1142940.4
A144: 80 | B144: =B143*(1+$B$4) -> 3080.9498 | C144: =B144*12 -> 36971.398 | D144: =C144*0.9 -> 33274.258 | E144: =E143*(1+$B$4) -> 3380.5603 | F144: =E144*12 -> 40566.723 | G144: =G143*(1+$B$4) -> 36970.15 | H144: =IF(A144<=$H$5,C144+F144-G144,(IF(F144>=D144,F144-G144,D143-G144))) -> 40567.971 | I144: =I143*(1+$B$5)+H144 -> 1407956.4 | K144: 80 | L144: =L143*(1+$B$4) -> 4479.3742 | M144: =L144*12 -> 53752.491 | N144: =M144*0.9 -> 48377.242 | O144: =O143*(1+$B$4) -> 3380.5603 | P144: =O144*12 -> 40566.723 | Q144: =Q143*(1+$B$4) -> 36970.15 | R144: =IF(K144<=$H$5,(M144+P144)-Q144,(IF(P144>=N144,P144-Q144,N144-Q144))) -> 57349.064 | S144: =S143*(1+$B$5)+R144 -> 1246007.1
A145: 81 | B145: =B144*(1+$B$4) -> 3157.9736 | C145: =B145*12 -> 37895.683 | D145: =C145*0.9 -> 34106.115 | E145: =E144*(1+$B$4) -> 3465.0743 | F145: =E145*12 -> 41580.891 | G145: =G144*(1+$B$4) -> 37894.404 | H145: =IF(A145<=$H$5,C145+F145-G145,(IF(F145>=D145,F145-G145,D144-G145))) -> 3686.4873 | I145: =I144*(1+$B$5)+H145 -> 1467961.2 | K145: 81 | L145: =L144*(1+$B$4) -> 4591.3586 | M145: =L145*12 -> 55096.303 | N145: =M145*0.9 -> 49586.673 | O145: =O144*(1+$B$4) -> 3465.0743 | P145: =O145*12 -> 41580.891 | Q145: =Q144*(1+$B$4) -> 37894.404 | R145: =IF(K145<=$H$5,(M145+P145)-Q145,(IF(P145>=N145,P145-Q145,N145-Q145))) -> 11692.269 | S145: =S144*(1+$B$5)+R145 -> 1307539.6
A146: 82 | B146: =B145*(1+$B$4) -> 3236.9229 | C146: =B146*12 -> 38843.075 | D146: =C146*0.9 -> 34958.767 | E146: =E145*(1+$B$4) -> 3551.7011 | F146: =E146*12 -> 42620.414 | G146: =G145*(1+$B$4) -> 38841.764 | H146: =IF(A146<=$H$5,C146+F146-G146,(IF(F146>=D146,F146-G146,D145-G146))) -> 3778.6495 | I146: =I145*(1+$B$5)+H146 -> 1530458.3 | K146: 82 | L146: =L145*(1+$B$4) -> 4706.1426 | M146: =L146*12 -> 56473.711 | N146: =M146*0.9 -> 50826.34 | O146: =O145*(1+$B$4) -> 3551.7011 | P146: =O146*12 -> 42620.414 | Q146: =Q145*(1+$B$4) -> 38841.764 | R146: =IF(K146<=$H$5,(M146+P146)-Q146,(IF(P146>=N146,P146-Q146,N146-Q146))) -> 11984.576 | S146: =S145*(1+$B$5)+R146 -> 1371825.8
A147: 83 | B147: =B146*(1+$B$4) -> 3317.846 | C147: =B147*12 -> 39814.152 | D147: =C147*0.9 -> 35832.737 | E147: =E146*(1+$B$4) -> 3640.4937 | F147: =E147*12 -> 43685.924 | G147: =G146*(1+$B$4) -> 39812.808 | H147: =IF(A147<=$H$5,C147+F147-G147,(IF(F147>=D147,F147-G147,D146-G147))) -> 3873.1157 | I147: =I146*(1+$B$5)+H147 -> 1595549.7 | K147: 83 | L147: =L146*(1+$B$4) -> 4823.7961 | M147: =L147*12 -> 57885.554 | N147: =M147*0.9 -> 52096.998 | O147: =O146*(1+$B$4) -> 3640.4937 | P147: =O147*12 -> 43685.924 | Q147: =Q146*(1+$B$4) -> 39812.808 | R147: =IF(K147<=$H$5,(M147+P147)-Q147,(IF(P147>=N147,P147-Q147,N147-Q147))) -> 12284.19 | S147: =S146*(1+$B$5)+R147 -> 1438983
A148: 84 | B148: =B147*(1+$B$4) -> 3400.7921 | C148: =B148*12 -> 40809.506 | D148: =C148*0.9 -> 36728.555 | E148: =E147*(1+$B$4) -> 3731.506 | F148: =E148*12 -> 44778.072 | G148: =G147*(1+$B$4) -> 40808.128 | H148: =IF(A148<=$H$5,C148+F148-G148,(IF(F148>=D148,F148-G148,D147-G148))) -> 3969.9436 | I148: =I147*(1+$B$5)+H148 -> 1663341.7 | K148: 84 | L148: =L147*(1+$B$4) -> 4944.391 | M148: =L148*12 -> 59332.692 | N148: =M148*0.9 -> 53399.423 | O148: =L148*0.9 -> 4449.9519 | P148: =O148*12 -> 53399.423 | Q148: =Q147*(1+$B$4) -> 40808.128 | R148: =IF(K148<=$H$5,(M148+P148)-Q148,(IF(P148>=N148,P148-Q148,N148-Q148))) -> 12591.295 | S148: =S147*(1+$B$5)+R148 -> 1509133.6
A149: 85 | B149: =B148*(1+$B$4) -> 3485.8119 | C149: =B149*12 -> 41829.743 | D149: =C149*0.9 -> 37646.769 | E149: =E148*(1+$B$4) -> 3824.7937 | F149: =E149*12 -> 45897.524 | G149: =G148*(1+$B$4) -> 41828.332 | H149: =IF(A149<=$H$5,C149+F149-G149,(IF(F149>=D149,F149-G149,D148-G149))) -> 4069.1922 | I149: =I148*(1+$B$5)+H149 -> 1733944.5 | K149: 85 | L149: =L148*(1+$B$4) -> 5068.0008 | M149: =L149*12 -> 60816.01 | N149: =M149*0.9 -> 54734.409 | O149: =L149*0.9 -> 4561.2007 | P149: =O149*12 -> 54734.409 | Q149: =Q148*(1+$B$4) -> 41828.332 | R149: =IF(K149<=$H$5,(M149+P149)-Q149,(IF(P149>=N149,P149-Q149,N149-Q149))) -> 12906.077 | S149: =S148*(1+$B$5)+R149 -> 1582405.1
A150: 86 | B150: =B149*(1+$B$4) -> 3572.9572 | C150: =B150*12 -> 42875.487 | D150: =C150*0.9 -> 38587.938 | E150: =E149*(1+$B$4) -> 3920.4135 | F150: =E150*12 -> 47044.962 | G150: =G149*(1+$B$4) -> 42874.04 | H150: =IF(A150<=$H$5,C150+F150-G150,(IF(F150>=D150,F150-G150,D149-G150))) -> 4170.922 | I150: =I149*(1+$B$5)+H150 -> 1807473.2 | K150: 86 | L150: =L149*(1+$B$4) -> 5194.7008 | M150: =L150*12 -> 62336.41 | N150: =M150*0.9 -> 56102.769 | O150: =L150*0.9 -> 4675.2307 | P150: =O150*12 -> 56102.769 | Q150: =Q149*(1+$B$4) -> 42874.04 | R150: =IF(K150<=$H$5,(M150+P150)-Q150,(IF(P150>=N150,P150-Q150,N150-Q150))) -> 13228.729 | S150: =S149*(1+$B$5)+R150 -> 1658930
A151: 87 | B151: =B150*(1+$B$4) -> 3662.2812 | C151: =B151*12 -> 43947.374 | D151: =C151*0.9 -> 39552.637 | E151: =E150*(1+$B$4) -> 4018.4238 | F151: =E151*12 -> 48221.086 | G151: =G150*(1+$B$4) -> 43945.891 | H151: =IF(A151<=$H$5,C151+F151-G151,(IF(F151>=D151,F151-G151,D150-G151))) -> 4275.1951 | I151: =I150*(1+$B$5)+H151 -> 1884047.4 | K151: 87 | L151: =L150*(1+$B$4) -> 5324.5683 | M151: =L151*12 -> 63894.82 | N151: =M151*0.9 -> 57505.338 | O151: =L151*0.9 -> 4792.1115 | P151: =O151*12 -> 57505.338 | Q151: =Q150*(1+$B$4) -> 43945.891 | R151: =IF(K151<=$H$5,(M151+P151)-Q151,(IF(P151>=N151,P151-Q151,N151-Q151))) -> 13559.447 | S151: =S150*(1+$B$5)+R151 -> 1738846.6
A152: 88 | B152: =B151*(1+$B$4) -> 3753.8382 | C152: =B152*12 -> 45046.058 | D152: =C152*0.9 -> 40541.453 | E152: =E151*(1+$B$4) -> 4118.8844 | F152: =E152*12 -> 49426.613 | G152: =G151*(1+$B$4) -> 45044.538 | H152: =IF(A152<=$H$5,C152+F152-G152,(IF(F152>=D152,F152-G152,D151-G152))) -> 4382.075 | I152: =I151*(1+$B$5)+H152 -> 1963791.3 | K152: 88 | L152: =L151*(1+$B$4) -> 5457.6826 | M152: =L152*12 -> 65492.191 | N152: =M152*0.9 -> 58942.972 | O152: =L152*0.9 -> 4911.9143 | P152: =O152*12 -> 58942.972 | Q152: =Q151*(1+$B$4) -> 45044.538 | R152: =IF(K152<=$H$5,(M152+P152)-Q152,(IF(P152>=N152,P152-Q152,N152-Q152))) -> 13898.433 | S152: =S151*(1+$B$5)+R152 -> 1822298.9
A153: 89 | B153: =B152*(1+$B$4) -> 3847.6842 | C153: =B153*12 -> 46172.21 | D153: =C153*0.9 -> 41554.989 | E153: =E152*(1+$B$4) -> 4221.8565 | F153: =E153*12 -> 50662.278 | G153: =G152*(1+$B$4) -> 46170.652 | H153: =IF(A153<=$H$5,C153+F153-G153,(IF(F153>=D153,F153-G153,D152-G153))) -> 4491.6268 | I153: =I152*(1+$B$5)+H153 -> 2046834.6 | K153: 89 | L153: =L152*(1+$B$4) -> 5594.1246 | M153: =L153*12 -> 67129.495 | N153: =M153*0.9 -> 60416.546 | O153: =L153*0.9 -> 5034.7122 | P153: =O153*12 -> 60416.546 | Q153: =Q152*(1+$B$4) -> 46170.652 | R153: =IF(K153<=$H$5,(M153+P153)-Q153,(IF(P153>=N153,P153-Q153,N153-Q153))) -> 14245.894 | S153: =S152*(1+$B$5)+R153 -> 1909436.8
A154: 90 | B154: =B153*(1+$B$4) -> 3943.8763 | C154: =B154*12 -> 47326.515 | D154: =C154*0.9 -> 42593.864 | E154: =E153*(1+$B$4) -> 4327.403 | F154: =E154*12 -> 51928.835 | G154: =G153*(1+$B$4) -> 47324.918 | H154: =IF(A154<=$H$5,C154+F154-G154,(IF(F154>=D154,F154-G154,D153-G154))) -> 4603.9175 | I154: =I153*(1+$B$5)+H154 -> 2133311.9 | K154: 90 | L154: =L153*(1+$B$4) -> 5733.9777 | M154: =L154*12 -> 68807.733 | N154: =M154*0.9 -> 61926.96 | O154: =L154*0.9 -> 5160.58 | P154: =O154*12 -> 61926.96 | Q154: =Q153*(1+$B$4) -> 47324.918 | R154: =IF(K154<=$H$5,(M154+P154)-Q154,(IF(P154>=N154,P154-Q154,N154-Q154))) -> 14602.042 | S154: =S153*(1+$B$5)+R154 -> 2000416.3
A155: 91 | B155: =B154*(1+$B$4) -> 4042.4732 | C155: =B155*12 -> 48509.678 | D155: =C155*0.9 -> 43658.71 | E155: =E154*(1+$B$4) -> 4435.588 | F155: =E155*12 -> 53227.056 | G155: =G154*(1+$B$4) -> 48508.041 | H155: =IF(A155<=$H$5,C155+F155-G155,(IF(F155>=D155,F155-G155,D154-G155))) -> 4719.0155 | I155: =I154*(1+$B$5)+H155 -> 2223363.4 | K155: 91 | L155: =L154*(1+$B$4) -> 5877.3272 | M155: =L155*12 -> 70527.926 | N155: =M155*0.9 -> 63475.134 | O155: =L155*0.9 -> 5289.5945 | P155: =O155*12 -> 63475.134 | Q155: =Q154*(1+$B$4) -> 48508.041 | R155: =IF(K155<=$H$5,(M155+P155)-Q155,(IF(P155>=N155,P155-Q155,N155-Q155))) -> 14967.093 | S155: =S154*(1+$B$5)+R155 -> 2095400
A156: 92 | B156: =B155*(1+$B$4) -> 4143.535 | C156: =B156*12 -> 49722.42 | D156: =C156*0.9 -> 44750.178 | E156: =E155*(1+$B$4) -> 4546.4777 | F156: =E156*12 -> 54557.733 | G156: =G155*(1+$B$4) -> 49720.742 | H156: =IF(A156<=$H$5,C156+F156-G156,(IF(F156>=D156,F156-G156,D155-G156))) -> 4836.9908 | I156: =I155*(1+$B$5)+H156 -> 2317134.9 | K156: 92 | L156: =L155*(1+$B$4) -> 6024.2604 | M156: =L156*12 -> 72291.124 | N156: =M156*0.9 -> 65062.012 | O156: =L156*0.9 -> 5421.8343 | P156: =O156*12 -> 65062.012 | Q156: =Q155*(1+$B$4) -> 49720.742 | R156: =IF(K156<=$H$5,(M156+P156)-Q156,(IF(P156>=N156,P156-Q156,N156-Q156))) -> 15341.27 | S156: =S155*(1+$B$5)+R156 -> 2194557.3
A157: 93 | B157: =B156*(1+$B$4) -> 4247.1234 | C157: =B157*12 -> 50965.48 | D157: =C157*0.9 -> 45868.932 | E157: =E156*(1+$B$4) -> 4660.1397 | F157: =E157*12 -> 55921.676 | G157: =G156*(1+$B$4) -> 50963.76 | H157: =IF(A157<=$H$5,C157+F157-G157,(IF(F157>=D157,F157-G157,D156-G157))) -> 4957.9156 | I157: =I156*(1+$B$5)+H157 -> 2414778.2 | K157: 93 | L157: =L156*(1+$B$4) -> 6174.8669 | M157: =L157*12 -> 74098.402 | N157: =M157*0.9 -> 66688.562 | O157: =L157*0.9 -> 5557.3802 | P157: =O157*12 -> 66688.562 | Q157: =Q156*(1+$B$4) -> 50963.76 | R157: =IF(K157<=$H$5,(M157+P157)-Q157,(IF(P157>=N157,P157-Q157,N157-Q157))) -> 15724.802 | S157: =S156*(1+$B$5)+R157 -> 2298064.4
...

Sheet SS Benefit Cal
A1: Social Security payout
B2: FRA | C2: =Main!B11 -> 2822
B3: Years for PV, NPV | C3: =Main!B12 -> 22 | E3: Average Cola since 1975 | F3: ='SSI cola for the year'!F5 -> 3.7294118
B4: Cola | C4: =Main!B13 -> 0.025
B5: Rate of Return | C5: =Main!B14 -> 0.04 | E5: AverageCPI since 1914 | F5: =Main!E12 -> 0.03263964
B6: Discount Rate | C6: =Main!B15 -> 0.04
B8: AGE | C8: Monthy benefit | D8: % change | E8: year2year change | G8: Monthy Benefit taken at 62 (Cola) | H8: Monthly Benefit taken at 67 (cola) | I8: Monthly Benefit taken at 70 (cola) | K8: Total take at 62. No Cola | L8: 62 yearly benefit | M8: 62 total with Cola | N8: 67 yearly benefit w Cola | O8: 67 total with Cola | P8: 70 yearly benefit w Cola | Q8: 70 total w cola | R8: 62,cola, invest,total | S8: 67, cola, invest total | T8: 70, cola, invest total | U8: Total take 62 compare to 70, cola, rate of return | V8: 70 total w cola | X8: PV take at 62, No Cola | Y8: PV take at 67, No Cola | Z8: PV take at 70, no cola | AA8: NPV take at 62, with Cola | AB8: NPV take at , 67 with Cola | AC8: NPV take at 70, with Cola | AD8: Take at 70, Loss of future gains/losses. | AE8: Take at 67, Loss of future gains/losses | AF8: PV of loss at 70 | AG8: PV of Loss at 67
B9: 62 | C9: =C2*D9 -> 1975.4 | D9: 0.7 | G9: =C9 -> 1975.4 | K9: =$C$9*12 -> 23704.8 | L9: =K9 -> 23704.8 | M9: =K9 -> 23704.8 | N9: 0 | O9: 0 | P9: 0 | Q9: 0 | R9: =M9 -> 23704.8 | S9: =O9 -> 0 | T9: =Q9 -> 0 | U9: =R9 -> 23704.8 | V9: 0 | X9: =PV($C$5,$C$3,K9,,0) -> -342560.8 | Y9: =PV($C$5,C3-5,#REF!) -> #REF! | Z9: =PV($C$5,$C$3-8,#REF!) -> #REF! | AA9: =NPV($C$5,L9:L34) -> 497144.78 | AB9: =NPV($C$5,N9:N34) -> 552028.27 | AC9: =NPV($C$5,P9:P34) -> 573489.85 | AD9: =FV($C$5,$C$3-8,,R17) -> -427382.94 | AE9: =FV($C$5,$C$3-5,,R14) -> -325147.93 | AF9: =AD9/(1+$C$5)^($C$3) -> -180336.53 | AG9: =AE9/(1+$C$5)^($C$3) -> -137197.92
B10: 63 | C10: =C2*D10 -> 2116.5 | D10: 0.75 | E10: =(C10-C9)/C9 -> 0.071428571 | G10: =G9*(1+$C$4) -> 2024.785 | K10: =K9+$K$9 -> 47409.6 | L10: =L9+(L9*$C$4) -> 24297.42 | M10: =M9+L10 -> 48002.22 | N10: 0 | O10: 0 | P10: 0 | Q10: 0 | R10: =L10+(1+$C$5)*R9 -> 48950.412 | S10: =O10 -> 0 | T10: =Q10 -> 0 | U10: =R10 -> 48950.412 | V10: 0
B11: 64 | C11: =C2*D11 -> 2257.6 | D11: 0.8 | E11: =(C11-C10)/C10 -> 0.066666667 | G11: =G10*(1+$C$4) -> 2075.4046 | K11: =K10+$K$9 -> 71114.4 | L11: =L10+(L10*$C$4) -> 24904.855 | M11: =M10+L11 -> 72907.076 | N11: 0 | O11: 0 | P11: 0 | Q11: 0 | R11: =L11+(1+$C$5)*R10 -> 75813.284 | S11: =O11 -> 0 | T11: =Q11 -> 0 | U11: =R11 -> 75813.284 | V11: 0
B12: 65 | C12: =C2*D12 -> 2446.674 | D12: 0.867 | E12: =(C12-C11)/C11 -> 0.08375 | G12: =G11*(1+$C$4) -> 2127.2897 | K12: =K11+$K$9 -> 94819.2 | L12: =L11+(L11*$C$4) -> 25527.477 | M12: =M11+L12 -> 98434.552 | N12: 0 | O12: 0 | P12: 0 | Q12: 0 | R12: =L12+(1+$C$5)*R11 -> 104373.29 | S12: =O12 -> 0 | T12: =Q12 -> 0 | U12: =R12 -> 104373.29 | V12: 0 | AF12: =FV(C5,C3,0,AF9) -> 427382.94 | AG12: =FV(C5,20,0,AG9) -> 300617.54
B13: 66 | C13: =C2*D13 -> 2632.926 | D13: 0.933 | E13: =(C13-C12)/C12 -> 0.076124567 | G13: =G12*(1+$C$4) -> 2180.472 | K13: =K12+$K$9 -> 118524 | L13: =L12+(L12*$C$4) -> 26165.664 | M13: =M12+L13 -> 124600.22 | N13: 0 | O13: 0 | P13: 0 | Q13: 0 | R13: =L13+(1+$C$5)*R12 -> 134713.89 | S13: =O13 -> 0 | T13: =Q13 -> 0 | U13: =R13 -> 134713.89 | V13: 0
B14: 67 | C14: =C2*D14 -> 2822 | D14: 1 | E14: =(C14-C13)/C13 -> 0.071811361 | G14: =G13*(1+$C$4) -> 2234.9838 | H14: =C14*(1+$C$4)^(B14-B9) -> 3192.834 | K14: =K13+$K$9 -> 142228.8 | L14: =L13+(L13*$C$4) -> 26819.805 | M14: =M13+L14 -> 151420.02 | N14: =H14*12 -> 38314.008 | O14: =N14 -> 38314.008 | P14: 0 | Q14: 0 | R14: =L14+(1+$C$5)*R13 -> 166922.25 | S14: =O14 -> 38314.008 | T14: =Q14 -> 0 | U14: =R14 -> 166922.25 | V14: 0
B15: 68 | C15: =C2*D15 -> 3047.76 | D15: 1.08 | E15: =(C15-C14)/C14 -> 0.08 | G15: =G14*(1+$C$4) -> 2290.8584 | H15: =H14*(1+$C$4) -> 3272.6548 | K15: =K14+$K$9 -> 165933.6 | L15: =L14+(L14*$C$4) -> 27490.301 | M15: =M14+L15 -> 178910.32 | N15: =H15*12 -> 39271.858 | O15: =O14+N15 -> 77585.866 | P15: 0 | Q15: 0 | R15: =L15+(1+$C$5)*R14 -> 201089.44 | S15: =(S14*(1+$C$5))+N15 -> 79118.426 | T15: =Q15 -> 0 | U15: =R15 -> 201089.44 | V15: 0
B16: 69 | C16: =C2*D16 -> 3273.52 | D16: 1.16 | E16: =(C16-C15)/C15 -> 0.074074074 | G16: =G15*(1+$C$4) -> 2348.1298 | H16: =H15*(1+$C$4) -> 3354.4712 | K16: =K15+$K$9 -> 189638.4 | L16: =L15+(L15*$C$4) -> 28177.558 | M16: =M15+L16 -> 207087.88 | N16: =H16*12 -> 40253.654 | O16: =O15+N16 -> 117839.52 | P16: 0 | Q16: 0 | R16: =L16+(1+$C$5)*R15 -> 237310.57 | S16: =(S15*(1+$C$5))+N16 -> 122536.82 | T16: =Q16 -> 0 | U16: =R16 -> 237310.57 | V16: 0
B17: 70 | C17: =C2*D17 -> 3499.28 | D17: 1.24 | E17: =(C17-C16)/C16 -> 0.068965517 | G17: =G16*(1+$C$4) -> 2406.8331 | H17: =H16*(1+$C$4) -> 3438.333 | I17: =C17*(1+$C$4)^(B17-B9) -> 4263.5329 | K17: =K16+$K$9 -> 213343.2 | L17: =L16+(L16*$C$4) -> 28881.997 | M17: =M16+L17 -> 235969.88 | N17: =H17*12 -> 41259.996 | O17: =O16+N17 -> 159099.52 | P17: =I17*12 -> 51162.395 | Q17: =P17 -> 51162.395 | R17: =R16*(1+$C$5) -> 246803 | S17: =(S16*(1+$C$5)) -> 127438.29 | T17: 0 | U17: =N17+R17 -> 288062.99 | V17: =P17 -> 51162.395
B18: 71 | G18: =G17*(1+$C$4) -> 2467.0039 | H18: =H17*(1+$C$4) -> 3524.2913 | I18: =I17*(1+$C$4) -> 4370.1212 | K18: =K17+$K$9 -> 237048 | L18: =L17+(L17*$C$4) -> 29604.047 | M18: =M17+L18 -> 265573.92 | N18: =H18*12 -> 42291.496 | O18: =O17+N18 -> 201391.01 | P18: =I18*12 -> 52441.455 | Q18: =Q17+$P$18 -> 103603.85 | R18: =R17*(1+$C$5) -> 256675.12 | S18: =(S17*(1+$C$5)) -> 132535.82 | T18: 0 | U18: =R18+K18-$K$16 -> 304084.72 | V18: =V17+P18 -> 103603.85
B19: 72 | G19: =G18*(1+$C$4) -> 2528.679 | H19: =H18*(1+$C$4) -> 3612.3986 | I19: =I18*(1+$C$4) -> 4479.3742 | K19: =K18+$K$9 -> 260752.8 | L19: =L18+(L18*$C$4) -> 30344.148 | M19: =M18+L19 -> 295918.07 | N19: =H19*12 -> 43348.783 | O19: =O18+N19 -> 244739.79 | P19: =I19*12 -> 53752.491 | Q19: =Q18+P19 -> 157356.34 | R19: =R18*(1+$C$5) -> 266942.12 | S19: =(S18*(1+$C$5)) -> 137837.25 | T19: 0 | U19: =R19+K19-$K$16 -> 338056.52 | V19: =V18+P19 -> 157356.34 | AD19: Money stays invested in an account invested at rate of return
B20: 73 | G20: =G19*(1+$C$4) -> 2591.896 | H20: =H19*(1+$C$4) -> 3702.7085 | I20: =I19*(1+$C$4) -> 4591.3586 | K20: =K19+$K$9 -> 284457.6 | L20: =L19+(L19*$C$4) -> 31102.752 | M20: =M19+L20 -> 327020.82 | N20: =H20*12 -> 44432.503 | O20: =O19+N20 -> 289172.3 | P20: =I20*12 -> 55096.303 | Q20: =Q19+P20 -> 212452.64 | R20: =R19*(1+$C$5) -> 277619.81 | S20: =(S19*(1+$C$5)) -> 143350.74 | T20: 0 | U20: =R20+K20-$K$16 -> 372439.01 | V20: =V19+P20 -> 212452.64 | AD20: How is this normalized to compare.
B21: 74 | G21: =G20*(1+$C$4) -> 2656.6934 | H21: =H20*(1+$C$4) -> 3795.2763 | I21: =I20*(1+$C$4) -> 4706.1426 | K21: =K20+$K$9 -> 308162.4 | L21: =L20+(L20*$C$4) -> 31880.321 | M21: =M20+L21 -> 358901.14 | N21: =H21*12 -> 45543.315 | O21: =O20+N21 -> 334715.61 | P21: =I21*12 -> 56473.711 | Q21: =Q20+P21 -> 268926.35 | R21: =R20*(1+$C$5) -> 288724.6 | S21: =(S20*(1+$C$5)) -> 149084.77 | T21: 0 | U21: =R21+K21-$K$16 -> 407248.6 | V21: =V20+P21 -> 268926.35
B22: 75 | G22: =G21*(1+$C$4) -> 2723.1107 | H22: =H21*(1+$C$4) -> 3890.1582 | I22: =I21*(1+$C$4) -> 4823.7961 | K22: =K21+$K$9 -> 331867.2 | L22: =L21+(L21*$C$4) -> 32677.329 | M22: =M21+L22 -> 391578.47 | N22: =H22*12 -> 46681.898 | O22: =O21+N22 -> 381397.51 | P22: =I22*12 -> 57885.554 | Q22: =Q21+P22 -> 326811.91 | R22: =R21*(1+$C$5) -> 300273.58 | S22: =(S21*(1+$C$5)) -> 155048.17 | T22: 0 | U22: =R22+K22-$K$16 -> 442502.38 | V22: =V21+P22 -> 326811.91
B23: 76 | G23: =G22*(1+$C$4) -> 2791.1885 | H23: =H22*(1+$C$4) -> 3987.4121 | I23: =I22*(1+$C$4) -> 4944.391 | K23: =K22+$K$9 -> 355572 | L23: =L22+(L22*$C$4) -> 33494.262 | M23: =M22+L23 -> 425072.74 | N23: =H23*12 -> 47848.945 | O23: =O22+N23 -> 429246.46 | P23: =I23*12 -> 59332.692 | Q23: =Q22+P23 -> 386144.6 | R23: =R22*(1+$C$5) -> 312284.53 | S23: =(S22*(1+$C$5)) -> 161250.09 | T23: 0 | U23: =R23+K23-$K$16 -> 478218.13 | V23: =V22+P23 -> 386144.6
B24: 77 | G24: =G23*(1+$C$4) -> 2860.9682 | H24: =H23*(1+$C$4) -> 4087.0974 | I24: =I23*(1+$C$4) -> 5068.0008 | K24: =K23+$K$9 -> 379276.8 | L24: =L23+(L23*$C$4) -> 34331.618 | M24: =M23+L24 -> 459404.35 | N24: =H24*12 -> 49045.169 | O24: =O23+N24 -> 478291.62 | P24: =I24*12 -> 60816.01 | Q24: =Q23+P24 -> 446960.61 | R24: =R23*(1+$C$5) -> 324775.91 | S24: =(S23*(1+$C$5)) -> 167700.1 | T24: 0 | U24: =R24+K24-$K$16 -> 514414.31 | V24: =V23+P24 -> 446960.61
B25: 78 | G25: =G24*(1+$C$4) -> 2932.4924 | H25: =H24*(1+$C$4) -> 4189.2749 | I25: =I24*(1+$C$4) -> 5194.7008 | K25: =K24+$K$9 -> 402981.6 | L25: =L24+(L24*$C$4) -> 35189.909 | M25: =M24+L25 -> 494594.26 | N25: =H25*12 -> 50271.298 | O25: =O24+N25 -> 528562.92 | P25: =I25*12 -> 62336.41 | Q25: =Q24+P25 -> 509297.02 | R25: =R24*(1+$C$5) -> 337766.94 | S25: =(S24*(1+$C$5)) -> 174408.1 | T25: 0 | U25: =R25+K25-$K$16 -> 551110.14 | V25: =V24+P25 -> 509297.02
B26: 79 | G26: =G25*(1+$C$4) -> 3005.8047 | H26: =H25*(1+$C$4) -> 4294.0067 | I26: =I25*(1+$C$4) -> 5324.5683 | K26: =K25+$K$9 -> 426686.4 | L26: =L25+(L25*$C$4) -> 36069.657 | M26: =M25+L26 -> 530663.92 | N26: =H26*12 -> 51528.081 | O26: =O25+N26 -> 580091 | P26: =I26*12 -> 63894.82 | Q26: =Q25+P26 -> 573191.84 | R26: =R25*(1+$C$5) -> 351277.62 | S26: =(S25*(1+$C$5)) -> 181384.42 | T26: 0 | U26: =R26+K26-$K$16 -> 588325.62 | V26: =V25+P26 -> 573191.84
B27: 80 | G27: =G26*(1+$C$4) -> 3080.9498 | H27: =H26*(1+$C$4) -> 4401.3569 | I27: =I26*(1+$C$4) -> 5457.6826 | K27: =K26+$K$9 -> 450391.2 | L27: =L26+(L26*$C$4) -> 36971.398 | M27: =M26+L27 -> 567635.32 | N27: =H27*12 -> 52816.283 | O27: =O26+N27 -> 632907.29 | P27: =I27*12 -> 65492.191 | Q27: =Q26+P27 -> 638684.03 | R27: =R26*(1+$C$5) -> 365328.73 | S27: =(S26*(1+$C$5)) -> 188639.8 | T27: 0 | U27: =R27+K27-$K$16 -> 626081.53 | V27: =V26+P27 -> 638684.03
B28: 81 | G28: =G27*(1+$C$4) -> 3157.9736 | H28: =H27*(1+$C$4) -> 4511.3908 | I28: =I27*(1+$C$4) -> 5594.1246 | K28: =K27+$K$9 -> 474096 | L28: =L27+(L27*$C$4) -> 37895.683 | M28: =M27+L28 -> 605531 | N28: =H28*12 -> 54136.69 | O28: =O27+N28 -> 687043.98 | P28: =I28*12 -> 67129.495 | Q28: =Q27+P28 -> 705813.53 | R28: =R27*(1+$C$5) -> 379941.88 | S28: =(S27*(1+$C$5)) -> 196185.39 | T28: 0 | U28: =R28+K28-$K$16 -> 664399.48 | V28: =V27+P28 -> 705813.53
B29: 82 | G29: =G28*(1+$C$4) -> 3236.9229 | H29: =H28*(1+$C$4) -> 4624.1756 | I29: =I28*(1+$C$4) -> 5733.9777 | K29: =K28+$K$9 -> 497800.8 | L29: =L28+(L28*$C$4) -> 38843.075 | M29: =M28+L29 -> 644374.07 | N29: =H29*12 -> 55490.107 | O29: =O28+N29 -> 742534.08 | P29: =I29*12 -> 68807.733 | Q29: =Q28+P29 -> 774621.26 | R29: =R28*(1+$C$5) -> 395139.55 | S29: =(S28*(1+$C$5)) -> 204032.81 | T29: 0 | U29: =R29+K29-$K$16 -> 703301.95 | V29: =V28+P29 -> 774621.26
B30: 83 | G30: =G29*(1+$C$4) -> 3317.846 | H30: =H29*(1+$C$4) -> 4739.78 | I30: =I29*(1+$C$4) -> 5877.3272 | K30: =K29+$K$9 -> 521505.6 | L30: =L29+(L29*$C$4) -> 39814.152 | M30: =M29+L30 -> 684188.23 | N30: =H30*12 -> 56877.36 | O30: =O29+N30 -> 799411.44 | P30: =I30*12 -> 70527.926 | Q30: =Q29+P30 -> 845149.19 | R30: =R29*(1+$C$5) -> 410945.13 | S30: =(S29*(1+$C$5)) -> 212194.12 | T30: 0 | U30: =R30+K30-$K$16 -> 742812.33 | V30: =V29+P30 -> 845149.19
B31: 84 | G31: =G30*(1+$C$4) -> 3400.7921 | H31: =H30*(1+$C$4) -> 4858.2745 | I31: =I30*(1+$C$4) -> 6024.2604 | K31: =K30+$K$9 -> 545210.4 | L31: =L30+(L30*$C$4) -> 40809.506 | M31: =M30+L31 -> 724997.73 | N31: =H31*12 -> 58299.294 | O31: =O30+N31 -> 857710.74 | P31: =I31*12 -> 72291.124 | Q31: =Q30+P31 -> 917440.31 | R31: =R30*(1+$C$5) -> 427382.94 | S31: =(S30*(1+$C$5)) -> 220681.89 | T31: 0 | U31: =R31+K31-$K$16 -> 782954.94 | V31: =V30+P31 -> 917440.31
B32: 85 | G32: =G31*(1+$C$4) -> 3485.8119 | H32: =H31*(1+$C$4) -> 4979.7313 | I32: =I31*(1+$C$4) -> 6174.8669 | K32: =K31+$K$9 -> 568915.2 | L32: =L31+(L31*$C$4) -> 41829.743 | M32: =M31+L32 -> 766827.48 | N32: =H32*12 -> 59756.776 | O32: =O31+N32 -> 917467.51 | P32: =I32*12 -> 74098.402 | Q32: =Q31+P32 -> 991538.71 | R32: =R31*(1+$C$5) -> 444478.26 | S32: =(S31*(1+$C$5)) -> 229509.16 | T32: 0 | U32: =R32+K32-$K$16 -> 823755.06 | V32: =V31+P32 -> 991538.71
... B47: 100 | G47: =G46*(1+$C$4) -> 5048.495 | H47: =H46*(1+$C$4) -> 7212.1358 | I47: =I46*(1+$C$4) -> 8943.0484 | K47: =K46+$K$9 -> 924487.2 | L47: =L46+(L46*$C$4) -> 60581.941 | M47: =M46+L47 -> 1535667.6 | N47: =H47*12 -> 86545.629 | O47: =O46+N47 -> 2015810.5 | P47: =I47*12 -> 107316.58 | Q47: =Q46+P47 -> 2353484 | R47: =R46*(1+$C$5) -> 800480.23 | S47: =(S46*(1+$C$5)) -> 413333.03 | T47: 0 | U47: =R47+K47-$K$16 -> 1535329 | V47: =V46+P47 -> 2353484

Sheet RMD Tables 2025
B4: Table III | G4: Discount Rate | H4: =Main!B14 -> 0.04
B5: (Uniform Lifetime) | G5: Balance at 72 | H5: 2000000
B6: (For Use by: | G6: Cola | H6: =Main!B13 -> 0.025
B7: Unmarried Owners,
B8: Married Owners Whose Spouses Aren't More Than 10 Years Younger, and
B9: Married Owners Whose Spouses Aren't the Sole Beneficiaries of Their IRAs)
B11: Age | C11: Distribution Period | D11: Age | E11: Distribution Period | H11: Balance at 72 | J11: RMD | K11: Cola Adjusted Initial RMD | M11: Balance/RMD %
B12: 72 | C12: 27.4 | D12: 97 | E12: 7.8 | G12: 72 | H12: =H5 -> 2000000 | I12: =C12 -> 27.4 | J12: =H12/I12 -> 72992.701 | M12: =J12/H12 -> 0.03649635
B13: 73 | C13: 26.5 | D13: 98 | E13: 7.3 | G13: 73 | H13: =(H12-J12)*(1+$H$4) -> 2004087.6 | I13: =C13 -> 26.5 | J13: =H13/I13 -> 75625.947 | K13: =J12*(1+$H$6) -> 74817.518 | M13: =J13/H13 -> 0.037735849
B14: 74 | C14: 25.5 | D14: 99 | E14: 6.8 | G14: 74 | H14: =(H13-J13)*(1+$H$4) -> 2005600.1 | I14: =C14 -> 25.5 | J14: =H14/I14 -> 78650.985 | K14: =K13*(1+$H$6) -> 76687.956 | M14: =J14/H14 -> 0.039215686
B15: 75 | C15: 24.6 | D15: 100 | E15: 6.4 | G15: 75 | H15: =(H14-J14)*(1+$H$4) -> 2004027.1 | I15: =C15 -> 24.6 | J15: =H15/I15 -> 81464.516 | K15: =K14*(1+$H$6) -> 78605.155 | M15: =J15/H15 -> 0.040650407
B16: 76 | C16: 23.7 | D16: 101 | E16: 6 | G16: 76 | H16: =(H15-J15)*(1+$H$4) -> 1999465.1 | I16: =C16 -> 23.7 | J16: =H16/I16 -> 84365.615 | K16: =K15*(1+$H$6) -> 80570.284 | M16: =J16/H16 -> 0.042194093
B17: 77 | C17: 22.9 | D17: 102 | E17: 5.6 | G17: 77 | H17: =(H16-J16)*(1+$H$4) -> 1991703.4 | I17: =C17 -> 22.9 | J17: =H17/I17 -> 86973.949 | K17: =K16*(1+$H$6) -> 82584.541 | M17: =J17/H17 -> 0.043668122
B18: 78 | C18: 22 | D18: 103 | E18: 5.2 | G18: 78 | H18: =(H17-J17)*(1+$H$4) -> 1980918.7 | I18: =C18 -> 22 | J18: =H18/I18 -> 90041.758 | K18: =K17*(1+$H$6) -> 84649.155 | M18: =J18/H18 -> 0.045454545
B19: 79 | C19: 21.1 | D19: 104 | E19: 4.9 | G19: 79 | H19: =(H18-J18)*(1+$H$4) -> 1966512 | I19: =C19 -> 21.1 | J19: =H19/I19 -> 93199.62 | K19: =K18*(1+$H$6) -> 86765.383 | M19: =J19/H19 -> 0.047393365
B20: 80 | C20: 20.2 | D20: 105 | E20: 4.6 | G20: 80 | H20: =(H19-J19)*(1+$H$4) -> 1948244.9 | I20: =C20 -> 20.2 | J20: =H20/I20 -> 96447.766 | K20: =K19*(1+$H$6) -> 88934.518 | M20: =J20/H20 -> 0.04950495
B21: 81 | C21: 19.4 | D21: 106 | E21: 4.3 | G21: 81 | H21: =(H20-J20)*(1+$H$4) -> 1925869 | I21: =C21 -> 19.4 | J21: =H21/I21 -> 99271.597 | K21: =K20*(1+$H$6) -> 91157.881 | M21: =J21/H21 -> 0.051546392
B22: 82 | C22: 18.5 | D22: 107 | E22: 4.1 | G22: 82 | H22: =(H21-J21)*(1+$H$4) -> 1899661.3 | I22: =C22 -> 18.5 | J22: =H22/I22 -> 102684.39 | K22: =K21*(1+$H$6) -> 93436.828 | M22: =J22/H22 -> 0.054054054
B23: 83 | C23: 17.7 | D23: 108 | E23: 3.9 | G23: 83 | H23: =(H22-J22)*(1+$H$4) -> 1868856 | I23: =C23 -> 17.7 | J23: =H23/I23 -> 105585.08 | K23: =K22*(1+$H$6) -> 95772.749 | M23: =J23/H23 -> 0.056497175
B24: 84 | C24: 16.8 | D24: 109 | E24: 3.7 | G24: 84 | H24: =(H23-J23)*(1+$H$4) -> 1833801.7 | I24: =C24 -> 16.8 | J24: =H24/I24 -> 109154.86 | K24: =K23*(1+$H$6) -> 98167.067 | M24: =J24/H24 -> 0.05952381
B25: 85 | C25: 16 | D25: 110 | E25: 3.5 | G25: 85 | H25: =(H24-J24)*(1+$H$4) -> 1793632.7 | I25: =C25 -> 16 | J25: =H25/I25 -> 112102.05 | K25: =K24*(1+$H$6) -> 100621.24 | M25: =J25/H25 -> 0.0625
... B34: 94 | C34: 9.5 | D34: 119 | E34: 2.3 | G34: 94 | H34: =(H33-J33)*(1+$H$4) -> 1219282.4 | I34: =C34 -> 9.5 | J34: =H34/I34 -> 128345.52 | K34: =K33*(1+$H$6) -> 125662.15 | M34: =J34/H34 -> 0.10526316
B35: 95 | C35: 8.9 | D35: 120 and over | E35: 2 | G35: 95 | H35: =(H34-J34)*(1+$H$4) -> 1134574.4 | I35: =C35 -> 8.9 | J35: =H35/I35 -> 127480.27 | K35: =K34*(1+$H$6) -> 128803.7 | M35: =J35/H35 -> 0.11235955
B36: 96 | C36: 8.4 | G36: 96 | H36: =(H35-J35)*(1+$H$4) -> 1047377.9 | I36: =C36 -> 8.4 | J36: =H36/I36 -> 124687.84 | K36: =K35*(1+$H$6) -> 132023.79 | M36: =J36/H36 -> 0.11904762
B37: 97 | G37: 97 | H37: =(H36-J36)*(1+$H$4) -> 959597.62 | I37: =E12 -> 7.8 | J37: =H37/I37 -> 123025.34 | K37: =K36*(1+$H$6) -> 135324.39 | M37: =J37/H37 -> 0.12820513
B38: 98 | G38: 98 | H38: =(H37-J37)*(1+$H$4) -> 870035.18 | I38: =E13 -> 7.3 | J38: =H38/I38 -> 119182.9 | K38: =K37*(1+$H$6) -> 138707.5 | M38: =J38/H38 -> 0.1369863
B39: 99 | G39: 99 | H39: =(H38-J38)*(1+$H$4) -> 780886.37 | I39: =E14 -> 6.8 | J39: =H39/I39 -> 114836.23 | K39: =K38*(1+$H$6) -> 142175.18 | M39: =J39/H39 -> 0.14705882
B40: 100 | G40: 100 | H40: =(H39-J39)*(1+$H$4) -> 692692.14 | I40: =E15 -> 6.4 | J40: =H40/I40 -> 108233.15 | K40: =K39*(1+$H$6) -> 145729.56 | M40: =J40/H40 -> 0.15625
B41: 101 | G41: 101 | H41: =(H40-J40)*(1+$H$4) -> 607837.35 | I41: =E16 -> 6 | J41: =H41/I41 -> 101306.23 | K41: =K40*(1+$H$6) -> 149372.8 | M41: =J41/H41 -> 0.16666667
B42: 102 | G42: 102 | H42: =(H41-J41)*(1+$H$4) -> 526792.37 | I42: =E17 -> 5.6 | J42: =H42/I42 -> 94070.067 | K42: =K41*(1+$H$6) -> 153107.12 | M42: =J42/H42 -> 0.17857143
B43: 103 | G43: 103 | H43: =(H42-J42)*(1+$H$4) -> 450031.2 | I43: =E18 -> 5.2 | J43: =H43/I43 -> 86544.461 | K43: =K42*(1+$H$6) -> 156934.8 | M43: =J43/H43 -> 0.19230769
B44: 104 | G44: 104 | H44: =(H43-J43)*(1+$H$4) -> 378026.21 | I44: =E19 -> 4.9 | J44: =H44/I44 -> 77148.206 | K44: =K43*(1+$H$6) -> 160858.17 | M44: =J44/H44 -> 0.20408163
B45: 105 | G45: 105 | H45: =(H44-J44)*(1+$H$4) -> 312913.12 | I45: =E20 -> 4.6 | J45: =H45/I45 -> 68024.592 | K45: =K44*(1+$H$6) -> 164879.62 | M45: =J45/H45 -> 0.2173913
B46: 106 | G46: 106 | H46: =(H45-J45)*(1+$H$4) -> 254684.07 | I46: =E21 -> 4.3 | J46: =H46/I46 -> 59228.854 | K46: =K45*(1+$H$6) -> 169001.62 | M46: =J46/H46 -> 0.23255814
B47: 107 | G47: 107 | H47: =(H46-J46)*(1+$H$4) -> 203273.43 | I47: =E22 -> 4.1 | J47: =H47/I47 -> 49578.884 | K47: =K46*(1+$H$6) -> 173226.66 | M47: =J47/H47 -> 0.24390244
B48: 108 | G48: 108 | H48: =(H47-J47)*(1+$H$4) -> 159842.32 | I48: =E23 -> 3.9 | J48: =H48/I48 -> 40985.211 | K48: =K47*(1+$H$6) -> 177557.32 | M48: =J48/H48 -> 0.25641026
... B60: 120 | G60: 120 | H60: =(H59-J59)*(1+$H$4) -> 1981.9551 | I60: =E35 -> 2 | J60: =H60/I60 -> 990.97756 | K60: =K59*(1+$H$6) -> 238794.86 | M60: =J60/H60 -> 0.5

Sheet Cpi_index_inflation_montly_1925
A1: Series ID | B1: Year | C1: Period | D1: Label | E1: Value | F1: 12-Month % Change
A2: CUUR0000SA0 | B2: 1925 | C2: M01 | D2: 9133 | E2: 17.3 | F2: 0
A3: CUUR0000SA0 | B3: 1925 | C3: M02 | D3: 9164 | E3: 17.2 | F3: 0
A4: CUUR0000SA0 | B4: 1925 | C4: M03 | D4: 9192 | E4: 17.3 | F4: 1.2
A5: CUUR0000SA0 | B5: 1925 | C5: M04 | D5: 9223 | E5: 17.2 | F5: 1.2
A6: CUUR0000SA0 | B6: 1925 | C6: M05 | D6: 9253 | E6: 17.3 | F6: 1.8
A7: CUUR0000SA0 | B7: 1925 | C7: M06 | D7: 9284 | E7: 17.5 | F7: 2.9
A8: CUUR0000SA0 | B8: 1925 | C8: M07 | D8: 9314 | E8: 17.7 | F8: 3.5
A9: CUUR0000SA0 | B9: 1925 | C9: M08 | D9: 9345 | E9: 17.7 | F9: 4.1
A10: CUUR0000SA0 | B10: 1925 | C10: M09 | D10: 9376 | E10: 17.7 | F10: 3.5
A11: CUUR0000SA0 | B11: 1925 | C11: M10 | D11: 9406 | E11: 17.7 | F11: 2.9
A12: CUUR0000SA0 | B12: 1925 | C12: M11 | D12: 9437 | E12: 18 | F12: 4.7
A13: CUUR0000SA0 | B13: 1925 | C13: M12 | D13: 9467 | E13: 17.9 | F13: 3.5
... A1009: CUUR0000SA0 | B1009: 2008 | C1009: M12 | D1009: 39783 | E1009: 210.228 | F1009: 0.1
A1010: CUUR0000SA0 | B1010: 2009 | C1010: M01 | D1010: 39814 | E1010: 211.143
A1011: CUUR0000SA0 | B1011: 2009 | C1011: M02 | D1011: 39845 | E1011: 212.193
A1012: CUUR0000SA0 | B1012: 2009 | C1012: M03 | D1012: 39873 | E1012: 212.709
A1013: CUUR0000SA0 | B1013: 2009 | C1013: M04 | D1013: 39904 | E1013: 213.24
A1014: CUUR0000SA0 | B1014: 2009 | C1014: M05 | D1014: 39934 | E1014: 213.856
A1015: CUUR0000SA0 | B1015: 2009 | C1015: M06 | D1015: 39965 | E1015: 215.693
A1016: CUUR0000SA0 | B1016: 2009 | C1016: M07 | D1016: 39995 | E1016: 215.351
A1017: CUUR0000SA0 | B1017: 2009 | C1017: M08 | D1017: 40026 | E1017: 215.834
A1018: CUUR0000SA0 | B1018: 2009 | C1018: M09 | D1018: 40057 | E1018: 215.969
A1019: CUUR0000SA0 | B1019: 2009 | C1019: M10 | D1019: 40087 | E1019: 216.177
A1020: CUUR0000SA0 | B1020: 2009 | C1020: M11 | D1020: 40118 | E1020: 216.33
A1021: CUUR0000SA0 | B1021: 2009 | C1021: M12 | D1021: 40148 | E1021: 215.949
A1022: CUUR0000SA0 | B1022: 2010 | C1022: M01 | D1022: 40179 | E1022: 216.687 | F1022: 2.6
A1023: CUUR0000SA0 | B1023: 2010 | C1023: M02 | D1023: 40210 | E1023: 216.741 | F1023: 2.1
A1024: CUUR0000SA0 | B1024: 2010 | C1024: M03 | D1024: 40238 | E1024: 217.631 | F1024: 2.3
A1025: CUUR0000SA0 | B1025: 2010 | C1025: M04 | D1025: 40269 | E1025: 218.009 | F1025: 2.2
A1026: CUUR0000SA0 | B1026: 2010 | C1026: M05 | D1026: 40299 | E1026: 218.178 | F1026: 2
A1027: CUUR0000SA0 | B1027: 2010 | C1027: M06 | D1027: 40330 | E1027: 217.965 | F1027: 1.1
A1028: CUUR0000SA0 | B1028: 2010 | C1028: M07 | D1028: 40360 | E1028: 218.011 | F1028: 1.2
A1029: CUUR0000SA0 | B1029: 2010 | C1029: M08 | D1029: 40391 | E1029: 218.312 | F1029: 1.1
A1030: CUUR0000SA0 | B1030: 2010 | C1030: M09 | D1030: 40422 | E1030: 218.439 | F1030: 1.1
A1031: CUUR0000SA0 | B1031: 2010 | C1031: M10 | D1031: 40452 | E1031: 218.711 | F1031: 1.2
A1032: CUUR0000SA0 | B1032: 2010 | C1032: M11 | D1032: 40483 | E1032: 218.803 | F1032: 1.1
A1033: CUUR0000SA0 | B1033: 2010 | C1033: M12 | D1033: 40513 | E1033: 219.179 | F1033: 1.5
A1034: CUUR0000SA0 | B1034: 2011 | C1034: M01 | D1034: 40544 | E1034: 220.223
A1035: CUUR0000SA0 | B1035: 2011 | C1035: M02 | D1035: 40575 | E1035: 221.309
A1036: CUUR0000SA0 | B1036: 2011 | C1036: M03 | D1036: 40603 | E1036: 223.467
A1037: CUUR0000SA0 | B1037: 2011 | C1037: M04 | D1037: 40634 | E1037: 224.906
A1038: CUUR0000SA0 | B1038: 2011 | C1038: M05 | D1038: 40664 | E1038: 225.964
A1039: CUUR0000SA0 | B1039: 2011 | C1039: M06 | D1039: 40695 | E1039: 225.722
A1040: CUUR0000SA0 | B1040: 2011 | C1040: M07 | D1040: 40725 | E1040: 225.922
A1041: CUUR0000SA0 | B1041: 2011 | C1041: M08 | D1041: 40756 | E1041: 226.545
A1042: CUUR0000SA0 | B1042: 2011 | C1042: M09 | D1042: 40787 | E1042: 226.889
A1043: CUUR0000SA0 | B1043: 2011 | C1043: M10 | D1043: 40817 | E1043: 226.421
A1044: CUUR0000SA0 | B1044: 2011 | C1044: M11 | D1044: 40848 | E1044: 226.23
A1045: CUUR0000SA0 | B1045: 2011 | C1045: M12 | D1045: 40878 | E1045: 225.672
A1046: CUUR0000SA0 | B1046: 2012 | C1046: M01 | D1046: 40909 | E1046: 226.665 | F1046: 2.9
A1047: CUUR0000SA0 | B1047: 2012 | C1047: M02 | D1047: 40940 | E1047: 227.663 | F1047: 2.9
A1048: CUUR0000SA0 | B1048: 2012 | C1048: M03 | D1048: 40969 | E1048: 229.392 | F1048: 2.7
A1049: CUUR0000SA0 | B1049: 2012 | C1049: M04 | D1049: 41000 | E1049: 230.085 | F1049: 2.3
A1050: CUUR0000SA0 | B1050: 2012 | C1050: M05 | D1050: 41030 | E1050: 229.815 | F1050: 1.7
A1051: CUUR0000SA0 | B1051: 2012 | C1051: M06 | D1051: 41061 | E1051: 229.478 | F1051: 1.7
A1052: CUUR0000SA0 | B1052: 2012 | C1052: M07 | D1052: 41091 | E1052: 229.104 | F1052: 1.4
A1053: CUUR0000SA0 | B1053: 2012 | C1053: M08 | D1053: 41122 | E1053: 230.379 | F1053: 1.7
A1054: CUUR0000SA0 | B1054: 2012 | C1054: M09 | D1054: 41153 | E1054: 231.407 | F1054: 2
A1055: CUUR0000SA0 | B1055: 2012 | C1055: M10 | D1055: 41183 | E1055: 231.317 | F1055: 2.2
A1056: CUUR0000SA0 | B1056: 2012 | C1056: M11 | D1056: 41214 | E1056: 230.221 | F1056: 1.8
A1057: CUUR0000SA0 | B1057: 2012 | C1057: M12 | D1057: 41244 | E1057: 229.601 | F1057: 1.7
A1058: CUUR0000SA0 | B1058: 2013 | C1058: M01 | D1058: 41275 | E1058: 230.28
A1059: CUUR0000SA0 | B1059: 2013 | C1059: M02 | D1059: 41306 | E1059: 232.166
A1060: CUUR0000SA0 | B1060: 2013 | C1060: M03 | D1060: 41334 | E1060: 232.773
A1061: CUUR0000SA0 | B1061: 2013 | C1061: M04 | D1061: 41365 | E1061: 232.531
A1062: CUUR0000SA0 | B1062: 2013 | C1062: M05 | D1062: 41395 | E1062: 232.945
A1063: CUUR0000SA0 | B1063: 2013 | C1063: M06 | D1063: 41426 | E1063: 233.504
A1064: CUUR0000SA0 | B1064: 2013 | C1064: M07 | D1064: 41456 | E1064: 233.596
A1065: CUUR0000SA0 | B1065: 2013 | C1065: M08 | D1065: 41487 | E1065: 233.877
A1066: CUUR0000SA0 | B1066: 2013 | C1066: M09 | D1066: 41518 | E1066: 234.149
A1067: CUUR0000SA0 | B1067: 2013 | C1067: M10 | D1067: 41548 | E1067: 233.546
A1068: CUUR0000SA0 | B1068: 2013 | C1068: M11 | D1068: 41579 | E1068: 233.069
A1069: CUUR0000SA0 | B1069: 2013 | C1069: M12 | D1069: 41609 | E1069: 233.049
A1070: CUUR0000SA0 | B1070: 2014 | C1070: M01 | D1070: 41640 | E1070: 233.916 | F1070: 1.6
A1071: CUUR0000SA0 | B1071: 2014 | C1071: M02 | D1071: 41671 | E1071: 234.781 | F1071: 1.1
A1072: CUUR0000SA0 | B1072: 2014 | C1072: M03 | D1072: 41699 | E1072: 236.293 | F1072: 1.5
A1073: CUUR0000SA0 | B1073: 2014 | C1073: M04 | D1073: 41730 | E1073: 237.072 | F1073: 2
A1074: CUUR0000SA0 | B1074: 2014 | C1074: M05 | D1074: 41760 | E1074: 237.9 | F1074: 2.1
A1075: CUUR0000SA0 | B1075: 2014 | C1075: M06 | D1075: 41791 | E1075: 238.343 | F1075: 2.1
A1076: CUUR0000SA0 | B1076: 2014 | C1076: M07 | D1076: 41821 | E1076: 238.25 | F1076: 2
A1077: CUUR0000SA0 | B1077: 2014 | C1077: M08 | D1077: 41852 | E1077: 237.852 | F1077: 1.7
A1078: CUUR0000SA0 | B1078: 2014 | C1078: M09 | D1078: 41883 | E1078: 238.031 | F1078: 1.7
A1079: CUUR0000SA0 | B1079: 2014 | C1079: M10 | D1079: 41913 | E1079: 237.433 | F1079: 1.7
A1080: CUUR0000SA0 | B1080: 2014 | C1080: M11 | D1080: 41944 | E1080: 236.151 | F1080: 1.3
A1081: CUUR0000SA0 | B1081: 2014 | C1081: M12 | D1081: 41974 | E1081: 234.812 | F1081: 0.8
A1082: CUUR0000SA0 | B1082: 2015 | C1082: M01 | D1082: 42005 | E1082: 233.707
A1083: CUUR0000SA0 | B1083: 2015 | C1083: M02 | D1083: 42036 | E1083: 234.722
A1084: CUUR0000SA0 | B1084: 2015 | C1084: M03 | D1084: 42064 | E1084: 236.119
A1085: CUUR0000SA0 | B1085: 2015 | C1085: M04 | D1085: 42095 | E1085: 236.599
A1086: CUUR0000SA0 | B1086: 2015 | C1086: M05 | D1086: 42125 | E1086: 237.805
A1087: CUUR0000SA0 | B1087: 2015 | C1087: M06 | D1087: 42156 | E1087: 238.638
A1088: CUUR0000SA0 | B1088: 2015 | C1088: M07 | D1088: 42186 | E1088: 238.654
A1089: CUUR0000SA0 | B1089: 2015 | C1089: M08 | D1089: 42217 | E1089: 238.316
A1090: CUUR0000SA0 | B1090: 2015 | C1090: M09 | D1090: 42248 | E1090: 237.945
A1091: CUUR0000SA0 | B1091: 2015 | C1091: M10 | D1091: 42278 | E1091: 237.838
A1092: CUUR0000SA0 | B1092: 2015 | C1092: M11 | D1092: 42309 | E1092: 237.336
A1093: CUUR0000SA0 | B1093: 2015 | C1093: M12 | D1093: 42339 | E1093: 236.525
A1094: CUUR0000SA0 | B1094: 2016 | C1094: M01 | D1094: 42370 | E1094: 236.916 | F1094: 1.4
A1095: CUUR0000SA0 | B1095: 2016 | C1095: M02 | D1095: 42401 | E1095: 237.111 | F1095: 1
...

Sheet Inflation
C4: Table of Historical Inflation Rates in Percent
C5: (1914-2025)
C7: Year | D7: Jan | E7: Feb | F7: Mar | G7: Apr | H7: May | I7: Jun | J7: Jul | K7: Aug | L7: Sep | M7: Oct | N7: Nov | O7: Dec | P7: Ave
C8: 1914 | D8: 2 | E8: 1 | F8: 1 | G8: 0 | H8: 2.1 | I8: 1 | J8: 1 | K8: 3 | L8: 2 | M8: 1 | N8: 1 | O8: 1 | P8: 1
C9: 1915 | D9: 1 | E9: 1 | F9: 0 | G9: 2 | H9: 2 | I9: 2 | J9: 1 | K9: -1 | L9: -1 | M9: 1 | N9: 1 | O9: 2 | P9: 1
C10: 1916 | D10: 3 | E10: 4 | F10: 6.1 | G10: 6 | H10: 5.9 | I10: 6.9 | J10: 6.9 | K10: 7.9 | L10: 9.9 | M10: 10.8 | N10: 11.7 | O10: 12.6 | P10: 7.9
C11: 1917 | D11: 12.5 | E11: 15.4 | F11: 14.3 | G11: 18.9 | H11: 19.6 | I11: 20.4 | J11: 18.5 | K11: 19.3 | L11: 19.8 | M11: 19.5 | N11: 17.4 | O11: 18.1 | P11: 17.4
C12: 1918 | D12: 19.7 | E12: 17.5 | F12: 16.7 | G12: 12.7 | H12: 13.3 | I12: 13.1 | J12: 18 | K12: 18.5 | L12: 18 | M12: 18.5 | N12: 20.7 | O12: 20.4 | P12: 18
C13: 1919 | D13: 17.9 | E13: 14.9 | F13: 17.1 | G13: 17.6 | H13: 16.6 | I13: 15 | J13: 15.2 | K13: 14.9 | L13: 13.4 | M13: 13.1 | N13: 13.5 | O13: 14.5 | P13: 14.6
C14: 1920 | D14: 17 | E14: 20.4 | F14: 20.1 | G14: 21.6 | H14: 21.9 | I14: 23.7 | J14: 19.5 | K14: 14.7 | L14: 12.4 | M14: 9.9 | N14: 7 | O14: 2.6 | P14: 15.6
C15: 1921 | D15: -1.6 | E15: -5.6 | F15: -7.1 | G15: -10.8 | H15: -14.1 | I15: -15.8 | J15: -14.9 | K15: -12.8 | L15: -12.5 | M15: -12.1 | N15: -12.1 | O15: -10.8 | P15: -10.5
C16: 1922 | D16: -11.1 | E16: -8.2 | F16: -8.7 | G16: -7.7 | H16: -5.6 | I16: -5.1 | J16: -5.1 | K16: -6.2 | L16: -5.1 | M16: -4.6 | N16: -3.4 | O16: -2.3 | P16: -6.1
C17: 1923 | D17: -0.6 | E17: -0.6 | F17: 0.6 | G17: 1.2 | H17: 1.2 | I17: 1.8 | J17: 2.4 | K17: 3 | L17: 3.6 | M17: 3.6 | N17: 3 | O17: 2.4 | P17: 1.8
C18: 1924 | D18: 3 | E18: 2.4 | F18: 1.8 | G18: 0.6 | H18: 0.6 | I18: 0 | J18: -0.6 | K18: -0.6 | L18: -0.6 | M18: -0.6 | N18: -0.6 | O18: 0 | P18: 0
C19: 1925 | D19: 0 | E19: 0 | F19: 1.2 | G19: 1.2 | H19: 1.8 | I19: 2.9 | J19: 3.5 | K19: 4.1 | L19: 3.5 | M19: 2.9 | N19: 4.7 | O19: 3.5 | P19: 2.3
... C118: 2024 | D118: 3.1 | E118: 3.2 | F118: 3.5 | G118: 3.4 | H118: 3.3 | I118: 3 | J118: 2.9 | K118: 2.5 | L118: 2.4 | M118: 2.6 | N118: 2.7 | O118: 2.9 | P118: 2.9
C119: 2025 | D119: 3 | E119: 2.8 | F119: 2.4 | G119: 2.3 | H119: 2.4 | I119: 2.7 | J119: 2.7 | K119: 2.9 | L119: 3 | M119: – (*) | N119: 2.7 | O119: Avail.
O120: Jan.
O121: 13
P123: =(SUM(P8:P118)/111)/100 -> 0.03263964

Sheet Sheet1
B3: todays $1000
B5: future amout | C5: years | D5: discount rate | E5: PV
B6: 1000 | C6: 5 | D6: 0.0326 | E6: =PV(D6,C6,B6,B6) -> -5397.7098
C9: =B6/(1+D6)^C6 -> 851.80345

Sheet Sheet2

Sheet index test
A1: CPI
B3: Base year | C3: Test Year | D3: Factor | E3: base price | H3: Equivalent cost
B4: =Cpi_index_inflation_montly_1925!E1154 -> 261.582 | C4: =Cpi_index_inflation_montly_1925!E1166 -> 281.148 | D4: =B4/C4 -> 0.93040676 | E4: 1000 | F4: =E4*D4 -> 930.40676 | H4: =C4/B4 -> 1.0747987 | I4: =E4*H4 -> 1074.7987

Sheet Salarys 2024
C2: State | D2: Average Salary | E2: Median Salary | F2: color
C3: Alabama | D3: 53400 | E3: 41350 | F3: R
C4: Alaska | D4: 69880 | E4: 56140 | F4: R
C5: Arizona | D5: 63040 | E5: 47680 | F5: R
C6: Arkansas | D6: 51250 | E6: 39060 | F6: R
C7: California | D7: 76960 | E7: 54030 | F7: B
C8: Colorado | D8: 71960 | E8: 54050 | F8: B
C9: Connecticut | D9: 73740 | E9: 56130 | F9: B
C10: Delaware | D10: 65990 | E10: 49280 | F10: B
C11: Florida | D11: 60210 | E11: 45070 | F11: R
C12: Georgia | D12: 61250 | E12: 45480 | F12: R
C13: Hawaii | D13: 65030 | E13: 50510 | F13: B
C14: Idaho | D14: 55640 | E14: 44240 | F14: R
... C20: Louisiana | D20: 53440 | E20: 41320 | F20: R
C21: Maine | D21: 60000 | E21: 47590
C22: Maryland | D22: 73620 | E22: 55810
C23: Massachusetts | D23: 80330 | E23: 60690
C24: Michigan | D24: 60600 | E24: 46940 | F24: R
C25: Minnesota | D25: 66700 | E25: 50880
C26: Mississippi | D26: 47570 | E26: 37500 | F26: R
C27: Missouri | D27: 57580 | E27: 45080 | F27: R
C28: Montana | D28: 55920 | E28: 45690 | F28: R
C29: Nebraska | D29: 58080 | E29: 46440 | F29: R
C30: Nevada | D30: 58900 | E30: 44810 | F30: R
C31: New Hampshire | D31: 66110 | E31: 49980
C32: New Jersey | D32: 73980 | E32: 54860
C33: New Mexico | D33: 57520 | E33: 43620
C34: New York | D34: 78620 | E34: 56840
C35: North Carolina | D35: 59730 | E35: 45440 | F35: R
C36: North Dakota | D36: 59050 | E36: 48830 | F36: R
C37: Ohio | D37: 59890 | E37: 46690 | F37: R
C38: Oklahoma | D38: 53450 | E38: 41480 | F38: R
C39: Oregon | D39: 66710 | E39: 50010
C40: Pennsylvania | D40: 61920 | E40: 47430 | F40: R
C41: Rhode Island | D41: 66610 | E41: 50970
C42: South Carolina | D42: 54250 | E42: 42220 | F42: R
C43: South Dakota | D43: 53230 | E43: 43680 | F43: R
C44: Tennessee | D44: 56030 | E44: 43820 | F44: R
C45: Texas | D45: 61240 | E45: 45970 | F45: R
C46: Utah | D46: 61070 | E46: 47020 | F46: R
C47: Vermont | D47: 62780 | E47: 49630
C48: Virginia | D48: 70050 | E48: 49920
C49: Washington | D49: 78130 | E49: 59920
C50: West Virginia | D50: 52200 | E50: 39770 | F50: R
C51: Wisconsin | D51: 59500 | E51: 47590 | F51: R
C52: Wyoming | D52: 57930 | E52: 47250 | F52: R
C54: Source: Bureau of Labor Statistics, “Occupational Employment and Wage Statistics,” May 2023.

Sheet s&p_returns
B1: Year | C1: Return in %
B2: Column1 | C2: Column2
B3: 2024 | C3: 25.02
B4: 2023 | C4: 26.29
B5: 2022 | C5: -18.11
B6: 2021 | C6: 28.71
B7: 2020 | C7: 18.4
B8: 2019 | C8: 31.49
B9: 2018 | C9: -4.38
B10: 2017 | C10: 21.83
B11: 2016 | C11: 11.96
B12: 2015 | C12: 1.38
B13: 2014 | C13: 13.69
B14: 2013 | C14: 32.39
... B101: 1926 | C101: 11.62

Sheet SSI cola for the year
B3: Social Security Cost-Of-Living Adjustments
B4: Year | C4: COLA
B5: 1975 | C5: 8 | E5: Average | F5: =SUM(C5:C55)/((B55-B5)+1) -> 3.7294118
B6: 1976 | C6: 6.4
B7: 1977 | C7: 5.9
B8: 1978 | C8: 6.5
B9: 1979 | C9: 9.9
B10: 1980 | C10: 14.3
B11: 1981 | C11: 11.2
B12: 1982 | C12: 7.4
B13: 1983 | C13: 3.5
B14: 1984 | C14: 3.5
B15: 1985 | C15: 3.1
B16: 1986 | C16: 1.3
B17: 1987 | C17: 4.2
... B28: 1998 | C28: 1.3
B29: 1999 a | C29: 2.5
B30: 2000 | C30: 3.5
B31: 2001 | C31: 2.6
B32: 2002 | C32: 1.4
B33: 2003 | C33: 2.1
B34: 2004 | C34: 2.7
B35: 2005 | C35: 4.1
B36: 2006 | C36: 3.3
B37: 2007 | C37: 2.3
B38: 2008 | C38: 5.8
B39: 2009 | C39: 0
B40: 2010 | C40: 0
B41: 2011 | C41: 3.6
... B55: 2025 | C55: 2.8
