Workbook
Name TimeSeries: 'SSI cola for the year'!$B$3

Sheet Main
A3: Full Retirement Age Benefit | B3: 2822
A4: Life Expectancy | B4: 22
A5: Cola | B5: 0.025 | D5: Average Cola since 1975 = | E5: ='SS Benefit Cal'!F3 -> 3.7294118
A6: Rate of Return | B6: 0.025 | D6: Average CPI since 1914 | E6: =Inflation!P123 -> 0.03263964
A7: Discount Rate | B7: 0.025
A10: AGE | B10: Monthly benefit | C10: % change | D10: year2year change
A11: 62 | B11: =$B$3*C11 -> 1975.4 | C11: 0.7
A12: 63 | B12: =$B$3*C12 -> 2116.5 | C12: 0.75 | D12: =(B12-B11)/B11 -> 0.071428571
A13: 64 | B13: =$B$3*C13 -> 2257.6 | C13: 0.8 | D13: =(B13-B12)/B12 -> 0.066666667
A14: 65 | B14: =$B$3*C14 -> 2446.674 | C14: 0.867 | D14: =(B14-B13)/B13 -> 0.08375
A15: 66 | B15: =$B$3*C15 -> 2632.926 | C15: 0.933 | D15: =(B15-B14)/B14 -> 0.076124567
A16: 67 | B16: =$B$3*C16 -> 2822 | C16: 1 | D16: =(B16-B15)/B15 -> 0.071811361 | G16: ="Monthly benefit with " & B5*100 & "% Cola " -> Monthly benefit with 2.5% Cola
A17: 68 | B17: =$B$3*C17 -> 3047.76 | C17: 1.08 | D17: =(B17-B16)/B16 -> 0.08
A18: 69 | B18: =$B$3*C18 -> 3273.52 | C18: 1.16 | D18: =(B18-B17)/B17 -> 0.074074074
A19: 70 | B19: =$B$3*C19 -> 3499.28 | C19: 1.24 | D19: =(B19-B18)/B18 -> 0.068965517
B23: Monthy Benefit taken at 62 (Cola) | C23: Monthly Benefit taken at 67 (cola) | D23: Monthly Benefit taken at 70 (cola)
A24: 62 | B24: =B11 -> 1975.4
A25: 63 | B25: =B24*(1+$B$5) -> 2024.785
A26: 64 | B26: =B25*(1+$B$5) -> 2075.4046
A27: 65 | B27: =B26*(1+$B$5) -> 2127.2897
A28: 66 | B28: =B27*(1+$B$5) -> 2180.472
A29: 67 | B29: =B28*(1+$B$5) -> 2234.9838 | C29: =B16 -> 2822
A30: 68 | B30: =B29*(1+$B$5) -> 2290.8584 | C30: =C29*(1+$B$5) -> 2892.55
A31: 69 | B31: =B30*(1+$B$5) -> 2348.1298 | C31: =C30*(1+$B$5) -> 2964.8637
A32: 70 | B32: =B31*(1+$B$5) -> 2406.8331 | C32: =C31*(1+$B$5) -> 3038.9853 | D32: =B19 -> 3499.28
A33: 71 | B33: =B32*(1+$B$5) -> 2467.0039 | C33: =C32*(1+$B$5) -> 3114.96 | D33: =D32*(1+$B$5) -> 3586.762
A34: 72 | B34: =B33*(1+$B$5) -> 2528.679 | C34: =C33*(1+$B$5) -> 3192.834 | D34: =D33*(1+$B$5) -> 3676.431
A35: 73 | B35: =B34*(1+$B$5) -> 2591.896 | C35: =C34*(1+$B$5) -> 3272.6548 | D35: =D34*(1+$B$5) -> 3768.3418
A36: 74 | B36: =B35*(1+$B$5) -> 2656.6934 | C36: =C35*(1+$B$5) -> 3354.4712 | D36: =D35*(1+$B$5) -> 3862.5504
A37: 75 | B37: =B36*(1+$B$5) -> 2723.1107 | C37: =C36*(1+$B$5) -> 3438.333 | D37: =D36*(1+$B$5) -> 3959.1141
A38: 76 | B38: =B37*(1+$B$5) -> 2791.1885 | C38: =C37*(1+$B$5) -> 3524.2913 | D38: =D37*(1+$B$5) -> 4058.092
A39: 77 | B39: =B38*(1+$B$5) -> 2860.9682 | C39: =C38*(1+$B$5) -> 3612.3986 | D39: =D38*(1+$B$5) -> 4159.5443
A40: 78 | B40: =B39*(1+$B$5) -> 2932.4924 | C40: =C39*(1+$B$5) -> 3702.7085 | D40: =D39*(1+$B$5) -> 4263.5329
A41: 79 | B41: =B40*(1+$B$5) -> 3005.8047 | C41: =C40*(1+$B$5) -> 3795.2763 | D41: =D40*(1+$B$5) -> 4370.1212
A42: 80 | B42: =B41*(1+$B$5) -> 3080.9498 | C42: =C41*(1+$B$5) -> 3890.1582 | D42: =D41*(1+$B$5) -> 4479.3742
A43: 81 | B43: =B42*(1+$B$5) -> 3157.9736 | C43: =C42*(1+$B$5) -> 3987.4121 | D43: =D42*(1+$B$5) -> 4591.3586
A44: 82 | B44: =B43*(1+$B$5) -> 3236.9229 | C44: =C43*(1+$B$5) -> 4087.0974 | D44: =D43*(1+$B$5) -> 4706.1426
... A62: 100 | B62: =B61*(1+$B$5) -> 5048.495 | C62: =C61*(1+$B$5) -> 6374.4771 | D62: =D61*(1+$B$5) -> 7339.9763
A65: Age | B65: Total take at 62. No Cola | C65: Total take at 67 No cola | D65: 70 total No Cola | F65: Yearly payment no Cola take@62 | G65: Yearly payment no Cola take@67 | H65: Yearly payment no Cola take@70
A66: 62 | B66: =B24*12 -> 23704.8 | F66: =B66 -> 23704.8 | G66: =0 -> 0 | H66: 0
A67: 63 | B67: =B66+B66 -> 47409.6 | F67: =F66 -> 23704.8 | G67: =0 -> 0 | H67: 0 | M67: ="Running total SS Benefit payout, No cola applied, No Time Value of money adjustment" -> Running total SS Benefit payout, No cola applied, No Time Value of money adjustment
A68: 64 | B68: =B67+$B$66 -> 71114.4 | F68: =F67 -> 23704.8 | G68: =0 -> 0 | H68: 0
A69: 65 | B69: =B68+$B$66 -> 94819.2 | F69: =F68 -> 23704.8 | G69: =0 -> 0 | H69: 0
A70: 66 | B70: =B69+$B$66 -> 118524 | F70: =F69 -> 23704.8 | G70: =0 -> 0 | H70: 0
A71: 67 | B71: =B70+$B$66 -> 142228.8 | C71: =C29 *12 -> 33864 | F71: =F70 -> 23704.8 | G71: =C71 -> 33864 | H71: 0
A72: 68 | B72: =B71+$B$66 -> 165933.6 | C72: =C71+$C$71 -> 67728 | F72: =F71 -> 23704.8 | G72: =G71 -> 33864 | H72: 0
A73: 69 | B73: =B72+$B$66 -> 189638.4 | C73: =C72+$C$71 -> 101592 | F73: =F72 -> 23704.8 | G73: =G72 -> 33864 | H73: 0
A74: 70 | B74: =B73+$B$66 -> 213343.2 | C74: =C73+$C$71 -> 135456 | D74: =D32*12 -> 41991.36 | F74: =F73 -> 23704.8 | G74: =G73 -> 33864 | H74: =D74 -> 41991.36
A75: 71 | B75: =B74+$B$66 -> 237048 | C75: =C74+$C$71 -> 169320 | D75: =D74+D74 -> 83982.72 | F75: =F74 -> 23704.8 | G75: =G74 -> 33864 | H75: =H74 -> 41991.36
A76: 72 | B76: =B75+$B$66 -> 260752.8 | C76: =C75+$C$71 -> 203184 | D76: =D75+$D$74 -> 125974.08 | F76: =F75 -> 23704.8 | G76: =G75 -> 33864 | H76: =H75 -> 41991.36
A77: 73 | B77: =B76+$B$66 -> 284457.6 | C77: =C76+$C$71 -> 237048 | D77: =D76+$D$74 -> 167965.44 | F77: =F76 -> 23704.8 | G77: =G76 -> 33864 | H77: =H76 -> 41991.36
A78: 74 | B78: =B77+$B$66 -> 308162.4 | C78: =C77+$C$71 -> 270912 | D78: =D77+$D$74 -> 209956.8 | F78: =F77 -> 23704.8 | G78: =G77 -> 33864 | H78: =H77 -> 41991.36
A79: 75 | B79: =B78+$B$66 -> 331867.2 | C79: =C78+$C$71 -> 304776 | D79: =D78+$D$74 -> 251948.16 | F79: =F78 -> 23704.8 | G79: =G78 -> 33864 | H79: =H78 -> 41991.36
A80: 76 | B80: =B79+$B$66 -> 355572 | C80: =C79+$C$71 -> 338640 | D80: =D79+$D$74 -> 293939.52 | F80: =F79 -> 23704.8 | G80: =G79 -> 33864 | H80: =H79 -> 41991.36
A81: 77 | B81: =B80+$B$66 -> 379276.8 | C81: =C80+$C$71 -> 372504 | D81: =D80+$D$74 -> 335930.88 | F81: =F80 -> 23704.8 | G81: =G80 -> 33864 | H81: =H80 -> 41991.36
A82: 78 | B82: =B81+$B$66 -> 402981.6 | C82: =C81+$C$71 -> 406368 | D82: =D81+$D$74 -> 377922.24 | F82: =F81 -> 23704.8 | G82: =G81 -> 33864 | H82: =H81 -> 41991.36
A83: 79 | B83: =B82+$B$66 -> 426686.4 | C83: =C82+$C$71 -> 440232 | D83: =D82+$D$74 -> 419913.6 | F83: =F82 -> 23704.8 | G83: =G82 -> 33864 | H83: =H82 -> 41991.36
A84: 80 | B84: =B83+$B$66 -> 450391.2 | C84: =C83+$C$71 -> 474096 | D84: =D83+$D$74 -> 461904.96 | F84: =F83 -> 23704.8 | G84: =G83 -> 33864 | H84: =H83 -> 41991.36
A85: 81 | B85: =B84+$B$66 -> 474096 | C85: =C84+$C$71 -> 507960 | D85: =D84+$D$74 -> 503896.32 | F85: =F84 -> 23704.8 | G85: =G84 -> 33864 | H85: =H84 -> 41991.36
A86: 82 | B86: =B85+$B$66 -> 497800.8 | C86: =C85+$C$71 -> 541824 | D86: =D85+$D$74 -> 545887.68 | F86: =F85 -> 23704.8 | G86: =G85 -> 33864 | H86: =H85 -> 41991.36
A87: 83 | B87: =B86+$B$66 -> 521505.6 | C87: =C86+$C$71 -> 575688 | D87: =D86+$D$74 -> 587879.04 | F87: =F86 -> 23704.8 | G87: =G86 -> 33864 | H87: =H86 -> 41991.36
... A103: 99 | B103: =B102+$B$66 -> 900782.4 | C103: =C102+$C$71 -> 1117512 | D103: =D102+$D$74 -> 1259740.8 | F103: =F102 -> 23704.8 | G103: =G102 -> 33864 | H103: =H102 -> 41991.36
A104: 100 | B104: =B103+$B$66 -> 924487.2 | C104: =C103+$C$71 -> 1151376 | D104: =D103+$D$74 -> 1301732.2 | F104: =F103 -> 23704.8 | G104: =G103 -> 33864 | H104: =H103 -> 41991.36 | K104: ="Totals with Cola of " & B5*100 & "% Rate of Return = 0.0 % " -> Totals with Cola of 2.5% Rate of Return = 0.0 %
A107: Age | B107: 62 yearly benefit | C107: 62 total with Cola | D107: 67 yearly benefit w Cola | E107: 67 total with Cola | F107: 70 yearly benefit w Cola | G107: 70 total w cola | H107: 62 total in todays $'s | I107: 67 total in todays $'s | J107: 70 total in todays $'S | K107: ="Discount rate = " & B7*100 & " %" -> Discount rate = 2.5 % | L107: ="Rate of return = " & B6*100 & " %" -> Rate of return = 2.5 %
A108: 62 | B108: =B66 -> 23704.8 | C108: =B108 -> 23704.8 | D108: 0 | E108: 0 | F108: 0 | G108: 0 | H108: =C108 -> 23704.8 | I108: =D108 -> 0 | J108: 0 | K108: 1000 | L108: =1000 -> 1000
A109: 63 | B109: =B108+(B108*$B$5) -> 24297.42 | C109: =C108+B109 -> 48002.22 | D109: 0 | E109: 0 | F109: 0 | G109: 0 | H109: =C109/(1+$B$7)^(A109-$A$108) -> 46831.434 | I109: =D109 -> 0 | J109: 0 | K109: =$K$108/(1+$B$7)^(A109-$A$108) -> 975.60976 | L109: =$L$108*(1+$B$6)^(A109-$A$108) -> 1025
A110: 64 | B110: =B109+(B109*$B$5) -> 24904.855 | C110: =C109+B110 -> 72907.076 | D110: 0 | E110: 0 | F110: 0 | G110: 0 | H110: =C110/(1+$B$7)^(A110-$A$108) -> 69394.004 | I110: =D110 -> 0 | J110: 0 | K110: =$K$108/(1+$B$7)^(A110-$A$108) -> 951.8144 | L110: =$L$108*(1+$B$6)^(A110-$A$108) -> 1050.625
A111: 65 | B111: =B110+(B110*$B$5) -> 25527.477 | C111: =C110+B111 -> 98434.552 | D111: 0 | E111: 0 | F111: 0 | G111: 0 | H111: =C111/(1+$B$7)^(A111-$A$108) -> 91406.267 | I111: =D111 -> 0 | J111: 0 | K111: =$K$108/(1+$B$7)^(A111-$A$108) -> 928.59941 | L111: =$L$108*(1+$B$6)^(A111-$A$108) -> 1076.8906
A112: 66 | B112: =B111+(B111*$B$5) -> 26165.664 | C112: =C111+B112 -> 124600.22 | D112: 0 | E112: 0 | F112: 0 | G112: 0 | H112: =C112/(1+$B$7)^(A112-$A$108) -> 112881.65 | I112: =D112 -> 0 | J112: 0 | K112: =$K$108/(1+$B$7)^(A112-$A$108) -> 905.95064 | L112: =$L$108*(1+$B$6)^(A112-$A$108) -> 1103.8129
A113: 67 | B113: =B112+(B112*$B$5) -> 26819.805 | C113: =C112+B113 -> 151420.02 | D113: =C71 -> 33864 | E113: =D113 -> 33864 | F113: 0 | G113: 0 | H113: =C113/(1+$B$7)^(A113-$A$108) -> 133833.24 | I113: =E113 -> 33864 | J113: 0 | K113: =$K$108/(1+$B$7)^(A113-$A$108) -> 883.85429 | L113: =$L$108*(1+$B$6)^(A113-$A$108) -> 1131.4082
A114: 68 | B114: =B113+(B113*$B$5) -> 27490.301 | C114: =C113+B114 -> 178910.32 | D114: =D113+D113*$B$5 -> 34710.6 | E114: =E113+D114 -> 68574.6 | F114: 0 | G114: 0 | H114: =C114/(1+$B$7)^(A114-$A$108) -> 154273.81 | I114: =E114/(1+$B$7)^(A114-$A$108) -> 59131.663 | J114: 0 | K114: =$K$108/(1+$B$7)^(A114-$A$108) -> 862.29687 | L114: =$L$108*(1+$B$6)^(A114-$A$108) -> 1159.6934
A115: 69 | B115: =B114+(B114*$B$5) -> 28177.558 | C115: =C114+B115 -> 207087.88 | D115: =D114+D114*$B$5 -> 35578.365 | E115: =E114+D115 -> 104152.96 | F115: 0 | G115: 0 | H115: =C115/(1+$B$7)^(A115-$A$108) -> 174215.83 | I115: =E115/(1+$B$7)^(A115-$A$108) -> 87620.269 | J115: 0 | K115: =$K$108/(1+$B$7)^(A115-$A$108) -> 841.26524 | L115: =$L$108*(1+$B$6)^(A115-$A$108) -> 1188.6858
A116: 70 | B116: =B115+(B115*$B$5) -> 28881.997 | C116: =C115+B116 -> 235969.88 | D116: =D115+D115*$B$5 -> 36467.824 | E116: =E115+D116 -> 140620.79 | F116: =D74 -> 41991.36 | G116: =D74 -> 41991.36 | H116: =C116/(1+$B$7)^(A116-$A$108) -> 193671.47 | I116: =E116/(1+$B$7)^(A116-$A$108) -> 115414.03 | J116: =G116 -> 41991.36 | K116: =$K$108/(1+$B$7)^(A116-$A$108) -> 820.74657 | L116: =$L$108*(1+$B$6)^(A116-$A$108) -> 1218.4029
A117: 71 | B117: =B116+(B116*$B$5) -> 29604.047 | C117: =C116+B117 -> 265573.92 | D117: =D116+D116*$B$5 -> 37379.52 | E117: =E116+D117 -> 178000.31 | F117: =F116 +F116*$B$5 -> 43041.144 | G117: =G116+F117 -> 85032.504 | H117: =C117/(1+$B$7)^(A117-$A$108) -> 212652.57 | I117: =E117/(1+$B$7)^(A117-$A$108) -> 142529.9 | J117: =G117/(1+$B$7)^(A117-$A$108) -> 68087.938 | K117: =$K$108/(1+$B$7)^(A117-$A$108) -> 800.72836 | L117: =$L$108*(1+$B$6)^(A117-$A$108) -> 1248.863 | N117: =PV(B7,A117-A108,0,G117) -> -68087.938
A118: 72 | B118: =B117+(B117*$B$5) -> 30344.148 | C118: =C117+B118 -> 295918.07 | D118: =D117+D117*$B$5 -> 38314.008 | E118: =E117+D118 -> 216314.32 | F118: =F117 +F117*$B$5 -> 44117.173 | G118: =G117+F118 -> 129149.68 | H118: =C118/(1+$B$7)^(A118-$A$108) -> 231170.73 | I118: =E118/(1+$B$7)^(A118-$A$108) -> 168984.4 | J118: =G118/(1+$B$7)^(A118-$A$108) -> 100891.52 | K118: =$K$108/(1+$B$7)^(A118-$A$108) -> 781.1984 | L118: =$L$108*(1+$B$6)^(A118-$A$108) -> 1280.0845
A119: 73 | B119: =B118+(B118*$B$5) -> 31102.752 | C119: =C118+B119 -> 327020.82 | D119: =D118+D118*$B$5 -> 39271.858 | E119: =E118+D119 -> 255586.17 | F119: =F118 +F118*$B$5 -> 45220.102 | G119: =G118+F119 -> 174369.78 | H119: =C119/(1+$B$7)^(A119-$A$108) -> 249237.21 | I119: =E119/(1+$B$7)^(A119-$A$108) -> 194793.67 | J119: =G119/(1+$B$7)^(A119-$A$108) -> 132895.02 | K119: =$K$108/(1+$B$7)^(A119-$A$108) -> 762.14478 | L119: =$L$108*(1+$B$6)^(A119-$A$108) -> 1312.0867
A120: 74 | B120: =B119+(B119*$B$5) -> 31880.321 | C120: =C119+B120 -> 358901.14 | D120: =D119+D119*$B$5 -> 40253.654 | E120: =E119+D120 -> 295839.83 | F120: =F119 +F119*$B$5 -> 46350.604 | G120: =G119+F120 -> 220720.38 | H120: =C120/(1+$B$7)^(A120-$A$108) -> 266863.06 | I120: =E120/(1+$B$7)^(A120-$A$108) -> 219973.45 | J120: =G120/(1+$B$7)^(A120-$A$108) -> 164117.94 | K120: =$K$108/(1+$B$7)^(A120-$A$108) -> 743.55589 | L120: =$L$108*(1+$B$6)^(A120-$A$108) -> 1344.8888
A121: 75 | B121: =B120+(B120*$B$5) -> 32677.329 | C121: =C120+B121 -> 391578.47 | D121: =D120+D120*$B$5 -> 41259.996 | E121: =E120+D121 -> 337099.82 | F121: =F120 +F120*$B$5 -> 47509.37 | G121: =G120+F121 -> 268229.75 | H121: =C121/(1+$B$7)^(A121-$A$108) -> 284059 | I121: =E121/(1+$B$7)^(A121-$A$108) -> 244539.08 | J121: =G121/(1+$B$7)^(A121-$A$108) -> 194579.33 | K121: =$K$108/(1+$B$7)^(A121-$A$108) -> 725.42038 | L121: =$L$108*(1+$B$6)^(A121-$A$108) -> 1378.511
A122: 76 | B122: =B121+(B121*$B$5) -> 33494.262 | C122: =C121+B122 -> 425072.74 | D122: =D121+D121*$B$5 -> 42291.496 | E122: =E121+D122 -> 379391.32 | F122: =F121 +F121*$B$5 -> 48697.104 | G122: =G121+F122 -> 316926.86 | H122: =C122/(1+$B$7)^(A122-$A$108) -> 300835.53 | I122: =E122/(1+$B$7)^(A122-$A$108) -> 268505.56 | J122: =G122/(1+$B$7)^(A122-$A$108) -> 224297.76 | K122: =$K$108/(1+$B$7)^(A122-$A$108) -> 707.7272 | L122: =$L$108*(1+$B$6)^(A122-$A$108) -> 1412.9738
A123: 77 | B123: =B122+(B122*$B$5) -> 34331.618 | C123: =C122+B123 -> 459404.35 | D123: =D122+D122*$B$5 -> 43348.783 | E123: =E122+D123 -> 422740.1 | F123: =F122 +F122*$B$5 -> 49914.531 | G123: =G122+F123 -> 366841.39 | H123: =C123/(1+$B$7)^(A123-$A$108) -> 317202.88 | I123: =E123/(1+$B$7)^(A123-$A$108) -> 291887.48 | J123: =G123/(1+$B$7)^(A123-$A$108) -> 253291.34 | K123: =$K$108/(1+$B$7)^(A123-$A$108) -> 690.46556 | L123: =$L$108*(1+$B$6)^(A123-$A$108) -> 1448.2982
A124: 78 | B124: =B123+(B123*$B$5) -> 35189.909 | C124: =C123+B124 -> 494594.26 | D124: =D123+D123*$B$5 -> 44432.503 | E124: =E123+D124 -> 467172.61 | F124: =F123 +F123*$B$5 -> 51162.395 | G124: =G123+F124 -> 418003.78 | H124: =C124/(1+$B$7)^(A124-$A$108) -> 333171.03 | I124: =E124/(1+$B$7)^(A124-$A$108) -> 314699.12 | J124: =G124/(1+$B$7)^(A124-$A$108) -> 281577.77 | K124: =$K$108/(1+$B$7)^(A124-$A$108) -> 673.62493 | L124: =$L$108*(1+$B$6)^(A124-$A$108) -> 1484.5056
A125: 79 | B125: =B124+(B124*$B$5) -> 36069.657 | C125: =C124+B125 -> 530663.92 | D125: =D124+D124*$B$5 -> 45543.315 | E125: =E124+D125 -> 512715.92 | F125: =F124 +F124*$B$5 -> 52441.455 | G125: =G124+F125 -> 470445.24 | H125: =C125/(1+$B$7)^(A125-$A$108) -> 348749.7 | I125: =E125/(1+$B$7)^(A125-$A$108) -> 336954.37 | J125: =G125/(1+$B$7)^(A125-$A$108) -> 309174.28 | K125: =$K$108/(1+$B$7)^(A125-$A$108) -> 657.19506 | L125: =$L$108*(1+$B$6)^(A125-$A$108) -> 1521.6183
A126: 80 | B126: =B125+(B125*$B$5) -> 36971.398 | C126: =C125+B126 -> 567635.32 | D126: =D125+D125*$B$5 -> 46681.898 | E126: =E125+D126 -> 559397.82 | F126: =F125 +F125*$B$5 -> 53752.491 | G126: =G125+F126 -> 524197.73 | H126: =C126/(1+$B$7)^(A126-$A$108) -> 363948.41 | I126: =E126/(1+$B$7)^(A126-$A$108) -> 358666.81 | J126: =G126/(1+$B$7)^(A126-$A$108) -> 336097.71 | K126: =$K$108/(1+$B$7)^(A126-$A$108) -> 641.16591 | L126: =$L$108*(1+$B$6)^(A126-$A$108) -> 1559.6587
A127: 81 | B127: =B126+(B126*$B$5) -> 37895.683 | C127: =C126+B127 -> 605531 | D127: =D126+D126*$B$5 -> 47848.945 | E127: =E126+D127 -> 607246.76 | F127: =F126 +F126*$B$5 -> 55096.303 | G127: =G126+F127 -> 579294.03 | H127: =C127/(1+$B$7)^(A127-$A$108) -> 378776.42 | I127: =E127/(1+$B$7)^(A127-$A$108) -> 379849.68 | J127: =G127/(1+$B$7)^(A127-$A$108) -> 362364.47 | K127: =$K$108/(1+$B$7)^(A127-$A$108) -> 625.52772 | L127: =$L$108*(1+$B$6)^(A127-$A$108) -> 1598.6502
A128: 82 | B128: =B127+(B127*$B$5) -> 38843.075 | C128: =C127+B128 -> 644374.07 | D128: =D127+D127*$B$5 -> 49045.169 | E128: =E127+D128 -> 656291.93 | F128: =F127 +F127*$B$5 -> 56473.711 | G128: =G127+F128 -> 635767.74 | H128: =C128/(1+$B$7)^(A128-$A$108) -> 393242.77 | I128: =E128/(1+$B$7)^(A128-$A$108) -> 400515.9 | J128: =G128/(1+$B$7)^(A128-$A$108) -> 387990.58 | K128: =$K$108/(1+$B$7)^(A128-$A$108) -> 610.27094 | L128: =$L$108*(1+$B$6)^(A128-$A$108) -> 1638.6164
A129: 83 | B129: =B128+(B128*$B$5) -> 39814.152 | C129: =C128+B129 -> 684188.23 | D129: =D128+D128*$B$5 -> 50271.298 | E129: =E128+D129 -> 706563.23 | F129: =F128 +F128*$B$5 -> 57885.554 | G129: =G128+F129 -> 693653.3 | H129: =C129/(1+$B$7)^(A129-$A$108) -> 407356.29 | I129: =E129/(1+$B$7)^(A129-$A$108) -> 420678.06 | J129: =G129/(1+$B$7)^(A129-$A$108) -> 412991.66 | K129: =$K$108/(1+$B$7)^(A129-$A$108) -> 595.38629 | L129: =$L$108*(1+$B$6)^(A129-$A$108) -> 1679.5819
... A146: 100 | B146: =B145+(B145*$B$5) -> 60581.941 | C146: =C145+B146 -> 1535667.6 | D146: =D145+D145*$B$5 -> 76493.726 | E146: =E145+D146 -> 1781682.7 | F146: =F145 +F145*$B$5 -> 88079.715 | G146: =G145+F146 -> 1931613.9 | H146: =C146/(1+$B$7)^(A146-$A$108) -> 600883.57 | I146: =E146/(1+$B$7)^(A146-$A$108) -> 697145.6 | J146: =G146/(1+$B$7)^(A146-$A$108) -> 755811.41 | K146: =$K$108/(1+$B$7)^(A146-$A$108) -> 391.28492 | L146: =$L$108*(1+$B$6)^(A146-$A$108) -> 2555.6824
L148: ="Totals with Cola of " & B5*100 & "% Rate of Return = " & B6*100 & "% " -> Totals with Cola of 2.5% Rate of Return = 2.5%
A152: Age | B152: 62, yearly benefit with cola | C152: 62-69 benefits, discount rate | D152: 62, invest + benefit->total | E152: 67, cola, invest total | F152: 70, cola, invest total | G152: 70 total w cola, invest rate
A153: 62 | B153: =B108 -> 23704.8 | C153: =B108 -> 23704.8 | D153: =C153 -> 23704.8 | E153: 0 | F153: 0 | G153: 0
A154: 63 | B154: =B109 -> 24297.42 | C154: =B109+(1+$B$6)*C153 -> 48594.84 | D154: =C154 -> 48594.84 | E154: 0 | F154: 0 | G154: 0
A155: 64 | B155: =B110 -> 24904.855 | C155: =B110+(1+$B$6)*C154 -> 74714.566 | D155: =C155 -> 74714.566 | E155: 0 | F155: 0 | G155: 0
A156: 65 | B156: =B111 -> 25527.477 | C156: =B111+(1+$B$6)*C155 -> 102109.91 | D156: =C156 -> 102109.91 | E156: 0 | F156: 0 | G156: 0
A157: 66 | B157: =B112 -> 26165.664 | C157: =B112+(1+$B$6)*C156 -> 130828.32 | D157: =C157 -> 130828.32 | E157: 0 | F157: 0 | G157: 0
A158: 67 | B158: =B113 -> 26819.805 | C158: =B113+(1+$B$6)*C157 -> 160918.83 | D158: =C158 -> 160918.83 | E158: =D113 -> 33864 | F158: 0 | G158: 0
A159: 68 | B159: =B114 -> 27490.301 | C159: =B114+(1+$B$6)*C158 -> 192432.1 | D159: =C159 -> 192432.1 | E159: =E158*(1+$B$6)+D114 -> 69421.2 | F159: 0 | G159: 0
A160: 69 | B160: =B115 -> 28177.558 | C160: =B115+(1+$B$6)*C159 -> 225420.46 | D160: =C160 -> 225420.46 | E160: =E159*(1+$B$6)+D115 -> 106735.1 | F160: 0 | G160: 0
A161: 70 | B161: =B116 -> 28881.997 | C161: =(1+$B$6)*C160 -> 231055.98 | D161: =B161+(1+$B$6)*D160 -> 259937.97 | E161: =E160*(1+$B$6)+D116 -> 145871.3 | F161: 0 | G161: =G116 -> 41991.36
A162: 71 | B162: =B117 -> 29604.047 | C162: =(1+$B$6)*C161 -> 236832.38 | D162: =B162+(1+$B$6)*D161 -> 296040.47 | E162: =E161*(1+$B$6)+D117 -> 186897.6 | F162: 0 | G162: =G161*(1+$B$6)+F117 -> 86082.288
A163: 72 | B163: =B118 -> 30344.148 | C163: =(1+$B$6)*C162 -> 242753.18 | D163: =B163+(1+$B$6)*D162 -> 333785.63 | E163: =E162*(1+$B$6)+D118 -> 229884.05 | F163: 0 | G163: =G162*(1+$B$6)+F118 -> 132351.52
...

Sheet SS Benefit Cal
A1: Social Security payout
B2: FRA | C2: =Main!B3 -> 2822
B3: Years for PV, NPV | C3: =Main!B4 -> 22 | E3: Average Cola since 1975 | F3: ='SSI cola for the year'!F5 -> 3.7294118
B4: Cola | C4: =Main!B5 -> 0.025
B5: Rate of Return | C5: =Main!B6 -> 0.025 | E5: AverageCPI since 1914 | F5: =Main!E6 -> 0.03263964
B6: Discount Rate | C6: =Main!B7 -> 0.025
B8: AGE | C8: Monthy benefit | D8: % change | E8: year2year change | G8: Monthy Benefit taken at 62 (Cola) | H8: Monthly Benefit taken at 67 (cola) | I8: Monthly Benefit taken at 70 (cola) | K8: Total take at 62. No Cola | L8: Total take at 67 No cola | M8: 70 total No Cola | N8: 62 yearly benefit | O8: 62 total with Cola | P8: 67 yearly benefit w Cola | Q8: 67 total with Cola | R8: 70 yearly benefit w Cola | S8: 70 total w cola | T8: 62,cola, invest,total | U8: 67, cola, invest total | V8: 70, cola, invest total | W8: Total take 62 compare to 70, cola, rate of return | X8: 70 total w cola | Z8: PV take at 62, No Cola | AA8: PV take at 67, No Cola | AB8: PV take at 70, no cola | AC8: NPV take at 62, with Cola | AD8: NPV take at , 67 with Cola | AE8: NPV take at 70, with Cola | AF8: Take at 70, Loss of future gains/losses. | AG8: Take at 67, Loss of future gains/losses | AH8: PV of loss at 70 | AI8: PV of Loss at 67
B9: 62 | C9: =C2*D9 -> 1975.4 | D9: 0.7 | G9: =C9 -> 1975.4 | K9: =$C$9*12 -> 23704.8 | N9: =K9 -> 23704.8 | O9: =K9 -> 23704.8 | P9: 0 | Q9: 0 | R9: 0 | S9: 0 | T9: =O9 -> 23704.8 | U9: =Q9 -> 0 | V9: =S9 -> 0 | W9: =T9 -> 23704.8 | X9: 0 | Z9: =PV($C$5,$C$3,K9,,0) -> -397420.77 | AA9: =PV($C$5,C3-5,L14) -> -464349.86 | AB9: =PV($C$5,$C$3-8,M17) -> -490917.3 | AC9: =NPV($C$5,N9:N34) -> 601292.49 | AD9: =NPV($C$5,P9:P34) -> 613217.24 | AE9: =NPV($C$5,R9:R34) -> 605226.11 | AF9: =FV($C$5,$C$3-8,,T17) -> -326476.05 | AG9: =FV($C$5,$C$3-5,,T14) -> -244857.03 | AH9: =AF9/(1+$C$5)^($C$3) -> -189638.4 | AI9: =AG9/(1+$C$5)^($C$3) -> -142228.8
B10: 63 | C10: =C2*D10 -> 2116.5 | D10: 0.75 | E10: =(C10-C9)/C9 -> 0.071428571 | G10: =G9*(1+$C$4) -> 2024.785 | K10: =K9+$K$9 -> 47409.6 | N10: =N9+(N9*$C$4) -> 24297.42 | O10: =O9+N10 -> 48002.22 | P10: 0 | Q10: 0 | R10: 0 | S10: 0 | T10: =N10+(1+$C$5)*T9 -> 48594.84 | U10: =Q10 -> 0 | V10: =S10 -> 0 | W10: =T10 -> 48594.84 | X10: 0
B11: 64 | C11: =C2*D11 -> 2257.6 | D11: 0.8 | E11: =(C11-C10)/C10 -> 0.066666667 | G11: =G10*(1+$C$4) -> 2075.4046 | K11: =K10+$K$9 -> 71114.4 | N11: =N10+(N10*$C$4) -> 24904.855 | O11: =O10+N11 -> 72907.076 | P11: 0 | Q11: 0 | R11: 0 | S11: 0 | T11: =N11+(1+$C$5)*T10 -> 74714.566 | U11: =Q11 -> 0 | V11: =S11 -> 0 | W11: =T11 -> 74714.566 | X11: 0
B12: 65 | C12: =C2*D12 -> 2446.674 | D12: 0.867 | E12: =(C12-C11)/C11 -> 0.08375 | G12: =G11*(1+$C$4) -> 2127.2897 | K12: =K11+$K$9 -> 94819.2 | N12: =N11+(N11*$C$4) -> 25527.477 | O12: =O11+N12 -> 98434.552 | P12: 0 | Q12: 0 | R12: 0 | S12: 0 | T12: =N12+(1+$C$5)*T11 -> 102109.91 | U12: =Q12 -> 0 | V12: =S12 -> 0 | W12: =T12 -> 102109.91 | X12: 0 | AH12: =FV(C5,C3,0,AH9) -> 326476.05 | AI12: =FV(C5,20,0,AI9) -> 233058.45
B13: 66 | C13: =C2*D13 -> 2632.926 | D13: 0.933 | E13: =(C13-C12)/C12 -> 0.076124567 | G13: =G12*(1+$C$4) -> 2180.472 | K13: =K12+$K$9 -> 118524 | N13: =N12+(N12*$C$4) -> 26165.664 | O13: =O12+N13 -> 124600.22 | P13: 0 | Q13: 0 | R13: 0 | S13: 0 | T13: =N13+(1+$C$5)*T12 -> 130828.32 | U13: =Q13 -> 0 | V13: =S13 -> 0 | W13: =T13 -> 130828.32 | X13: 0
B14: 67 | C14: =C2*D14 -> 2822 | D14: 1 | E14: =(C14-C13)/C13 -> 0.071811361 | G14: =G13*(1+$C$4) -> 2234.9838 | H14: =$C$14 -> 2822 | K14: =K13+$K$9 -> 142228.8 | L14: =C14*12 -> 33864 | N14: =N13+(N13*$C$4) -> 26819.805 | O14: =O13+N14 -> 151420.02 | P14: =L14 -> 33864 | Q14: =L14 -> 33864 | R14: 0 | S14: 0 | T14: =N14+(1+$C$5)*T13 -> 160918.83 | U14: =Q14 -> 33864 | V14: =S14 -> 0 | W14: =T14 -> 160918.83 | X14: 0
B15: 68 | C15: =C2*D15 -> 3047.76 | D15: 1.08 | E15: =(C15-C14)/C14 -> 0.08 | G15: =G14*(1+$C$4) -> 2290.8584 | H15: =H14*(1+$C$4) -> 2892.55 | K15: =K14+$K$9 -> 165933.6 | L15: =L14+$L$14 -> 67728 | N15: =N14+(N14*$C$4) -> 27490.301 | O15: =O14+N15 -> 178910.32 | P15: =P14+P14*$C$4 -> 34710.6 | Q15: =Q14+P15 -> 68574.6 | R15: 0 | S15: 0 | T15: =N15+(1+$C$5)*T14 -> 192432.1 | U15: =(U14*(1+$C$5))+P15 -> 69421.2 | V15: =S15 -> 0 | W15: =T15 -> 192432.1 | X15: 0
B16: 69 | C16: =C2*D16 -> 3273.52 | D16: 1.16 | E16: =(C16-C15)/C15 -> 0.074074074 | G16: =G15*(1+$C$4) -> 2348.1298 | H16: =H15*(1+$C$4) -> 2964.8637 | K16: =K15+$K$9 -> 189638.4 | L16: =L15+$L$14 -> 101592 | N16: =N15+(N15*$C$4) -> 28177.558 | O16: =O15+N16 -> 207087.88 | P16: =P15+P15*$C$4 -> 35578.365 | Q16: =Q15+P16 -> 104152.96 | R16: 0 | S16: 0 | T16: =N16+(1+$C$5)*T15 -> 225420.46 | U16: =(U15*(1+$C$5))+P16 -> 106735.1 | V16: =S16 -> 0 | W16: =T16 -> 225420.46 | X16: 0
B17: 70 | C17: =C2*D17 -> 3499.28 | D17: 1.24 | E17: =(C17-C16)/C16 -> 0.068965517 | G17: =G16*(1+$C$4) -> 2406.8331 | H17: =H16*(1+$C$4) -> 3038.9853 | I17: =C17 -> 3499.28 | K17: =K16+$K$9 -> 213343.2 | L17: =L16+$L$14 -> 135456 | M17: =C17*12 -> 41991.36 | N17: =N16+(N16*$C$4) -> 28881.997 | O17: =O16+N17 -> 235969.88 | P17: =P16+P16*$C$4 -> 36467.824 | Q17: =Q16+P17 -> 140620.79 | R17: =M17 -> 41991.36 | S17: =M17 -> 41991.36 | T17: =T16*(1+$C$5) -> 231055.98 | U17: =(U16*(1+$C$5)) -> 109403.47 | V17: 0 | W17: =P17+T17 -> 267523.8 | X17: =R17 -> 41991.36
B18: 71 | G18: =G17*(1+$C$4) -> 2467.0039 | H18: =H17*(1+$C$4) -> 3114.96 | I18: =I17*(1+$C$4) -> 3586.762 | K18: =K17+$K$9 -> 237048 | L18: =L17+$L$14 -> 169320 | M18: =M17+$M$17 -> 83982.72 | N18: =N17+(N17*$C$4) -> 29604.047 | O18: =O17+N18 -> 265573.92 | P18: =P17+P17*$C$4 -> 37379.52 | Q18: =Q17+P18 -> 178000.31 | R18: =R17 +R17*$C$4 -> 43041.144 | S18: =S17+$R$18 -> 85032.504 | T18: =T17*(1+$C$5) -> 236832.38 | U18: =(U17*(1+$C$5)) -> 112138.56 | V18: 0 | W18: =T18+K18-$K$16 -> 284241.98 | X18: =X17+R18 -> 85032.504
B19: 72 | G19: =G18*(1+$C$4) -> 2528.679 | H19: =H18*(1+$C$4) -> 3192.834 | I19: =I18*(1+$C$4) -> 3676.431 | K19: =K18+$K$9 -> 260752.8 | L19: =L18+$L$14 -> 203184 | M19: =M18+$M$17 -> 125974.08 | N19: =N18+(N18*$C$4) -> 30344.148 | O19: =O18+N19 -> 295918.07 | P19: =P18+P18*$C$4 -> 38314.008 | Q19: =Q18+P19 -> 216314.32 | R19: =R18 +R18*$C$4 -> 44117.173 | S19: =S18+R19 -> 129149.68 | T19: =T18*(1+$C$5) -> 242753.18 | U19: =(U18*(1+$C$5)) -> 114942.02 | V19: 0 | W19: =T19+K19-$K$16 -> 313867.58 | X19: =X18+R19 -> 129149.68 | AF19: Money stays invested in an account invested at rate of return
B20: 73 | G20: =G19*(1+$C$4) -> 2591.896 | H20: =H19*(1+$C$4) -> 3272.6548 | I20: =I19*(1+$C$4) -> 3768.3418 | K20: =K19+$K$9 -> 284457.6 | L20: =L19+$L$14 -> 237048 | M20: =M19+$M$17 -> 167965.44 | N20: =N19+(N19*$C$4) -> 31102.752 | O20: =O19+N20 -> 327020.82 | P20: =P19+P19*$C$4 -> 39271.858 | Q20: =Q19+P20 -> 255586.17 | R20: =R19 +R19*$C$4 -> 45220.102 | S20: =S19+R20 -> 174369.78 | T20: =T19*(1+$C$5) -> 248822.01 | U20: =(U19*(1+$C$5)) -> 117815.57 | V20: 0 | W20: =T20+K20-$K$16 -> 343641.21 | X20: =X19+R20 -> 174369.78 | AF20: How is this normalized to compare.
B21: 74 | G21: =G20*(1+$C$4) -> 2656.6934 | H21: =H20*(1+$C$4) -> 3354.4712 | I21: =I20*(1+$C$4) -> 3862.5504 | K21: =K20+$K$9 -> 308162.4 | L21: =L20+$L$14 -> 270912 | M21: =M20+$M$17 -> 209956.8 | N21: =N20+(N20*$C$4) -> 31880.321 | O21: =O20+N21 -> 358901.14 | P21: =P20+P20*$C$4 -> 40253.654 | Q21: =Q20+P21 -> 295839.83 | R21: =R20 +R20*$C$4 -> 46350.604 | S21: =S20+R21 -> 220720.38 | T21: =T20*(1+$C$5) -> 255042.56 | U21: =(U20*(1+$C$5)) -> 120760.96 | V21: 0 | W21: =T21+K21-$K$16 -> 373566.56 | X21: =X20+R21 -> 220720.38
B22: 75 | G22: =G21*(1+$C$4) -> 2723.1107 | H22: =H21*(1+$C$4) -> 3438.333 | I22: =I21*(1+$C$4) -> 3959.1141 | K22: =K21+$K$9 -> 331867.2 | L22: =L21+$L$14 -> 304776 | M22: =M21+$M$17 -> 251948.16 | N22: =N21+(N21*$C$4) -> 32677.329 | O22: =O21+N22 -> 391578.47 | P22: =P21+P21*$C$4 -> 41259.996 | Q22: =Q21+P22 -> 337099.82 | R22: =R21 +R21*$C$4 -> 47509.37 | S22: =S21+R22 -> 268229.75 | T22: =T21*(1+$C$5) -> 261418.63 | U22: =(U21*(1+$C$5)) -> 123779.99 | V22: 0 | W22: =T22+K22-$K$16 -> 403647.43 | X22: =X21+R22 -> 268229.75
B23: 76 | G23: =G22*(1+$C$4) -> 2791.1885 | H23: =H22*(1+$C$4) -> 3524.2913 | I23: =I22*(1+$C$4) -> 4058.092 | K23: =K22+$K$9 -> 355572 | L23: =L22+$L$14 -> 338640 | M23: =M22+$M$17 -> 293939.52 | N23: =N22+(N22*$C$4) -> 33494.262 | O23: =O22+N23 -> 425072.74 | P23: =P22+P22*$C$4 -> 42291.496 | Q23: =Q22+P23 -> 379391.32 | R23: =R22 +R22*$C$4 -> 48697.104 | S23: =S22+R23 -> 316926.86 | T23: =T22*(1+$C$5) -> 267954.09 | U23: =(U22*(1+$C$5)) -> 126874.49 | V23: 0 | W23: =T23+K23-$K$16 -> 433887.69 | X23: =X22+R23 -> 316926.86
B24: 77 | G24: =G23*(1+$C$4) -> 2860.9682 | H24: =H23*(1+$C$4) -> 3612.3986 | I24: =I23*(1+$C$4) -> 4159.5443 | K24: =K23+$K$9 -> 379276.8 | L24: =L23+$L$14 -> 372504 | M24: =M23+$M$17 -> 335930.88 | N24: =N23+(N23*$C$4) -> 34331.618 | O24: =O23+N24 -> 459404.35 | P24: =P23+P23*$C$4 -> 43348.783 | Q24: =Q23+P24 -> 422740.1 | R24: =R23 +R23*$C$4 -> 49914.531 | S24: =S23+R24 -> 366841.39 | T24: =T23*(1+$C$5) -> 274652.95 | U24: =(U23*(1+$C$5)) -> 130046.35 | V24: 0 | W24: =T24+K24-$K$16 -> 464291.35 | X24: =X23+R24 -> 366841.39
B25: 78 | G25: =G24*(1+$C$4) -> 2932.4924 | H25: =H24*(1+$C$4) -> 3702.7085 | I25: =I24*(1+$C$4) -> 4263.5329 | K25: =K24+$K$9 -> 402981.6 | L25: =L24+$L$14 -> 406368 | M25: =M24+$M$17 -> 377922.24 | N25: =N24+(N24*$C$4) -> 35189.909 | O25: =O24+N25 -> 494594.26 | P25: =P24+P24*$C$4 -> 44432.503 | Q25: =Q24+P25 -> 467172.61 | R25: =R24 +R24*$C$4 -> 51162.395 | S25: =S24+R25 -> 418003.78 | T25: =T24*(1+$C$5) -> 281519.27 | U25: =(U24*(1+$C$5)) -> 133297.51 | V25: 0 | W25: =T25+K25-$K$16 -> 494862.47 | X25: =X24+R25 -> 418003.78
B26: 79 | G26: =G25*(1+$C$4) -> 3005.8047 | H26: =H25*(1+$C$4) -> 3795.2763 | I26: =I25*(1+$C$4) -> 4370.1212 | K26: =K25+$K$9 -> 426686.4 | L26: =L25+$L$14 -> 440232 | M26: =M25+$M$17 -> 419913.6 | N26: =N25+(N25*$C$4) -> 36069.657 | O26: =O25+N26 -> 530663.92 | P26: =P25+P25*$C$4 -> 45543.315 | Q26: =Q25+P26 -> 512715.92 | R26: =R25 +R25*$C$4 -> 52441.455 | S26: =S25+R26 -> 470445.24 | T26: =T25*(1+$C$5) -> 288557.25 | U26: =(U25*(1+$C$5)) -> 136629.95 | V26: 0 | W26: =T26+K26-$K$16 -> 525605.25 | X26: =X25+R26 -> 470445.24
B27: 80 | G27: =G26*(1+$C$4) -> 3080.9498 | H27: =H26*(1+$C$4) -> 3890.1582 | I27: =I26*(1+$C$4) -> 4479.3742 | K27: =K26+$K$9 -> 450391.2 | L27: =L26+$L$14 -> 474096 | M27: =M26+$M$17 -> 461904.96 | N27: =N26+(N26*$C$4) -> 36971.398 | O27: =O26+N27 -> 567635.32 | P27: =P26+P26*$C$4 -> 46681.898 | Q27: =Q26+P27 -> 559397.82 | R27: =R26 +R26*$C$4 -> 53752.491 | S27: =S26+R27 -> 524197.73 | T27: =T26*(1+$C$5) -> 295771.18 | U27: =(U26*(1+$C$5)) -> 140045.69 | V27: 0 | W27: =T27+K27-$K$16 -> 556523.98 | X27: =X26+R27 -> 524197.73
B28: 81 | G28: =G27*(1+$C$4) -> 3157.9736 | H28: =H27*(1+$C$4) -> 3987.4121 | I28: =I27*(1+$C$4) -> 4591.3586 | K28: =K27+$K$9 -> 474096 | L28: =L27+$L$14 -> 507960 | M28: =M27+$M$17 -> 503896.32 | N28: =N27+(N27*$C$4) -> 37895.683 | O28: =O27+N28 -> 605531 | P28: =P27+P27*$C$4 -> 47848.945 | Q28: =Q27+P28 -> 607246.76 | R28: =R27 +R27*$C$4 -> 55096.303 | S28: =S27+R28 -> 579294.03 | T28: =T27*(1+$C$5) -> 303165.46 | U28: =(U27*(1+$C$5)) -> 143546.84 | V28: 0 | W28: =T28+K28-$K$16 -> 587623.06 | X28: =X27+R28 -> 579294.03
B29: 82 | G29: =G28*(1+$C$4) -> 3236.9229 | H29: =H28*(1+$C$4) -> 4087.0974 | I29: =I28*(1+$C$4) -> 4706.1426 | K29: =K28+$K$9 -> 497800.8 | L29: =L28+$L$14 -> 541824 | M29: =M28+$M$17 -> 545887.68 | N29: =N28+(N28*$C$4) -> 38843.075 | O29: =O28+N29 -> 644374.07 | P29: =P28+P28*$C$4 -> 49045.169 | Q29: =Q28+P29 -> 656291.93 | R29: =R28 +R28*$C$4 -> 56473.711 | S29: =S28+R29 -> 635767.74 | T29: =T28*(1+$C$5) -> 310744.6 | U29: =(U28*(1+$C$5)) -> 147135.51 | V29: 0 | W29: =T29+K29-$K$16 -> 618907 | X29: =X28+R29 -> 635767.74
B30: 83 | G30: =G29*(1+$C$4) -> 3317.846 | H30: =H29*(1+$C$4) -> 4189.2749 | I30: =I29*(1+$C$4) -> 4823.7961 | K30: =K29+$K$9 -> 521505.6 | L30: =L29+$L$14 -> 575688 | M30: =M29+$M$17 -> 587879.04 | N30: =N29+(N29*$C$4) -> 39814.152 | O30: =O29+N30 -> 684188.23 | P30: =P29+P29*$C$4 -> 50271.298 | Q30: =Q29+P30 -> 706563.23 | R30: =R29 +R29*$C$4 -> 57885.554 | S30: =S29+R30 -> 693653.3 | T30: =T29*(1+$C$5) -> 318513.21 | U30: =(U29*(1+$C$5)) -> 150813.9 | V30: 0 | W30: =T30+K30-$K$16 -> 650380.41 | X30: =X29+R30 -> 693653.3
B31: 84 | G31: =G30*(1+$C$4) -> 3400.7921 | H31: =H30*(1+$C$4) -> 4294.0067 | I31: =I30*(1+$C$4) -> 4944.391 | K31: =K30+$K$9 -> 545210.4 | L31: =L30+$L$14 -> 609552 | M31: =M30+$M$17 -> 629870.4 | N31: =N30+(N30*$C$4) -> 40809.506 | O31: =O30+N31 -> 724997.73 | P31: =P30+P30*$C$4 -> 51528.081 | Q31: =Q30+P31 -> 758091.31 | R31: =R30 +R30*$C$4 -> 59332.692 | S31: =S30+R31 -> 752985.99 | T31: =T30*(1+$C$5) -> 326476.05 | U31: =(U30*(1+$C$5)) -> 154584.24 | V31: 0 | W31: =T31+K31-$K$16 -> 682048.05 | X31: =X30+R31 -> 752985.99
B32: 85 | G32: =G31*(1+$C$4) -> 3485.8119 | H32: =H31*(1+$C$4) -> 4401.3569 | I32: =I31*(1+$C$4) -> 5068.0008 | K32: =K31+$K$9 -> 568915.2 | L32: =L31+$L$14 -> 643416 | M32: =M31+$M$17 -> 671861.76 | N32: =N31+(N31*$C$4) -> 41829.743 | O32: =O31+N32 -> 766827.48 | P32: =P31+P31*$C$4 -> 52816.283 | Q32: =Q31+P32 -> 810907.6 | R32: =R31 +R31*$C$4 -> 60816.01 | S32: =S31+R32 -> 813802 | T32: =T31*(1+$C$5) -> 334637.95 | U32: =(U31*(1+$C$5)) -> 158448.85 | V32: 0 | W32: =T32+K32-$K$16 -> 713914.75 | X32: =X31+R32 -> 813802
... B47: 100 | G47: =G46*(1+$C$4) -> 5048.495 | H47: =H46*(1+$C$4) -> 6374.4771 | I47: =I46*(1+$C$4) -> 7339.9763 | K47: =K46+$K$9 -> 924487.2 | L47: =L46+$L$14 -> 1151376 | M47: =M46+$M$17 -> 1301732.2 | N47: =N46+(N46*$C$4) -> 60581.941 | O47: =O46+N47 -> 1535667.6 | P47: =P46+P46*$C$4 -> 76493.726 | Q47: =Q46+P47 -> 1781682.7 | R47: =R46 +R46*$C$4 -> 88079.715 | S47: =S46+R47 -> 1931613.9 | T47: =T46*(1+$C$5) -> 484655.52 | U47: =(U46*(1+$C$5)) -> 229481.18 | V47: 0 | W47: =T47+K47-$K$16 -> 1219504.3 | X47: =X46+R47 -> 1931613.9

Sheet Frank and Bill
A2: Full Retirment Age Benefit | B2: =Main!B3 -> 2822
A3: Life Expectancy | B3: =Main!B4 -> 22
A4: Cola | B4: =Main!B5 -> 0.025 | D4: Average since 1975 = | E4: ='SS Benefit Cal'!F3 -> 3.7294118 | G4: Starting retirement funds to draw from = | H4: 250000
A5: Rate of Return | B5: 0.0326 | D5: AverageCPI since 1914 | E5: =Main!E6 -> 0.03263964 | G5: Frank and Bill age of death | H5: 80
A6: Discount Rate | B6: =Main!B7 -> 0.025
A7: Spouse Full retirement Benefit | B7: 2500
A9: Yearly expense | B9: 23704
G10: Spouse
A11: AGE | B11: Monthy benefit | C11: % change | D11: year2year change | F11: AGE | G11: Monthy benefit | H11: % change | I11: year2year change
A12: 62 | B12: =$B$2*C12 -> 1975.4 | C12: 0.7 | F12: 62 | G12: =$B$7*H12 -> 1750 | H12: 0.7
A13: 63 | B13: =$B$2*C13 -> 2116.5 | C13: 0.75 | D13: =(B13-B12)/B12 -> 0.071428571 | F13: 63 | G13: =$B$7*H13 -> 1875 | H13: 0.75 | I13: =(G13-G12)/G12 -> 0.071428571
A14: 64 | B14: =$B$2*C14 -> 2257.6 | C14: 0.8 | D14: =(B14-B13)/B13 -> 0.066666667 | F14: 64 | G14: =$B$7*H14 -> 2000 | H14: 0.8 | I14: =(G14-G13)/G13 -> 0.066666667
A15: 65 | B15: =$B$2*C15 -> 2446.674 | C15: 0.867 | D15: =(B15-B14)/B14 -> 0.08375 | F15: 65 | G15: =$B$7*H15 -> 2167.5 | H15: 0.867 | I15: =(G15-G14)/G14 -> 0.08375
A16: 66 | B16: =$B$2*C16 -> 2632.926 | C16: 0.933 | D16: =(B16-B15)/B15 -> 0.076124567 | F16: 66 | G16: =$B$7*H16 -> 2332.5 | H16: 0.933 | I16: =(G16-G15)/G15 -> 0.076124567
A17: 67 | B17: =$B$2*C17 -> 2822 | C17: 1 | D17: =(B17-B16)/B16 -> 0.071811361 | F17: 67 | G17: =B7 -> 2500 | H17: 1 | I17: =(G17-G16)/G16 -> 0.071811361
A18: 68 | B18: =$B$2*C18 -> 3047.76 | C18: 1.08 | D18: =(B18-B17)/B17 -> 0.08 | F18: 68 | G18: =$B$7*H18 -> 2700 | H18: 1.08 | I18: =(G18-G17)/G17 -> 0.08
A19: 69 | B19: =$B$2*C19 -> 3273.52 | C19: 1.16 | D19: =(B19-B18)/B18 -> 0.074074074 | F19: 69 | G19: =$B$7*H19 -> 2900 | H19: 1.16 | I19: =(G19-G18)/G18 -> 0.074074074
A20: 70 | B20: =$B$2*C20 -> 3499.28 | C20: 1.24 | D20: =(B20-B19)/B19 -> 0.068965517 | F20: 70 | G20: =$B$7*H20 -> 3100 | H20: 1.24 | I20: =(G20-G19)/G19 -> 0.068965517
A23: Frank | G23: Bill | N23: Frank | O23: Bill
A24: Age | B24: Monthly benefit | C24: Yearly Benefit | D24: Yearly Expenses | E24: expense vs income | F24: Savings | G24: Age | H24: Monthly benefit | I24: Yearly Benefit | J24: Yearly Expenses | K24: Change to savings | L24: Saving | M24: Age | N24: Savings | O24: Savings
A25: 62 | B25: =B12 -> 1975.4 | C25: =B25*12 -> 23704.8 | D25: =B9 -> 23704 | E25: =C25-D25 -> 0.8 | F25: =$H$4*(1+$B$5) -> 258150 | G25: 62 | H25: 0 | I25: =H25*12 -> 0 | J25: =B9 -> 23704 | K25: =I25-J25 -> -23704 | L25: =($H$4)*(1+$B$5)+K25 -> 234446 | M25: 62 | N25: =F25 -> 258150 | O25: =L25 -> 234446
A26: 63 | B26: =B25*(1+$B$4) -> 2024.785 | C26: =B26*12 -> 24297.42 | D26: =D25*(1+$B$4) -> 24296.6 | E26: =C26-D26 -> 0.82 | F26: =F25*(1+$B$5)+E26 -> 266566.51 | G26: 63 | H26: 0 | I26: =H26*12 -> 0 | J26: =J25*(1+$B$4) -> 24296.6 | K26: =I26-J26 -> -24296.6 | L26: =(L25)*(1+$B$5)+K26 -> 217792.34 | M26: 63 | N26: =F26 -> 266566.51 | O26: =L26 -> 217792.34
A27: 64 | B27: =B26*(1+$B$4) -> 2075.4046 | C27: =B27*12 -> 24904.855 | D27: =D26*(1+$B$4) -> 24904.015 | E27: =C27-D27 -> 0.8405 | F27: =F26*(1+$B$5)+E27 -> 275257.42 | G27: 64 | H27: 0 | I27: =H27*12 -> 0 | J27: =J26*(1+$B$4) -> 24904.015 | K27: =I27-J27 -> -24904.015 | L27: =(L26)*(1+$B$5)+K27 -> 199988.35 | M27: 64 | N27: =F27 -> 275257.42 | O27: =L27 -> 199988.35
A28: 65 | B28: =B27*(1+$B$4) -> 2127.2897 | C28: =B28*12 -> 25527.477 | D28: =D27*(1+$B$4) -> 25526.615 | E28: =C28-D28 -> 0.8615125 | F28: =F27*(1+$B$5)+E28 -> 284231.67 | G28: 65 | H28: 0 | I28: =H28*12 -> 0 | J28: =J27*(1+$B$4) -> 25526.615 | K28: =I28-J28 -> -25526.615 | L28: =(L27)*(1+$B$5)+K28 -> 180981.36 | M28: 65 | N28: =F28 -> 284231.67 | O28: =L28 -> 180981.36
A29: 66 | B29: =B28*(1+$B$4) -> 2180.472 | C29: =B29*12 -> 26165.664 | D29: =D28*(1+$B$4) -> 26164.781 | E29: =C29-D29 -> 0.88305031 | F29: =F28*(1+$B$5)+E29 -> 293498.51 | G29: 66 | H29: 0 | I29: =H29*12 -> 0 | J29: =J28*(1+$B$4) -> 26164.781 | K29: =I29-J29 -> -26164.781 | L29: =(L28)*(1+$B$5)+K29 -> 160716.57 | M29: 66 | N29: =F29 -> 293498.51 | O29: =L29 -> 160716.57
A30: 67 | B30: =B29*(1+$B$4) -> 2234.9838 | C30: =B30*12 -> 26819.805 | D30: =D29*(1+$B$4) -> 26818.9 | E30: =C30-D30 -> 0.90512657 | F30: =F29*(1+$B$5)+E30 -> 303067.46 | G30: 67 | H30: 0 | I30: =H30*12 -> 0 | J30: =J29*(1+$B$4) -> 26818.9 | K30: =I30-J30 -> -26818.9 | L30: =(L29)*(1+$B$5)+K30 -> 139137.03 | M30: 67 | N30: =F30 -> 303067.46 | O30: =L30 -> 139137.03
A31: 68 | B31: =B30*(1+$B$4) -> 2290.8584 | C31: =B31*12 -> 27490.301 | D31: =D30*(1+$B$4) -> 27489.373 | E31: =C31-D31 -> 0.92775473 | F31: =F30*(1+$B$5)+E31 -> 312948.39 | G31: 68 | H31: 0 | I31: =H31*12 -> 0 | J31: =J30*(1+$B$4) -> 27489.373 | K31: =I31-J31 -> -27489.373 | L31: =(L30)*(1+$B$5)+K31 -> 116183.53 | M31: 68 | N31: =F31 -> 312948.39 | O31: =L31 -> 116183.53
A32: 69 | B32: =B31*(1+$B$4) -> 2348.1298 | C32: =B32*12 -> 28177.558 | D32: =D31*(1+$B$4) -> 28176.607 | E32: =C32-D32 -> 0.9509486 | F32: =F31*(1+$B$5)+E32 -> 323151.46 | G32: 69 | H32: 0 | I32: =H32*12 -> 0 | J32: =J31*(1+$B$4) -> 28176.607 | K32: =I32-J32 -> -28176.607 | L32: =(L31)*(1+$B$5)+K32 -> 91794.502 | M32: 69 | N32: =F32 -> 323151.46 | O32: =L32 -> 91794.502
A33: 70 | B33: =B32*(1+$B$4) -> 2406.8331 | C33: =B33*12 -> 28881.997 | D33: =D32*(1+$B$4) -> 28881.022 | E33: =C33-D33 -> 0.97472232 | F33: =F32*(1+$B$5)+E33 -> 333687.17 | G33: 70 | H33: =B20 -> 3499.28 | I33: =H33*12 -> 41991.36 | J33: =J32*(1+$B$4) -> 28881.022 | K33: =I33-J33 -> 13110.338 | L33: =(L32)*(1+$B$5)+K33 -> 107897.34 | M33: 70 | N33: =F33 -> 333687.17 | O33: =L33 -> 107897.34
A34: 71 | B34: =B33*(1+$B$4) -> 2467.0039 | C34: =B34*12 -> 29604.047 | D34: =D33*(1+$B$4) -> 29603.048 | E34: =C34-D34 -> 0.99909038 | F34: =F33*(1+$B$5)+E34 -> 344566.37 | G34: 71 | H34: =H33*(1+$B$4) -> 3586.762 | I34: =H34*12 -> 43041.144 | J34: =J33*(1+$B$4) -> 29603.048 | K34: =I34-J34 -> 13438.096 | L34: =(L33)*(1+$B$5)+K34 -> 124852.89 | M34: 71 | N34: =F34 -> 344566.37 | O34: =L34 -> 124852.89
A35: 72 | B35: =B34*(1+$B$4) -> 2528.679 | C35: =B35*12 -> 30344.148 | D35: =D34*(1+$B$4) -> 30343.124 | E35: =C35-D35 -> 1.0240676 | F35: =F34*(1+$B$5)+E35 -> 355800.26 | G35: 72 | H35: =H34*(1+$B$4) -> 3676.431 | I35: =H35*12 -> 44117.173 | J35: =J34*(1+$B$4) -> 30343.124 | K35: =I35-J35 -> 13774.049 | L35: =(L34)*(1+$B$5)+K35 -> 142697.14 | M35: 72 | N35: =F35 -> 355800.26 | O35: =L35 -> 142697.14
A36: 73 | B36: =B35*(1+$B$4) -> 2591.896 | C36: =B36*12 -> 31102.752 | D36: =D35*(1+$B$4) -> 31101.702 | E36: =C36-D36 -> 1.0496693 | F36: =F35*(1+$B$5)+E36 -> 367400.4 | G36: 73 | H36: =H35*(1+$B$4) -> 3768.3418 | I36: =H36*12 -> 45220.102 | J36: =J35*(1+$B$4) -> 31101.702 | K36: =I36-J36 -> 14118.4 | L36: =(L35)*(1+$B$5)+K36 -> 161467.47 | M36: 73 | N36: =F36 -> 367400.4 | O36: =L36 -> 161467.47
A37: 74 | B37: =B36*(1+$B$4) -> 2656.6934 | C37: =B37*12 -> 31880.321 | D37: =D36*(1+$B$4) -> 31879.245 | E37: =C37-D37 -> 1.0759111 | F37: =F36*(1+$B$5)+E37 -> 379378.73 | G37: 74 | H37: =H36*(1+$B$4) -> 3862.5504 | I37: =H37*12 -> 46350.604 | J37: =J36*(1+$B$4) -> 31879.245 | K37: =I37-J37 -> 14471.36 | L37: =(L36)*(1+$B$5)+K37 -> 181202.67 | M37: 74 | N37: =F37 -> 379378.73 | O37: =L37 -> 181202.67
A38: 75 | B38: =B37*(1+$B$4) -> 2723.1107 | C38: =B38*12 -> 32677.329 | D38: =D37*(1+$B$4) -> 32676.226 | E38: =C38-D38 -> 1.1028088 | F38: =F37*(1+$B$5)+E38 -> 391747.58 | G38: 75 | H38: =H37*(1+$B$4) -> 3959.1141 | I38: =H38*12 -> 47509.37 | J38: =J37*(1+$B$4) -> 32676.226 | K38: =I38-J38 -> 14833.144 | L38: =(L37)*(1+$B$5)+K38 -> 201943.02 | M38: 75 | N38: =F38 -> 391747.58 | O38: =L38 -> 201943.02
A39: 76 | B39: =B38*(1+$B$4) -> 2791.1885 | C39: =B39*12 -> 33494.262 | D39: =D38*(1+$B$4) -> 33493.131 | E39: =C39-D39 -> 1.1303791 | F39: =F38*(1+$B$5)+E39 -> 404519.68 | G39: 76 | H39: =H38*(1+$B$4) -> 4058.092 | I39: =H39*12 -> 48697.104 | J39: =J38*(1+$B$4) -> 33493.131 | K39: =I39-J39 -> 15203.972 | L39: =(L38)*(1+$B$5)+K39 -> 223730.33 | M39: 76 | N39: =F39 -> 404519.68 | O39: =L39 -> 223730.33
A40: 77 | B40: =B39*(1+$B$4) -> 2860.9682 | C40: =B40*12 -> 34331.618 | D40: =D39*(1+$B$4) -> 34330.46 | E40: =C40-D40 -> 1.1586385 | F40: =F39*(1+$B$5)+E40 -> 417708.18 | G40: 77 | H40: =H39*(1+$B$4) -> 4159.5443 | I40: =H40*12 -> 49914.531 | J40: =J39*(1+$B$4) -> 34330.46 | K40: =I40-J40 -> 15584.072 | L40: =(L39)*(1+$B$5)+K40 -> 246608.01 | M40: 77 | N40: =F40 -> 417708.18 | O40: =L40 -> 246608.01
A41: 78 | B41: =B40*(1+$B$4) -> 2932.4924 | C41: =B41*12 -> 35189.909 | D41: =D40*(1+$B$4) -> 35188.721 | E41: =C41-D41 -> 1.1876045 | F41: =F40*(1+$B$5)+E41 -> 431326.65 | G41: 78 | H41: =H40*(1+$B$4) -> 4263.5329 | I41: =H41*12 -> 51162.395 | J41: =J40*(1+$B$4) -> 35188.721 | K41: =I41-J41 -> 15973.673 | L41: =(L40)*(1+$B$5)+K41 -> 270621.11 | M41: 78 | N41: =F41 -> 431326.65 | O41: =L41 -> 270621.11
A42: 79 | B42: =B41*(1+$B$4) -> 3005.8047 | C42: =B42*12 -> 36069.657 | D42: =D41*(1+$B$4) -> 36068.439 | E42: =C42-D42 -> 1.2172946 | F42: =F41*(1+$B$5)+E42 -> 445389.12 | G42: 79 | H42: =H41*(1+$B$4) -> 4370.1212 | I42: =H42*12 -> 52441.455 | J42: =J41*(1+$B$4) -> 36068.439 | K42: =I42-J42 -> 16373.015 | L42: =(L41)*(1+$B$5)+K42 -> 295816.37 | M42: 79 | N42: =F42 -> 445389.12 | O42: =L42 -> 295816.37
A43: 80 | B43: =B42*(1+$B$4) -> 3080.9498 | C43: =B43*12 -> 36971.398 | D43: =D42*(1+$B$4) -> 36970.15 | E43: =C43-D43 -> 1.247727 | F43: =F42*(1+$B$5)+E43 -> 459910.05 | G43: 80 | H43: =H42*(1+$B$4) -> 4479.3742 | I43: =H43*12 -> 53752.491 | J43: =J42*(1+$B$4) -> 36970.15 | K43: =I43-J43 -> 16782.341 | L43: =(L42)*(1+$B$5)+K43 -> 322242.33 | M43: 80 | N43: =F43 -> 459910.05 | O43: =L43 -> 322242.33
A44: 81 | B44: =B43*(1+$B$4) -> 3157.9736 | C44: =B44*12 -> 37895.683 | D44: =D43*(1+$B$4) -> 37894.404 | E44: =C44-D44 -> 1.2789201 | F44: =F43*(1+$B$5)+E44 -> 474904.4 | G44: 81 | H44: =H43*(1+$B$4) -> 4591.3586 | I44: =H44*12 -> 55096.303 | J44: =J43*(1+$B$4) -> 37894.404 | K44: =I44-J44 -> 17201.899 | L44: =(L43)*(1+$B$5)+K44 -> 349949.33 | M44: 81 | N44: =F44 -> 474904.4 | O44: =L44 -> 349949.33
A45: 82 | B45: =B44*(1+$B$4) -> 3236.9229 | C45: =B45*12 -> 38843.075 | D45: =D44*(1+$B$4) -> 38841.764 | E45: =C45-D45 -> 1.3108932 | F45: =F44*(1+$B$5)+E45 -> 490387.59 | G45: 82 | H45: =H44*(1+$B$4) -> 4706.1426 | I45: =H45*12 -> 56473.711 | J45: =J44*(1+$B$4) -> 38841.764 | K45: =I45-J45 -> 17631.947 | L45: =(L44)*(1+$B$5)+K45 -> 378989.62 | M45: 82 | N45: =F45 -> 490387.59 | O45: =L45 -> 378989.62
... A63: 100 | B63: =B62*(1+$B$4) -> 5048.495 | C63: =B63*12 -> 60581.941 | D63: =D62*(1+$B$4) -> 60579.896 | E63: =C63-D63 -> 2.0445459 | F63: =F62*(1+$B$5)+E63 -> 873649.32 | G63: 100 | H63: =H62*(1+$B$4) -> 7339.9763 | I63: =H63*12 -> 88079.715 | J63: =J62*(1+$B$4) -> 60579.896 | K63: =I63-J63 -> 27499.819 | L63: =(L62)*(1+$B$5)+K63 -> 1202620.4 | M63: 100 | N63: =F63 -> 873649.32 | O63: =L63 -> 1202620.4
A74: Frank | J74: Bill
A75: Age | B75: Montly benefit | C75: Yearly Benefit | D75: Spouse Montly benefit | E75: Spouse Yearly Benefit | F75: Yearly Expenses | G75: expenses vs invome | H75: Saving | J75: Age | K75: Montly benefit | L75: Yearly Benefit | M75: Spouse Monthly Benefit | N75: Spouse Yearly Benefit | O75: Yearly Expenses | P75: Expenses vs Income | Q75: Saving
A76: 62 | B76: =B12 -> 1975.4 | C76: =B25*12 -> 23704.8 | D76: =$G$15 -> 2167.5 | E76: =D76*12 -> 26010 | F76: =$B$9 -> 23704 | G76: =(E76+C76)-F76 -> 26010.8 | H76: =$H$4*(1+$B$5)+G76 -> 284160.8 | J76: 62 | K76: 0 | L76: =K76*12 -> 0 | M76: =D76 -> 2167.5 | N76: =M76*12 -> 26010 | O76: =B9 -> 23704 | P76: =(L76+N76)-O76 -> 2306 | Q76: =($H$4)*(1+$B$5)+N76+P76-C76 -> 262761.2 | X76: ="Compare Saving of Married Frank and Bill at rate of return of " & B5*100 & "% and Cola of " & B4*100 & "% " & "Yearly Expenses = $" & B9 -> Compare Saving of Married Frank and Bill at rate of return of 3.26% and Cola of 2.5% Yearly Expenses = $23704
A77: 63 | B77: =B76*(1+$B$4) -> 2024.785 | C77: =B26*12 -> 24297.42 | D77: =D76*(1+$B$4) -> 2221.6875 | E77: =D77*12 -> 26660.25 | F77: =F76*(1+$B$4) -> 24296.6 | G77: =(E77+C77)-F77 -> 26661.07 | H77: =H76*(1+$B$5)+G77 -> 320085.51 | J77: 63 | K77: 0 | L77: =K77*12 -> 0 | M77: =M76*(1+$B$4) -> 2221.6875 | N77: =M77*12 -> 26660.25 | O77: =O76*(1+$B$4) -> 24296.6 | P77: =(L77+N77)-O77 -> 2363.65 | Q77: =Q76*(1+$B$5)+P77 -> 273690.87
A78: 64 | B78: =B77*(1+$B$4) -> 2075.4046 | C78: =B27*12 -> 24904.855 | D78: =D77*(1+$B$4) -> 2277.2297 | E78: =D78*12 -> 27326.756 | F78: =F77*(1+$B$4) -> 24904.015 | G78: =(E78+C78)-F78 -> 27327.597 | H78: =H77*(1+$B$5)+G78 -> 357847.9 | J78: 64 | K78: 0 | L78: =K78*12 -> 0 | M78: =M77*(1+$B$4) -> 2277.2297 | N78: =M78*12 -> 27326.756 | O78: =O77*(1+$B$4) -> 24904.015 | P78: =(L78+N78)-O78 -> 2422.7413 | Q78: =Q77*(1+$B$5)+P78 -> 285035.93
A79: 65 | B79: =B78*(1+$B$4) -> 2127.2897 | C79: =B28*12 -> 25527.477 | D79: =D78*(1+$B$4) -> 2334.1604 | E79: =D79*12 -> 28009.925 | F79: =F78*(1+$B$4) -> 25526.615 | G79: =(E79+C79)-F79 -> 28010.787 | H79: =H78*(1+$B$5)+G79 -> 397524.52 | J79: 65 | K79: 0 | L79: =K79*12 -> 0 | M79: =M78*(1+$B$4) -> 2334.1604 | N79: =M79*12 -> 28009.925 | O79: =O78*(1+$B$4) -> 25526.615 | P79: =(L79+N79)-O79 -> 2483.3098 | Q79: =Q78*(1+$B$5)+P79 -> 296811.41
A80: 66 | B80: =B79*(1+$B$4) -> 2180.472 | C80: =B29*12 -> 26165.664 | D80: =D79*(1+$B$4) -> 2392.5144 | E80: =D80*12 -> 28710.173 | F80: =F79*(1+$B$4) -> 26164.781 | G80: =(E80+C80)-F80 -> 28711.056 | H80: =H79*(1+$B$5)+G80 -> 439194.88 | J80: 66 | K80: 0 | L80: =K80*12 -> 0 | M80: =M79*(1+$B$4) -> 2392.5144 | N80: =M80*12 -> 28710.173 | O80: =O79*(1+$B$4) -> 26164.781 | P80: =(L80+N80)-O80 -> 2545.3925 | Q80: =Q79*(1+$B$5)+P80 -> 309032.85
A81: 67 | B81: =B80*(1+$B$4) -> 2234.9838 | C81: =B30*12 -> 26819.805 | D81: =D80*(1+$B$4) -> 2452.3273 | E81: =D81*12 -> 29427.928 | F81: =F80*(1+$B$4) -> 26818.9 | G81: =(E81+C81)-F81 -> 29428.833 | H81: =H80*(1+$B$5)+G81 -> 482941.47 | J81: 67 | K81: 0 | L81: =K81*12 -> 0 | M81: =M80*(1+$B$4) -> 2452.3273 | N81: =M81*12 -> 29427.928 | O81: =O80*(1+$B$4) -> 26818.9 | P81: =(L81+N81)-O81 -> 2609.0273 | Q81: =Q80*(1+$B$5)+P81 -> 321716.35
A82: 68 | B82: =B81*(1+$B$4) -> 2290.8584 | C82: =B31*12 -> 27490.301 | D82: =D81*(1+$B$4) -> 2513.6355 | E82: =D82*12 -> 30163.626 | F82: =F81*(1+$B$4) -> 27489.373 | G82: =(E82+C82)-F82 -> 30164.554 | H82: =H81*(1+$B$5)+G82 -> 528849.91 | J82: 68 | K82: 0 | L82: =K82*12 -> 0 | M82: =M81*(1+$B$4) -> 2513.6355 | N82: =M82*12 -> 30163.626 | O82: =O81*(1+$B$4) -> 27489.373 | P82: =(L82+N82)-O82 -> 2674.253 | Q82: =Q81*(1+$B$5)+P82 -> 334878.56
A83: 69 | B83: =B82*(1+$B$4) -> 2348.1298 | C83: =B32*12 -> 28177.558 | D83: =D82*(1+$B$4) -> 2576.4764 | E83: =D83*12 -> 30917.716 | F83: =F82*(1+$B$4) -> 28176.607 | G83: =(E83+C83)-F83 -> 30918.667 | H83: =H82*(1+$B$5)+G83 -> 577009.09 | J83: 69 | K83: 0 | L83: =K83*12 -> 0 | M83: =M82*(1+$B$4) -> 2576.4764 | N83: =M83*12 -> 30917.716 | O83: =O82*(1+$B$4) -> 28176.607 | P83: =(L83+N83)-O83 -> 2741.1093 | Q83: =Q82*(1+$B$5)+P83 -> 348536.71
A84: 70 | B84: =B83*(1+$B$4) -> 2406.8331 | C84: =B33*12 -> 28881.997 | D84: =D83*(1+$B$4) -> 2640.8883 | E84: =D84*12 -> 31690.659 | F84: =F83*(1+$B$4) -> 28881.022 | G84: =(E84+C84)-F84 -> 31691.634 | H84: =H83*(1+$B$5)+G84 -> 627511.22 | J84: 70 | K84: =B20 -> 3499.28 | L84: =K84*12 -> 41991.36 | M84: =M83*(1+$B$4) -> 2640.8883 | N84: =M84*12 -> 31690.659 | O84: =O83*(1+$B$4) -> 28881.022 | P84: =(L84+N84)-O84 -> 44800.997 | Q84: =Q83*(1+$B$5)+P84 -> 404700
A85: 71 | B85: =B84*(1+$B$4) -> 2467.0039 | C85: =B34*12 -> 29604.047 | D85: =D84*(1+$B$4) -> 2706.9105 | E85: =D85*12 -> 32482.926 | F85: =F84*(1+$B$4) -> 29603.048 | G85: =(E85+C85)-F85 -> 32483.925 | H85: =H84*(1+$B$5)+G85 -> 680452.01 | J85: 71 | K85: =K84*(1+$B$4) -> 3586.762 | L85: =K85*12 -> 43041.144 | M85: =M84*(1+$B$4) -> 2706.9105 | N85: =M85*12 -> 32482.926 | O85: =O84*(1+$B$4) -> 29603.048 | P85: =(L85+N85)-O85 -> 45921.022 | Q85: =Q84*(1+$B$5)+P85 -> 463814.24
A86: 72 | B86: =B85*(1+$B$4) -> 2528.679 | C86: =B35*12 -> 30344.148 | D86: =D85*(1+$B$4) -> 2774.5832 | E86: =D86*12 -> 33294.999 | F86: =F85*(1+$B$4) -> 30343.124 | G86: =(E86+C86)-F86 -> 33296.023 | H86: =H85*(1+$B$5)+G86 -> 735930.77 | J86: 72 | K86: =K85*(1+$B$4) -> 3676.431 | L86: =K86*12 -> 44117.173 | M86: =M85*(1+$B$4) -> 2774.5832 | N86: =M86*12 -> 33294.999 | O86: =O85*(1+$B$4) -> 30343.124 | P86: =(L86+N86)-O86 -> 47069.048 | Q86: =Q85*(1+$B$5)+P86 -> 526003.64
A87: 73 | B87: =B86*(1+$B$4) -> 2591.896 | C87: =B36*12 -> 31102.752 | D87: =D86*(1+$B$4) -> 2843.9478 | E87: =D87*12 -> 34127.374 | F87: =F86*(1+$B$4) -> 31101.702 | G87: =(E87+C87)-F87 -> 34128.424 | H87: =H86*(1+$B$5)+G87 -> 794050.53 | J87: 73 | K87: =K86*(1+$B$4) -> 3768.3418 | L87: =K87*12 -> 45220.102 | M87: =M86*(1+$B$4) -> 2843.9478 | N87: =M87*12 -> 34127.374 | O87: =O86*(1+$B$4) -> 31101.702 | P87: =(L87+N87)-O87 -> 48245.774 | Q87: =Q86*(1+$B$5)+P87 -> 591397.13
A88: 74 | B88: =B87*(1+$B$4) -> 2656.6934 | C88: =B37*12 -> 31880.321 | D88: =D87*(1+$B$4) -> 2915.0465 | E88: =D88*12 -> 34980.558 | F88: =F87*(1+$B$4) -> 31879.245 | G88: =(E88+C88)-F88 -> 34981.634 | H88: =H87*(1+$B$5)+G88 -> 854918.21 | J88: 74 | K88: =K87*(1+$B$4) -> 3862.5504 | L88: =K88*12 -> 46350.604 | M88: =M87*(1+$B$4) -> 2915.0465 | N88: =M88*12 -> 34980.558 | O88: =O87*(1+$B$4) -> 31879.245 | P88: =(L88+N88)-O88 -> 49451.918 | Q88: =Q87*(1+$B$5)+P88 -> 660128.59
A89: 75 | B89: =B88*(1+$B$4) -> 2723.1107 | C89: =B38*12 -> 32677.329 | D89: =D88*(1+$B$4) -> 2987.9227 | E89: =D89*12 -> 35855.072 | F89: =F88*(1+$B$4) -> 32676.226 | G89: =(E89+C89)-F89 -> 35856.175 | H89: =H88*(1+$B$5)+G89 -> 918644.72 | J89: 75 | K89: =K88*(1+$B$4) -> 3959.1141 | L89: =K89*12 -> 47509.37 | M89: =M88*(1+$B$4) -> 2987.9227 | N89: =M89*12 -> 35855.072 | O89: =O88*(1+$B$4) -> 32676.226 | P89: =(L89+N89)-O89 -> 50688.216 | Q89: =Q88*(1+$B$5)+P89 -> 732337
A90: 76 | B90: =B89*(1+$B$4) -> 2791.1885 | C90: =B39*12 -> 33494.262 | D90: =D89*(1+$B$4) -> 3062.6208 | E90: =D90*12 -> 36751.449 | F90: =F89*(1+$B$4) -> 33493.131 | G90: =(E90+C90)-F90 -> 36752.579 | H90: =H89*(1+$B$5)+G90 -> 985345.12 | J90: 76 | K90: =K89*(1+$B$4) -> 4058.092 | L90: =K90*12 -> 48697.104 | M90: =M89*(1+$B$4) -> 3062.6208 | N90: =M90*12 -> 36751.449 | O90: =O89*(1+$B$4) -> 33493.131 | P90: =(L90+N90)-O90 -> 51955.421 | Q90: =Q89*(1+$B$5)+P90 -> 808166.61
A91: 77 | B91: =B90*(1+$B$4) -> 2860.9682 | C91: =B40*12 -> 34331.618 | D91: =D90*(1+$B$4) -> 3139.1863 | E91: =D91*12 -> 37670.235 | F91: =F90*(1+$B$4) -> 34330.46 | G91: =(E91+C91)-F91 -> 37671.394 | H91: =H90*(1+$B$5)+G91 -> 1055138.8 | J91: 77 | K91: =K90*(1+$B$4) -> 4159.5443 | L91: =K91*12 -> 49914.531 | M91: =M90*(1+$B$4) -> 3139.1863 | N91: =M91*12 -> 37670.235 | O91: =O90*(1+$B$4) -> 34330.46 | P91: =(L91+N91)-O91 -> 53254.307 | Q91: =Q90*(1+$B$5)+P91 -> 887767.15
A92: 78 | B92: =B91*(1+$B$4) -> 2932.4924 | C92: =B41*12 -> 35189.909 | D92: =D91*(1+$B$4) -> 3217.6659 | E92: =D92*12 -> 38611.991 | F92: =F91*(1+$B$4) -> 35188.721 | G92: =(E92+C92)-F92 -> 38613.179 | H92: =H91*(1+$B$5)+G92 -> 1128149.5 | J92: 78 | K92: =K91*(1+$B$4) -> 4263.5329 | L92: =K92*12 -> 51162.395 | M92: =M91*(1+$B$4) -> 3217.6659 | N92: =M92*12 -> 38611.991 | O92: =O91*(1+$B$4) -> 35188.721 | P92: =(L92+N92)-O92 -> 54585.665 | Q92: =Q91*(1+$B$5)+P92 -> 971294.02
A93: 79 | B93: =B92*(1+$B$4) -> 3005.8047 | C93: =B42*12 -> 36069.657 | D93: =D92*(1+$B$4) -> 3298.1076 | E93: =D93*12 -> 39577.291 | F93: =F92*(1+$B$4) -> 36068.439 | G93: =(E93+C93)-F93 -> 39578.508 | H93: =H92*(1+$B$5)+G93 -> 1204505.6 | J93: 79 | K93: =K92*(1+$B$4) -> 4370.1212 | L93: =K93*12 -> 52441.455 | M93: =M92*(1+$B$4) -> 3298.1076 | N93: =M93*12 -> 39577.291 | O93: =O92*(1+$B$4) -> 36068.439 | P93: =(L93+N93)-O93 -> 55950.306 | Q93: =Q92*(1+$B$5)+P93 -> 1058908.5
A94: 80 | B94: =B93*(1+$B$4) -> 3080.9498 | C94: =B43*12 -> 36971.398 | D94: =D93*(1+$B$4) -> 3380.5603 | E94: =D94*12 -> 40566.723 | F94: =F93*(1+$B$4) -> 36970.15 | G94: =(E94+C94)-F94 -> 40567.971 | H94: =H93*(1+$B$5)+G94 -> 1284340.5 | J94: 80 | K94: =K93*(1+$B$4) -> 4479.3742 | L94: =K94*12 -> 53752.491 | M94: =M93*(1+$B$4) -> 3380.5603 | N94: =M94*12 -> 40566.723 | O94: =O93*(1+$B$4) -> 36970.15 | P94: =(L94+N94)-O94 -> 57349.064 | Q94: =Q93*(1+$B$5)+P94 -> 1150778
A95: 81 | B95: =B94*(1+$B$4) -> 3157.9736 | C95: =B44*12 -> 37895.683 | D95: =D94*(1+$B$4) -> 3465.0743 | E95: =D95*12 -> 41580.891 | F95: =F94*(1+$B$4) -> 37894.404 | G95: =(E95+C95)-F95 -> 41582.17 | H95: =H94*(1+$B$5)+G95 -> 1367792.2 | J95: 81 | K95: =K94*(1+$B$4) -> 4591.3586 | L95: =K95*12 -> 55096.303 | M95: =M94*(1+$B$4) -> 3465.0743 | N95: =M95*12 -> 41580.891 | O95: =O94*(1+$B$4) -> 37894.404 | P95: =(L95+N95)-O95 -> 58782.791 | Q95: =Q94*(1+$B$5)+P95 -> 1247076.1
A96: 82 | B96: =B95*(1+$B$4) -> 3236.9229 | C96: =B45*12 -> 38843.075 | D96: =D95*(1+$B$4) -> 3551.7011 | E96: =D96*12 -> 42620.414 | F96: =F95*(1+$B$4) -> 38841.764 | G96: =(E96+C96)-F96 -> 42621.725 | H96: =H95*(1+$B$5)+G96 -> 1455003.9 | J96: 82 | K96: =K95*(1+$B$4) -> 4706.1426 | L96: =K96*12 -> 56473.711 | M96: =M95*(1+$B$4) -> 3551.7011 | N96: =M96*12 -> 42620.414 | O96: =O95*(1+$B$4) -> 38841.764 | P96: =(L96+N96)-O96 -> 60252.36 | Q96: =Q95*(1+$B$5)+P96 -> 1347983.2
... A114: 100 | B114: =B113*(1+$B$4) -> 5048.495 | C114: =B63*12 -> 60581.941 | D114: =D113*(1+$B$4) -> 5539.4416 | E114: =D114*12 -> 66473.3 | F114: =F113*(1+$B$4) -> 60579.896 | G114: =(E114+C114)-F114 -> 66475.344 | H114: =H113*(1+$B$5)+G114 -> 3867079.1 | J114: 100 | K114: =K113*(1+$B$4) -> 7339.9763 | L114: =K114*12 -> 88079.715 | M114: =M113*(1+$B$4) -> 5539.4416 | N114: =M114*12 -> 66473.3 | O114: =O113*(1+$B$4) -> 60579.896 | P114: =(L114+N114)-O114 -> 93973.119 | Q114: =Q113*(1+$B$5)+P114 -> 4203848.1
A123: Frank | J123: Bill
A124: Age | B124: Montly benefit | C124: Yearly Benefit | D124: 90% of Franks Yearly benefit | E124: Spouse Montly benefit | F124: Spouse Yearly Benefit | G124: Yearly Expenses | H124: expenses vs income | I124: Saving | K124: Age | L124: Montly benefit | M124: Yearly Benefit | N124: 90% of Bills Yearly Benefit | O124: Spouse Monthly Benefit | P124: Spouse Yearly Benefit | Q124: Yearly Expenses | R124: Expenses vs Income | S124: Saving
A125: 62 | B125: =B12 -> 1975.4 | C125: =B125*12 -> 23704.8 | D125: =C125*0.9 -> 21334.32 | E125: =$G$15 -> 2167.5 | F125: =IF(A125<=$H$4,E125*12,D125) -> 26010 | G125: =$B$9 -> 23704 | H125: =(F125+C125)-G125 -> 26010.8 | I125: =$H$4*(1+$B$5)+H125 -> 284160.8 | K125: 62 | L125: 0 | M125: =L125*12 -> 0 | N125: =M125*$B$4 -> 0 | O125: =E125 -> 2167.5 | P125: =O125*12 -> 26010 | Q125: =$B$9 -> 23704 | R125: =IF(K125<=$H$6,(M125+P125)-Q125,(IF(P125>=N125,P125-Q125,N125-G126))) -> 2306 | S125: =($H$4)*(1+$B$5)+P125+R125-C125 -> 262761.2
A126: 63 | B126: =B125*(1+$B$4) -> 2024.785 | C126: =B126*12 -> 24297.42 | D126: =C126*0.9 -> 21867.678 | E126: =E125*(1+$B$4) -> 2221.6875 | F126: =E126*12 -> 26660.25 | G126: =G125*(1+$B$4) -> 24296.6 | H126: =IF(A126<=$H$5,C126+F126-G126,(IF(F126>=D126,F126-G126,D125-G126))) -> 26661.07 | I126: =I125*(1+$B$5)+H126 -> 320085.51 | K126: 63 | L126: 0 | M126: =L126*12 -> 0 | N126: =M126*$B$4 -> 0 | O126: =O125*(1+$B$4) -> 2221.6875 | P126: =O126*12 -> 26660.25 | Q126: =Q125*(1+$B$4) -> 24296.6 | R126: =IF(K126<=$H$5,(M126+P126)-Q126,(IF(P126>=N126,P126-Q126,N126-Q126))) -> 2363.65 | S126: =S125*(1+$B$5)+R126 -> 273690.87
A127: 64 | B127: =B126*(1+$B$4) -> 2075.4046 | C127: =B127*12 -> 24904.855 | D127: =C127*0.9 -> 22414.37 | E127: =E126*(1+$B$4) -> 2277.2297 | F127: =E127*12 -> 27326.756 | G127: =G126*(1+$B$4) -> 24904.015 | H127: =IF(A127<=$H$5,C127+F127-G127,(IF(F127>=D127,F127-G127,D126-G127))) -> 27327.597 | I127: =I126*(1+$B$5)+H127 -> 357847.9 | K127: 64 | L127: 0 | M127: =L127*12 -> 0 | N127: =M127*$B$4 -> 0 | O127: =O126*(1+$B$4) -> 2277.2297 | P127: =O127*12 -> 27326.756 | Q127: =Q126*(1+$B$4) -> 24904.015 | R127: =IF(K127<=$H$5,(M127+P127)-Q127,(IF(P127>=N127,P127-Q127,N127-Q127))) -> 2422.7413 | S127: =S126*(1+$B$5)+R127 -> 285035.93
A128: 65 | B128: =B127*(1+$B$4) -> 2127.2897 | C128: =B128*12 -> 25527.477 | D128: =C128*0.9 -> 22974.729 | E128: =E127*(1+$B$4) -> 2334.1604 | F128: =E128*12 -> 28009.925 | G128: =G127*(1+$B$4) -> 25526.615 | H128: =IF(A128<=$H$5,C128+F128-G128,(IF(F128>=D128,F128-G128,D127-G128))) -> 28010.787 | I128: =I127*(1+$B$5)+H128 -> 397524.52 | K128: 65 | L128: 0 | M128: =L128*12 -> 0 | N128: =M128*$B$4 -> 0 | O128: =O127*(1+$B$4) -> 2334.1604 | P128: =O128*12 -> 28009.925 | Q128: =Q127*(1+$B$4) -> 25526.615 | R128: =IF(K128<=$H$5,(M128+P128)-Q128,(IF(P128>=N128,P128-Q128,N128-Q128))) -> 2483.3098 | S128: =S127*(1+$B$5)+R128 -> 296811.41
A129: 66 | B129: =B128*(1+$B$4) -> 2180.472 | C129: =B129*12 -> 26165.664 | D129: =C129*0.9 -> 23549.097 | E129: =E128*(1+$B$4) -> 2392.5144 | F129: =E129*12 -> 28710.173 | G129: =G128*(1+$B$4) -> 26164.781 | H129: =IF(A129<=$H$5,C129+F129-G129,(IF(F129>=D129,F129-G129,D128-G129))) -> 28711.056 | I129: =I128*(1+$B$5)+H129 -> 439194.88 | K129: 66 | L129: 0 | M129: =L129*12 -> 0 | N129: =M129*$B$4 -> 0 | O129: =O128*(1+$B$4) -> 2392.5144 | P129: =O129*12 -> 28710.173 | Q129: =Q128*(1+$B$4) -> 26164.781 | R129: =IF(K129<=$H$5,(M129+P129)-Q129,(IF(P129>=N129,P129-Q129,N129-Q129))) -> 2545.3925 | S129: =S128*(1+$B$5)+R129 -> 309032.85
A130: 67 | B130: =B129*(1+$B$4) -> 2234.9838 | C130: =B130*12 -> 26819.805 | D130: =C130*0.9 -> 24137.825 | E130: =E129*(1+$B$4) -> 2452.3273 | F130: =E130*12 -> 29427.928 | G130: =G129*(1+$B$4) -> 26818.9 | H130: =IF(A130<=$H$5,C130+F130-G130,(IF(F130>=D130,F130-G130,D129-G130))) -> 29428.833 | I130: =I129*(1+$B$5)+H130 -> 482941.47 | K130: 67 | L130: 0 | M130: =L130*12 -> 0 | N130: =M130*$B$4 -> 0 | O130: =O129*(1+$B$4) -> 2452.3273 | P130: =O130*12 -> 29427.928 | Q130: =Q129*(1+$B$4) -> 26818.9 | R130: =IF(K130<=$H$5,(M130+P130)-Q130,(IF(P130>=N130,P130-Q130,N130-Q130))) -> 2609.0273 | S130: =S129*(1+$B$5)+R130 -> 321716.35
A131: 68 | B131: =B130*(1+$B$4) -> 2290.8584 | C131: =B131*12 -> 27490.301 | D131: =C131*0.9 -> 24741.27 | E131: =E130*(1+$B$4) -> 2513.6355 | F131: =E131*12 -> 30163.626 | G131: =G130*(1+$B$4) -> 27489.373 | H131: =IF(A131<=$H$5,C131+F131-G131,(IF(F131>=D131,F131-G131,D130-G131))) -> 30164.554 | I131: =I130*(1+$B$5)+H131 -> 528849.91 | K131: 68 | L131: 0 | M131: =L131*12 -> 0 | N131: =M131*$B$4 -> 0 | O131: =O130*(1+$B$4) -> 2513.6355 | P131: =O131*12 -> 30163.626 | Q131: =Q130*(1+$B$4) -> 27489.373 | R131: =IF(K131<=$H$5,(M131+P131)-Q131,(IF(P131>=N131,P131-Q131,N131-Q131))) -> 2674.253 | S131: =S130*(1+$B$5)+R131 -> 334878.56
A132: 69 | B132: =B131*(1+$B$4) -> 2348.1298 | C132: =B132*12 -> 28177.558 | D132: =C132*0.9 -> 25359.802 | E132: =E131*(1+$B$4) -> 2576.4764 | F132: =E132*12 -> 30917.716 | G132: =G131*(1+$B$4) -> 28176.607 | H132: =IF(A132<=$H$5,C132+F132-G132,(IF(F132>=D132,F132-G132,D131-G132))) -> 30918.667 | I132: =I131*(1+$B$5)+H132 -> 577009.09 | K132: 69 | L132: 0 | M132: =L132*12 -> 0 | N132: =M132*$B$4 -> 0 | O132: =O131*(1+$B$4) -> 2576.4764 | P132: =O132*12 -> 30917.716 | Q132: =Q131*(1+$B$4) -> 28176.607 | R132: =IF(K132<=$H$5,(M132+P132)-Q132,(IF(P132>=N132,P132-Q132,N132-Q132))) -> 2741.1093 | S132: =S131*(1+$B$5)+R132 -> 348536.71
A133: 70 | B133: =B132*(1+$B$4) -> 2406.8331 | C133: =B133*12 -> 28881.997 | D133: =C133*0.9 -> 25993.797 | E133: =E132*(1+$B$4) -> 2640.8883 | F133: =E133*12 -> 31690.659 | G133: =G132*(1+$B$4) -> 28881.022 | H133: =IF(A133<=$H$5,C133+F133-G133,(IF(F133>=D133,F133-G133,D132-G133))) -> 31691.634 | I133: =I132*(1+$B$5)+H133 -> 627511.22 | K133: 70 | L133: =B20 -> 3499.28 | M133: =L133*12 -> 41991.36 | N133: =M133*0.9 -> 37792.224 | O133: =O132*(1+$B$4) -> 2640.8883 | P133: =O133*12 -> 31690.659 | Q133: =Q132*(1+$B$4) -> 28881.022 | R133: =IF(K133<=$H$5,(M133+P133)-Q133,(IF(P133>=N133,P133-Q133,N133-Q133))) -> 44800.997 | S133: =S132*(1+$B$5)+R133 -> 404700
A134: 71 | B134: =B133*(1+$B$4) -> 2467.0039 | C134: =B134*12 -> 29604.047 | D134: =C134*0.9 -> 26643.642 | E134: =E133*(1+$B$4) -> 2706.9105 | F134: =E134*12 -> 32482.926 | G134: =G133*(1+$B$4) -> 29603.048 | H134: =IF(A134<=$H$5,C134+F134-G134,(IF(F134>=D134,F134-G134,D133-G134))) -> 32483.925 | I134: =I133*(1+$B$5)+H134 -> 680452.01 | K134: 71 | L134: =L133*(1+$B$4) -> 3586.762 | M134: =L134*12 -> 43041.144 | N134: =M134*0.9 -> 38737.03 | O134: =O133*(1+$B$4) -> 2706.9105 | P134: =O134*12 -> 32482.926 | Q134: =Q133*(1+$B$4) -> 29603.048 | R134: =IF(K134<=$H$5,(M134+P134)-Q134,(IF(P134>=N134,P134-Q134,N134-Q134))) -> 45921.022 | S134: =S133*(1+$B$5)+R134 -> 463814.24
A135: 72 | B135: =B134*(1+$B$4) -> 2528.679 | C135: =B135*12 -> 30344.148 | D135: =C135*0.9 -> 27309.733 | E135: =E134*(1+$B$4) -> 2774.5832 | F135: =E135*12 -> 33294.999 | G135: =G134*(1+$B$4) -> 30343.124 | H135: =IF(A135<=$H$5,C135+F135-G135,(IF(F135>=D135,F135-G135,D134-G135))) -> 33296.023 | I135: =I134*(1+$B$5)+H135 -> 735930.77 | K135: 72 | L135: =L134*(1+$B$4) -> 3676.431 | M135: =L135*12 -> 44117.173 | N135: =M135*0.9 -> 39705.455 | O135: =O134*(1+$B$4) -> 2774.5832 | P135: =O135*12 -> 33294.999 | Q135: =Q134*(1+$B$4) -> 30343.124 | R135: =IF(K135<=$H$5,(M135+P135)-Q135,(IF(P135>=N135,P135-Q135,N135-Q135))) -> 47069.048 | S135: =S134*(1+$B$5)+R135 -> 526003.64
A136: 73 | B136: =B135*(1+$B$4) -> 2591.896 | C136: =B136*12 -> 31102.752 | D136: =C136*0.9 -> 27992.477 | E136: =E135*(1+$B$4) -> 2843.9478 | F136: =E136*12 -> 34127.374 | G136: =G135*(1+$B$4) -> 31101.702 | H136: =IF(A136<=$H$5,C136+F136-G136,(IF(F136>=D136,F136-G136,D135-G136))) -> 34128.424 | I136: =I135*(1+$B$5)+H136 -> 794050.53 | K136: 73 | L136: =L135*(1+$B$4) -> 3768.3418 | M136: =L136*12 -> 45220.102 | N136: =M136*0.9 -> 40698.092 | O136: =O135*(1+$B$4) -> 2843.9478 | P136: =O136*12 -> 34127.374 | Q136: =Q135*(1+$B$4) -> 31101.702 | R136: =IF(K136<=$H$5,(M136+P136)-Q136,(IF(P136>=N136,P136-Q136,N136-Q136))) -> 48245.774 | S136: =S135*(1+$B$5)+R136 -> 591397.13
A137: 74 | B137: =B136*(1+$B$4) -> 2656.6934 | C137: =B137*12 -> 31880.321 | D137: =C137*0.9 -> 28692.289 | E137: =E136*(1+$B$4) -> 2915.0465 | F137: =E137*12 -> 34980.558 | G137: =G136*(1+$B$4) -> 31879.245 | H137: =IF(A137<=$H$5,C137+F137-G137,(IF(F137>=D137,F137-G137,D136-G137))) -> 34981.634 | I137: =I136*(1+$B$5)+H137 -> 854918.21 | K137: 74 | L137: =L136*(1+$B$4) -> 3862.5504 | M137: =L137*12 -> 46350.604 | N137: =M137*0.9 -> 41715.544 | O137: =O136*(1+$B$4) -> 2915.0465 | P137: =O137*12 -> 34980.558 | Q137: =Q136*(1+$B$4) -> 31879.245 | R137: =IF(K137<=$H$5,(M137+P137)-Q137,(IF(P137>=N137,P137-Q137,N137-Q137))) -> 49451.918 | S137: =S136*(1+$B$5)+R137 -> 660128.59 | Y137: ="Compare Saving of Married Frank and Bill at rate of return of " & B5*100 & "% and Cola of " & B4*100 & "% " & "Yearly Expenses = $" & B9 & " Frank and Bill pass at age " & H5 -> Compare Saving of Married Frank and Bill at rate of return of 3.26% and Cola of 2.5% Yearly Expenses = $23704 Frank and Bill pass at age 80
A138: 75 | B138: =B137*(1+$B$4) -> 2723.1107 | C138: =B138*12 -> 32677.329 | D138: =C138*0.9 -> 29409.596 | E138: =E137*(1+$B$4) -> 2987.9227 | F138: =E138*12 -> 35855.072 | G138: =G137*(1+$B$4) -> 32676.226 | H138: =IF(A138<=$H$5,C138+F138-G138,(IF(F138>=D138,F138-G138,D137-G138))) -> 35856.175 | I138: =I137*(1+$B$5)+H138 -> 918644.72 | K138: 75 | L138: =L137*(1+$B$4) -> 3959.1141 | M138: =L138*12 -> 47509.37 | N138: =M138*0.9 -> 42758.433 | O138: =O137*(1+$B$4) -> 2987.9227 | P138: =O138*12 -> 35855.072 | Q138: =Q137*(1+$B$4) -> 32676.226 | R138: =IF(K138<=$H$5,(M138+P138)-Q138,(IF(P138>=N138,P138-Q138,N138-Q138))) -> 50688.216 | S138: =S137*(1+$B$5)+R138 -> 732337
A139: 76 | B139: =B138*(1+$B$4) -> 2791.1885 | C139: =B139*12 -> 33494.262 | D139: =C139*0.9 -> 30144.836 | E139: =E138*(1+$B$4) -> 3062.6208 | F139: =E139*12 -> 36751.449 | G139: =G138*(1+$B$4) -> 33493.131 | H139: =IF(A139<=$H$5,C139+F139-G139,(IF(F139>=D139,F139-G139,D138-G139))) -> 36752.579 | I139: =I138*(1+$B$5)+H139 -> 985345.12 | K139: 76 | L139: =L138*(1+$B$4) -> 4058.092 | M139: =L139*12 -> 48697.104 | N139: =M139*0.9 -> 43827.393 | O139: =O138*(1+$B$4) -> 3062.6208 | P139: =O139*12 -> 36751.449 | Q139: =Q138*(1+$B$4) -> 33493.131 | R139: =IF(K139<=$H$5,(M139+P139)-Q139,(IF(P139>=N139,P139-Q139,N139-Q139))) -> 51955.421 | S139: =S138*(1+$B$5)+R139 -> 808166.61
A140: 77 | B140: =B139*(1+$B$4) -> 2860.9682 | C140: =B140*12 -> 34331.618 | D140: =C140*0.9 -> 30898.457 | E140: =E139*(1+$B$4) -> 3139.1863 | F140: =E140*12 -> 37670.235 | G140: =G139*(1+$B$4) -> 34330.46 | H140: =IF(A140<=$H$5,C140+F140-G140,(IF(F140>=D140,F140-G140,D139-G140))) -> 37671.394 | I140: =I139*(1+$B$5)+H140 -> 1055138.8 | K140: 77 | L140: =L139*(1+$B$4) -> 4159.5443 | M140: =L140*12 -> 49914.531 | N140: =M140*0.9 -> 44923.078 | O140: =O139*(1+$B$4) -> 3139.1863 | P140: =O140*12 -> 37670.235 | Q140: =Q139*(1+$B$4) -> 34330.46 | R140: =IF(K140<=$H$5,(M140+P140)-Q140,(IF(P140>=N140,P140-Q140,N140-Q140))) -> 53254.307 | S140: =S139*(1+$B$5)+R140 -> 887767.15
A141: 78 | B141: =B140*(1+$B$4) -> 2932.4924 | C141: =B141*12 -> 35189.909 | D141: =C141*0.9 -> 31670.918 | E141: =E140*(1+$B$4) -> 3217.6659 | F141: =E141*12 -> 38611.991 | G141: =G140*(1+$B$4) -> 35188.721 | H141: =IF(A141<=$H$5,C141+F141-G141,(IF(F141>=D141,F141-G141,D140-G141))) -> 38613.179 | I141: =I140*(1+$B$5)+H141 -> 1128149.5 | K141: 78 | L141: =L140*(1+$B$4) -> 4263.5329 | M141: =L141*12 -> 51162.395 | N141: =M141*0.9 -> 46046.155 | O141: =O140*(1+$B$4) -> 3217.6659 | P141: =O141*12 -> 38611.991 | Q141: =Q140*(1+$B$4) -> 35188.721 | R141: =IF(K141<=$H$5,(M141+P141)-Q141,(IF(P141>=N141,P141-Q141,N141-Q141))) -> 54585.665 | S141: =S140*(1+$B$5)+R141 -> 971294.02
A142: 79 | B142: =B141*(1+$B$4) -> 3005.8047 | C142: =B142*12 -> 36069.657 | D142: =C142*0.9 -> 32462.691 | E142: =E141*(1+$B$4) -> 3298.1076 | F142: =E142*12 -> 39577.291 | G142: =G141*(1+$B$4) -> 36068.439 | H142: =IF(A142<=$H$5,C142+F142-G142,(IF(F142>=D142,F142-G142,D141-G142))) -> 39578.508 | I142: =I141*(1+$B$5)+H142 -> 1204505.6 | K142: 79 | L142: =L141*(1+$B$4) -> 4370.1212 | M142: =L142*12 -> 52441.455 | N142: =M142*0.9 -> 47197.309 | O142: =O141*(1+$B$4) -> 3298.1076 | P142: =O142*12 -> 39577.291 | Q142: =Q141*(1+$B$4) -> 36068.439 | R142: =IF(K142<=$H$5,(M142+P142)-Q142,(IF(P142>=N142,P142-Q142,N142-Q142))) -> 55950.306 | S142: =S141*(1+$B$5)+R142 -> 1058908.5
A143: 80 | B143: =B142*(1+$B$4) -> 3080.9498 | C143: =B143*12 -> 36971.398 | D143: =C143*0.9 -> 33274.258 | E143: =E142*(1+$B$4) -> 3380.5603 | F143: =E143*12 -> 40566.723 | G143: =G142*(1+$B$4) -> 36970.15 | H143: =IF(A143<=$H$5,C143+F143-G143,(IF(F143>=D143,F143-G143,D142-G143))) -> 40567.971 | I143: =I142*(1+$B$5)+H143 -> 1284340.5 | K143: 80 | L143: =L142*(1+$B$4) -> 4479.3742 | M143: =L143*12 -> 53752.491 | N143: =M143*0.9 -> 48377.242 | O143: =O142*(1+$B$4) -> 3380.5603 | P143: =O143*12 -> 40566.723 | Q143: =Q142*(1+$B$4) -> 36970.15 | R143: =IF(K143<=$H$5,(M143+P143)-Q143,(IF(P143>=N143,P143-Q143,N143-Q143))) -> 57349.064 | S143: =S142*(1+$B$5)+R143 -> 1150778
A144: 81 | B144: =B143*(1+$B$4) -> 3157.9736 | C144: =B144*12 -> 37895.683 | D144: =C144*0.9 -> 34106.115 | E144: =E143*(1+$B$4) -> 3465.0743 | F144: =E144*12 -> 41580.891 | G144: =G143*(1+$B$4) -> 37894.404 | H144: =IF(A144<=$H$5,C144+F144-G144,(IF(F144>=D144,F144-G144,D143-G144))) -> 3686.4873 | I144: =I143*(1+$B$5)+H144 -> 1329896.5 | K144: 81 | L144: =L143*(1+$B$4) -> 4591.3586 | M144: =L144*12 -> 55096.303 | N144: =M144*0.9 -> 49586.673 | O144: =O143*(1+$B$4) -> 3465.0743 | P144: =O144*12 -> 41580.891 | Q144: =Q143*(1+$B$4) -> 37894.404 | R144: =IF(K144<=$H$5,(M144+P144)-Q144,(IF(P144>=N144,P144-Q144,N144-Q144))) -> 11692.269 | S144: =S143*(1+$B$5)+R144 -> 1199985.6
A145: 82 | B145: =B144*(1+$B$4) -> 3236.9229 | C145: =B145*12 -> 38843.075 | D145: =C145*0.9 -> 34958.767 | E145: =E144*(1+$B$4) -> 3551.7011 | F145: =E145*12 -> 42620.414 | G145: =G144*(1+$B$4) -> 38841.764 | H145: =IF(A145<=$H$5,C145+F145-G145,(IF(F145>=D145,F145-G145,D144-G145))) -> 3778.6495 | I145: =I144*(1+$B$5)+H145 -> 1377029.8 | K145: 82 | L145: =L144*(1+$B$4) -> 4706.1426 | M145: =L145*12 -> 56473.711 | N145: =M145*0.9 -> 50826.34 | O145: =O144*(1+$B$4) -> 3551.7011 | P145: =O145*12 -> 42620.414 | Q145: =Q144*(1+$B$4) -> 38841.764 | R145: =IF(K145<=$H$5,(M145+P145)-Q145,(IF(P145>=N145,P145-Q145,N145-Q145))) -> 11984.576 | S145: =S144*(1+$B$5)+R145 -> 1251089.7
A146: 83 | B146: =B145*(1+$B$4) -> 3317.846 | C146: =B146*12 -> 39814.152 | D146: =C146*0.9 -> 35832.737 | E146: =E145*(1+$B$4) -> 3640.4937 | F146: =E146*12 -> 43685.924 | G146: =G145*(1+$B$4) -> 39812.808 | H146: =IF(A146<=$H$5,C146+F146-G146,(IF(F146>=D146,F146-G146,D145-G146))) -> 3873.1157 | I146: =I145*(1+$B$5)+H146 -> 1425794.1 | K146: 83 | L146: =L145*(1+$B$4) -> 4823.7961 | M146: =L146*12 -> 57885.554 | N146: =M146*0.9 -> 52096.998 | O146: =O145*(1+$B$4) -> 3640.4937 | P146: =O146*12 -> 43685.924 | Q146: =Q145*(1+$B$4) -> 39812.808 | R146: =IF(K146<=$H$5,(M146+P146)-Q146,(IF(P146>=N146,P146-Q146,N146-Q146))) -> 12284.19 | S146: =S145*(1+$B$5)+R146 -> 1304159.4
A147: 84 | B147: =B146*(1+$B$4) -> 3400.7921 | C147: =B147*12 -> 40809.506 | D147: =C147*0.9 -> 36728.555 | E147: =E146*(1+$B$4) -> 3731.506 | F147: =E147*12 -> 44778.072 | G147: =G146*(1+$B$4) -> 40808.128 | H147: =IF(A147<=$H$5,C147+F147-G147,(IF(F147>=D147,F147-G147,D146-G147))) -> 3969.9436 | I147: =I146*(1+$B$5)+H147 -> 1476244.9 | K147: 84 | L147: =L146*(1+$B$4) -> 4944.391 | M147: =L147*12 -> 59332.692 | N147: =M147*0.9 -> 53399.423 | O147: =L147*0.9 -> 4449.9519 | P147: =O147*12 -> 53399.423 | Q147: =Q146*(1+$B$4) -> 40808.128 | R147: =IF(K147<=$H$5,(M147+P147)-Q147,(IF(P147>=N147,P147-Q147,N147-Q147))) -> 12591.295 | S147: =S146*(1+$B$5)+R147 -> 1359266.3
A148: 85 | B148: =B147*(1+$B$4) -> 3485.8119 | C148: =B148*12 -> 41829.743 | D148: =C148*0.9 -> 37646.769 | E148: =E147*(1+$B$4) -> 3824.7937 | F148: =E148*12 -> 45897.524 | G148: =G147*(1+$B$4) -> 41828.332 | H148: =IF(A148<=$H$5,C148+F148-G148,(IF(F148>=D148,F148-G148,D147-G148))) -> 4069.1922 | I148: =I147*(1+$B$5)+H148 -> 1528439.7 | K148: 85 | L148: =L147*(1+$B$4) -> 5068.0008 | M148: =L148*12 -> 60816.01 | N148: =M148*0.9 -> 54734.409 | O148: =L148*0.9 -> 4561.2007 | P148: =O148*12 -> 54734.409 | Q148: =Q147*(1+$B$4) -> 41828.332 | R148: =IF(K148<=$H$5,(M148+P148)-Q148,(IF(P148>=N148,P148-Q148,N148-Q148))) -> 12906.077 | S148: =S147*(1+$B$5)+R148 -> 1416484.5
A149: 86 | B149: =B148*(1+$B$4) -> 3572.9572 | C149: =B149*12 -> 42875.487 | D149: =C149*0.9 -> 38587.938 | E149: =E148*(1+$B$4) -> 3920.4135 | F149: =E149*12 -> 47044.962 | G149: =G148*(1+$B$4) -> 42874.04 | H149: =IF(A149<=$H$5,C149+F149-G149,(IF(F149>=D149,F149-G149,D148-G149))) -> 4170.922 | I149: =I148*(1+$B$5)+H149 -> 1582437.7 | K149: 86 | L149: =L148*(1+$B$4) -> 5194.7008 | M149: =L149*12 -> 62336.41 | N149: =M149*0.9 -> 56102.769 | O149: =L149*0.9 -> 4675.2307 | P149: =O149*12 -> 56102.769 | Q149: =Q148*(1+$B$4) -> 42874.04 | R149: =IF(K149<=$H$5,(M149+P149)-Q149,(IF(P149>=N149,P149-Q149,N149-Q149))) -> 13228.729 | S149: =S148*(1+$B$5)+R149 -> 1475890.6
A150: 87 | B150: =B149*(1+$B$4) -> 3662.2812 | C150: =B150*12 -> 43947.374 | D150: =C150*0.9 -> 39552.637 | E150: =E149*(1+$B$4) -> 4018.4238 | F150: =E150*12 -> 48221.086 | G150: =G149*(1+$B$4) -> 43945.891 | H150: =IF(A150<=$H$5,C150+F150-G150,(IF(F150>=D150,F150-G150,D149-G150))) -> 4275.1951 | I150: =I149*(1+$B$5)+H150 -> 1638300.4 | K150: 87 | L150: =L149*(1+$B$4) -> 5324.5683 | M150: =L150*12 -> 63894.82 | N150: =M150*0.9 -> 57505.338 | O150: =L150*0.9 -> 4792.1115 | P150: =O150*12 -> 57505.338 | Q150: =Q149*(1+$B$4) -> 43945.891 | R150: =IF(K150<=$H$5,(M150+P150)-Q150,(IF(P150>=N150,P150-Q150,N150-Q150))) -> 13559.447 | S150: =S149*(1+$B$5)+R150 -> 1537564.1
A151: 88 | B151: =B150*(1+$B$4) -> 3753.8382 | C151: =B151*12 -> 45046.058 | D151: =C151*0.9 -> 40541.453 | E151: =E150*(1+$B$4) -> 4118.8844 | F151: =E151*12 -> 49426.613 | G151: =G150*(1+$B$4) -> 45044.538 | H151: =IF(A151<=$H$5,C151+F151-G151,(IF(F151>=D151,F151-G151,D150-G151))) -> 4382.075 | I151: =I150*(1+$B$5)+H151 -> 1696091 | K151: 88 | L151: =L150*(1+$B$4) -> 5457.6826 | M151: =L151*12 -> 65492.191 | N151: =M151*0.9 -> 58942.972 | O151: =L151*0.9 -> 4911.9143 | P151: =O151*12 -> 58942.972 | Q151: =Q150*(1+$B$4) -> 45044.538 | R151: =IF(K151<=$H$5,(M151+P151)-Q151,(IF(P151>=N151,P151-Q151,N151-Q151))) -> 13898.433 | S151: =S150*(1+$B$5)+R151 -> 1601587.1
A152: 89 | B152: =B151*(1+$B$4) -> 3847.6842 | C152: =B152*12 -> 46172.21 | D152: =C152*0.9 -> 41554.989 | E152: =E151*(1+$B$4) -> 4221.8565 | F152: =E152*12 -> 50662.278 | G152: =G151*(1+$B$4) -> 46170.652 | H152: =IF(A152<=$H$5,C152+F152-G152,(IF(F152>=D152,F152-G152,D151-G152))) -> 4491.6268 | I152: =I151*(1+$B$5)+H152 -> 1755875.2 | K152: 89 | L152: =L151*(1+$B$4) -> 5594.1246 | M152: =L152*12 -> 67129.495 | N152: =M152*0.9 -> 60416.546 | O152: =L152*0.9 -> 5034.7122 | P152: =O152*12 -> 60416.546 | Q152: =Q151*(1+$B$4) -> 46170.652 | R152: =IF(K152<=$H$5,(M152+P152)-Q152,(IF(P152>=N152,P152-Q152,N152-Q152))) -> 14245.894 | S152: =S151*(1+$B$5)+R152 -> 1668044.8
A153: 90 | B153: =B152*(1+$B$4) -> 3943.8763 | C153: =B153*12 -> 47326.515 | D153: =C153*0.9 -> 42593.864 | E153: =E152*(1+$B$4) -> 4327.403 | F153: =E153*12 -> 51928.835 | G153: =G152*(1+$B$4) -> 47324.918 | H153: =IF(A153<=$H$5,C153+F153-G153,(IF(F153>=D153,F153-G153,D152-G153))) -> 4603.9175 | I153: =I152*(1+$B$5)+H153 -> 1817720.7 | K153: 90 | L153: =L152*(1+$B$4) -> 5733.9777 | M153: =L153*12 -> 68807.733 | N153: =M153*0.9 -> 61926.96 | O153: =L153*0.9 -> 5160.58 | P153: =O153*12 -> 61926.96 | Q153: =Q152*(1+$B$4) -> 47324.918 | R153: =IF(K153<=$H$5,(M153+P153)-Q153,(IF(P153>=N153,P153-Q153,N153-Q153))) -> 14602.042 | S153: =S152*(1+$B$5)+R153 -> 1737025.1
A154: 91 | B154: =B153*(1+$B$4) -> 4042.4732 | C154: =B154*12 -> 48509.678 | D154: =C154*0.9 -> 43658.71 | E154: =E153*(1+$B$4) -> 4435.588 | F154: =E154*12 -> 53227.056 | G154: =G153*(1+$B$4) -> 48508.041 | H154: =IF(A154<=$H$5,C154+F154-G154,(IF(F154>=D154,F154-G154,D153-G154))) -> 4719.0155 | I154: =I153*(1+$B$5)+H154 -> 1881697.4 | K154: 91 | L154: =L153*(1+$B$4) -> 5877.3272 | M154: =L154*12 -> 70527.926 | N154: =M154*0.9 -> 63475.134 | O154: =L154*0.9 -> 5289.5945 | P154: =O154*12 -> 63475.134 | Q154: =Q153*(1+$B$4) -> 48508.041 | R154: =IF(K154<=$H$5,(M154+P154)-Q154,(IF(P154>=N154,P154-Q154,N154-Q154))) -> 14967.093 | S154: =S153*(1+$B$5)+R154 -> 1808619.2
A155: 92 | B155: =B154*(1+$B$4) -> 4143.535 | C155: =B155*12 -> 49722.42 | D155: =C155*0.9 -> 44750.178 | E155: =E154*(1+$B$4) -> 4546.4777 | F155: =E155*12 -> 54557.733 | G155: =G154*(1+$B$4) -> 49720.742 | H155: =IF(A155<=$H$5,C155+F155-G155,(IF(F155>=D155,F155-G155,D154-G155))) -> 4836.9908 | I155: =I154*(1+$B$5)+H155 -> 1947877.7 | K155: 92 | L155: =L154*(1+$B$4) -> 6024.2604 | M155: =L155*12 -> 72291.124 | N155: =M155*0.9 -> 65062.012 | O155: =L155*0.9 -> 5421.8343 | P155: =O155*12 -> 65062.012 | Q155: =Q154*(1+$B$4) -> 49720.742 | R155: =IF(K155<=$H$5,(M155+P155)-Q155,(IF(P155>=N155,P155-Q155,N155-Q155))) -> 15341.27 | S155: =S154*(1+$B$5)+R155 -> 1882921.4
A156: 93 | B156: =B155*(1+$B$4) -> 4247.1234 | C156: =B156*12 -> 50965.48 | D156: =C156*0.9 -> 45868.932 | E156: =E155*(1+$B$4) -> 4660.1397 | F156: =E156*12 -> 55921.676 | G156: =G155*(1+$B$4) -> 50963.76 | H156: =IF(A156<=$H$5,C156+F156-G156,(IF(F156>=D156,F156-G156,D155-G156))) -> 4957.9156 | I156: =I155*(1+$B$5)+H156 -> 2016336.5 | K156: 93 | L156: =L155*(1+$B$4) -> 6174.8669 | M156: =L156*12 -> 74098.402 | N156: =M156*0.9 -> 66688.562 | O156: =L156*0.9 -> 5557.3802 | P156: =O156*12 -> 66688.562 | Q156: =Q155*(1+$B$4) -> 50963.76 | R156: =IF(K156<=$H$5,(M156+P156)-Q156,(IF(P156>=N156,P156-Q156,N156-Q156))) -> 15724.802 | S156: =S155*(1+$B$5)+R156 -> 1960029.5
...

Sheet RMD Tables 2025
B4: Table III | G4: Discount Rate | H4: =Main!B6 -> 0.025
B5: (Uniform Lifetime) | G5: Balance at 72 | H5: 2000000
B6: (For Use by: | G6: Cola | H6: =Main!B5 -> 0.025
B7: Unmarried Owners,
B8: Married Owners Whose Spouses Aren't More Than 10 Years Younger, and
B9: Married Owners Whose Spouses Aren't the Sole Beneficiaries of Their IRAs)
B11: Age | C11: Distribution Period | D11: Age | E11: Distribution Period | H11: Balance at 72 | J11: RMD | K11: Cola Adjusted Initial RMD | M11: Balance/RMD %
B12: 72 | C12: 27.4 | D12: 97 | E12: 7.8 | G12: 72 | H12: =H5 -> 2000000 | I12: =C12 -> 27.4 | J12: =H12/I12 -> 72992.701 | M12: =J12/H12 -> 0.03649635
B13: 73 | C13: 26.5 | D13: 98 | E13: 7.3 | G13: 73 | H13: =(H12-J12)*(1+$H$4) -> 1975182.5 | I13: =C13 -> 26.5 | J13: =H13/I13 -> 74535.188 | K13: =J12*(1+$H$6) -> 74817.518 | M13: =J13/H13 -> 0.037735849
B14: 74 | C14: 25.5 | D14: 99 | E14: 6.8 | G14: 74 | H14: =(H13-J13)*(1+$H$4) -> 1948163.5 | I14: =C14 -> 25.5 | J14: =H14/I14 -> 76398.568 | K14: =K13*(1+$H$6) -> 76687.956 | M14: =J14/H14 -> 0.039215686
B15: 75 | C15: 24.6 | D15: 100 | E15: 6.4 | G15: 75 | H15: =(H14-J14)*(1+$H$4) -> 1918559 | I15: =C15 -> 24.6 | J15: =H15/I15 -> 77990.205 | K15: =K14*(1+$H$6) -> 78605.155 | M15: =J15/H15 -> 0.040650407
B16: 76 | C16: 23.7 | D16: 101 | E16: 6 | G16: 76 | H16: =(H15-J15)*(1+$H$4) -> 1886583 | I16: =C16 -> 23.7 | J16: =H16/I16 -> 79602.66 | K16: =K15*(1+$H$6) -> 80570.284 | M16: =J16/H16 -> 0.042194093
B17: 77 | C17: 22.9 | D17: 102 | E17: 5.6 | G17: 77 | H17: =(H16-J16)*(1+$H$4) -> 1852154.9 | I17: =C17 -> 22.9 | J17: =H17/I17 -> 80880.126 | K17: =K16*(1+$H$6) -> 82584.541 | M17: =J17/H17 -> 0.043668122
B18: 78 | C18: 22 | D18: 103 | E18: 5.2 | G18: 78 | H18: =(H17-J17)*(1+$H$4) -> 1815556.6 | I18: =C18 -> 22 | J18: =H18/I18 -> 82525.302 | K18: =K17*(1+$H$6) -> 84649.155 | M18: =J18/H18 -> 0.045454545
B19: 79 | C19: 21.1 | D19: 104 | E19: 4.9 | G19: 79 | H19: =(H18-J18)*(1+$H$4) -> 1776357.1 | I19: =C19 -> 21.1 | J19: =H19/I19 -> 84187.541 | K19: =K18*(1+$H$6) -> 86765.383 | M19: =J19/H19 -> 0.047393365
B20: 80 | C20: 20.2 | D20: 105 | E20: 4.6 | G20: 80 | H20: =(H19-J19)*(1+$H$4) -> 1734473.8 | I20: =C20 -> 20.2 | J20: =H20/I20 -> 85865.041 | K20: =K19*(1+$H$6) -> 88934.518 | M20: =J20/H20 -> 0.04950495
B21: 81 | C21: 19.4 | D21: 106 | E21: 4.3 | G21: 81 | H21: =(H20-J20)*(1+$H$4) -> 1689824 | I21: =C21 -> 19.4 | J21: =H21/I21 -> 87104.33 | K21: =K20*(1+$H$6) -> 91157.881 | M21: =J21/H21 -> 0.051546392
B22: 82 | C22: 18.5 | D22: 107 | E22: 4.1 | G22: 82 | H22: =(H21-J21)*(1+$H$4) -> 1642787.7 | I22: =C22 -> 18.5 | J22: =H22/I22 -> 88799.333 | K22: =K21*(1+$H$6) -> 93436.828 | M22: =J22/H22 -> 0.054054054
B23: 83 | C23: 17.7 | D23: 108 | E23: 3.9 | G23: 83 | H23: =(H22-J22)*(1+$H$4) -> 1592838 | I23: =C23 -> 17.7 | J23: =H23/I23 -> 89990.849 | K23: =K22*(1+$H$6) -> 95772.749 | M23: =J23/H23 -> 0.056497175
B24: 84 | C24: 16.8 | D24: 109 | E24: 3.7 | G24: 84 | H24: =(H23-J23)*(1+$H$4) -> 1540418.4 | I24: =C24 -> 16.8 | J24: =H24/I24 -> 91691.569 | K24: =K23*(1+$H$6) -> 98167.067 | M24: =J24/H24 -> 0.05952381
B25: 85 | C25: 16 | D25: 110 | E25: 3.5 | G25: 85 | H25: =(H24-J24)*(1+$H$4) -> 1484945 | I25: =C25 -> 16 | J25: =H25/I25 -> 92809.06 | K25: =K24*(1+$H$6) -> 100621.24 | M25: =J25/H25 -> 0.0625
... B34: 94 | C34: 9.5 | D34: 119 | E34: 2.3 | G34: 94 | H34: =(H33-J33)*(1+$H$4) -> 885718.84 | I34: =C34 -> 9.5 | J34: =H34/I34 -> 93233.562 | K34: =K33*(1+$H$6) -> 125662.15 | M34: =J34/H34 -> 0.10526316
B35: 95 | C35: 8.9 | D35: 120 and over | E35: 2 | G35: 95 | H35: =(H34-J34)*(1+$H$4) -> 812297.41 | I35: =C35 -> 8.9 | J35: =H35/I35 -> 91269.371 | K35: =K34*(1+$H$6) -> 128803.7 | M35: =J35/H35 -> 0.11235955
B36: 96 | C36: 8.4 | G36: 96 | H36: =(H35-J35)*(1+$H$4) -> 739053.74 | I36: =C36 -> 8.4 | J36: =H36/I36 -> 87982.588 | K36: =K35*(1+$H$6) -> 132023.79 | M36: =J36/H36 -> 0.11904762
B37: 97 | G37: 97 | H37: =(H36-J36)*(1+$H$4) -> 667347.93 | I37: =E12 -> 7.8 | J37: =H37/I37 -> 85557.426 | K37: =K36*(1+$H$6) -> 135324.39 | M37: =J37/H37 -> 0.12820513
B38: 98 | G38: 98 | H38: =(H37-J37)*(1+$H$4) -> 596335.26 | I38: =E13 -> 7.3 | J38: =H38/I38 -> 81689.762 | K38: =K37*(1+$H$6) -> 138707.5 | M38: =J38/H38 -> 0.1369863
B39: 99 | G39: 99 | H39: =(H38-J38)*(1+$H$4) -> 527511.64 | I39: =E14 -> 6.8 | J39: =H39/I39 -> 77575.241 | K39: =K38*(1+$H$6) -> 142175.18 | M39: =J39/H39 -> 0.14705882
B40: 100 | G40: 100 | H40: =(H39-J39)*(1+$H$4) -> 461184.81 | I40: =E15 -> 6.4 | J40: =H40/I40 -> 72060.126 | K40: =K39*(1+$H$6) -> 145729.56 | M40: =J40/H40 -> 0.15625
B41: 101 | G41: 101 | H41: =(H40-J40)*(1+$H$4) -> 398852.8 | I41: =E16 -> 6 | J41: =H41/I41 -> 66475.466 | K41: =K40*(1+$H$6) -> 149372.8 | M41: =J41/H41 -> 0.16666667
B42: 102 | G42: 102 | H42: =(H41-J41)*(1+$H$4) -> 340686.76 | I42: =E17 -> 5.6 | J42: =H42/I42 -> 60836.922 | K42: =K41*(1+$H$6) -> 153107.12 | M42: =J42/H42 -> 0.17857143
B43: 103 | G43: 103 | H43: =(H42-J42)*(1+$H$4) -> 286846.09 | I43: =E18 -> 5.2 | J43: =H43/I43 -> 55162.709 | K43: =K42*(1+$H$6) -> 156934.8 | M43: =J43/H43 -> 0.19230769
B44: 104 | G44: 104 | H44: =(H43-J43)*(1+$H$4) -> 237475.46 | I44: =E19 -> 4.9 | J44: =H44/I44 -> 48464.38 | K44: =K43*(1+$H$6) -> 160858.17 | M44: =J44/H44 -> 0.20408163
B45: 105 | G45: 105 | H45: =(H44-J44)*(1+$H$4) -> 193736.36 | I45: =E20 -> 4.6 | J45: =H45/I45 -> 42116.6 | K45: =K44*(1+$H$6) -> 164879.62 | M45: =J45/H45 -> 0.2173913
B46: 106 | G46: 106 | H46: =(H45-J45)*(1+$H$4) -> 155410.25 | I46: =E21 -> 4.3 | J46: =H46/I46 -> 36141.92 | K46: =K45*(1+$H$6) -> 169001.62 | M46: =J46/H46 -> 0.23255814
B47: 107 | G47: 107 | H47: =(H46-J46)*(1+$H$4) -> 122250.04 | I47: =E22 -> 4.1 | J47: =H47/I47 -> 29817.084 | K47: =K46*(1+$H$6) -> 173226.66 | M47: =J47/H47 -> 0.24390244
B48: 108 | G48: 108 | H48: =(H47-J47)*(1+$H$4) -> 94743.783 | I48: =E23 -> 3.9 | J48: =H48/I48 -> 24293.278 | K48: =K47*(1+$H$6) -> 177557.32 | M48: =J48/H48 -> 0.25641026
... B60: 120 | G60: 120 | H60: =(H59-J59)*(1+$H$4) -> 986.82255 | I60: =E35 -> 2 | J60: =H60/I60 -> 493.41128 | K60: =K59*(1+$H$6) -> 238794.86 | M60: =J60/H60 -> 0.5

Sheet Cpi_index_inflation_montly_1925
A1: Series ID | B1: Year | C1: Period | D1: Label | E1: Value | F1: 12-Month % Change
A2: CUUR0000SA0 | B2: 1925 | C2: M01 | D2: 9133 | E2: 17.3 | F2: 0
A3: CUUR0000SA0 | B3: 1925 | C3: M02 | D3: 9164 | E3: 17.2 | F3: 0
A4: CUUR0000SA0 | B4: 1925 | C4: M03 | D4: 9192 | E4: 17.3 | F4: 1.2
A5: CUUR0000SA0 | B5: 1925 | C5: M04 | D5: 9223 | E5: 17.2 | F5: 1.2
A6: CUUR0000SA0 | B6: 1925 | C6: M05 | D6: 9253 | E6: 17.3 | F6: 1.8
A7: CUUR0000SA0 | B7: 1925 | C7: M06 | D7: 9284 | E7: 17.5 | F7: 2.9
A8: CUUR0000SA0 | B8: 1925 | C8: M07 | D8: 9314 | E8: 17.7 | F8: 3.5
A9: CUUR0000SA0 | B9: 1925 | C9: M08 | D9: 9345 | E9: 17.7 | F9: 4.1
A10: CUUR0000SA0 | B10: 1925 | C10: M09 | D10: 9376 | E10: 17.7 | F10: 3.5
A11: CUUR0000SA0 | B11: 1925 | C11: M10 | D11: 9406 | E11: 17.7 | F11: 2.9
A12: CUUR0000SA0 | B12: 1925 | C12: M11 | D12: 9437 | E12: 18 | F12: 4.7
A13: CUUR0000SA0 | B13: 1925 | C13: M12 | D13: 9467 | E13: 17.9 | F13: 3.5
... A1009: CUUR0000SA0 | B1009: 2008 | C1009: M12 | D1009: 39783 | E1009: 210.228 | F1009: 0.1
A1010: CUUR0000SA0 | B1010: 2009 | C1010: M01 | D1010: 39814 | E1010: 211.143
A1011: CUUR0000SA0 | B1011: 2009 | C1011: M02 | D1011: 39845 | E1011: 212.193
A1012: CUUR0000SA0 | B1012: 2009 | C1012: M03 | D1012: 39873 | E1012: 212.709
A1013: CUUR0000SA0 | B1013: 2009 | C1013: M04 | D1013: 39904 | E1013: 213.24
A1014: CUUR0000SA0 | B1014: 2009 | C1014: M05 | D1014: 39934 | E1014: 213.856
A1015: CUUR0000SA0 | B1015: 2009 | C1015: M06 | D1015: 39965 | E1015: 215.693
A1016: CUUR0000SA0 | B1016: 2009 | C1016: M07 | D1016: 39995 | E1016: 215.351
A1017: CUUR0000SA0 | B1017: 2009 | C1017: M08 | D1017: 40026 | E1017: 215.834
A1018: CUUR0000SA0 | B1018: 2009 | C1018: M09 | D1018: 40057 | E1018: 215.969
A1019: CUUR0000SA0 | B1019: 2009 | C1019: M10 | D1019: 40087 | E1019: 216.177
A1020: CUUR0000SA0 | B1020: 2009 | C1020: M11 | D1020: 40118 | E1020: 216.33
A1021: CUUR0000SA0 | B1021: 2009 | C1021: M12 | D1021: 40148 | E1021: 215.949
A1022: CUUR0000SA0 | B1022: 2010 | C1022: M01 | D1022: 40179 | E1022: 216.687 | F1022: 2.6
A1023: CUUR0000SA0 | B1023: 2010 | C1023: M02 | D1023: 40210 | E1023: 216.741 | F1023: 2.1
A1024: CUUR0000SA0 | B1024: 2010 | C1024: M03 | D1024: 40238 | E1024: 217.631 | F1024: 2.3
A1025: CUUR0000SA0 | B1025: 2010 | C1025: M04 | D1025: 40269 | E1025: 218.009 | F1025: 2.2
A1026: CUUR0000SA0 | B1026: 2010 | C1026: M05 | D1026: 40299 | E1026: 218.178 | F1026: 2
A1027: CUUR0000SA0 | B1027: 2010 | C1027: M06 | D1027: 40330 | E1027: 217.965 | F1027: 1.1
A1028: CUUR0000SA0 | B1028: 2010 | C1028: M07 | D1028: 40360 | E1028: 218.011 | F1028: 1.2
A1029: CUUR0000SA0 | B1029: 2010 | C1029: M08 | D1029: 40391 | E1029: 218.312 | F1029: 1.1
A1030: CUUR0000SA0 | B1030: 2010 | C1030: M09 | D1030: 40422 | E1030: 218.439 | F1030: 1.1
A1031: CUUR0000SA0 | B1031: 2010 | C1031: M10 | D1031: 40452 | E1031: 218.711 | F1031: 1.2
A1032: CUUR0000SA0 | B1032: 2010 | C1032: M11 | D1032: 40483 | E1032: 218.803 | F1032: 1.1
A1033: CUUR0000SA0 | B1033: 2010 | C1033: M12 | D1033: 40513 | E1033: 219.179 | F1033: 1.5
A1034: CUUR0000SA0 | B1034: 2011 | C1034: M01 | D1034: 40544 | E1034: 220.223
A1035: CUUR0000SA0 | B1035: 2011 | C1035: M02 | D1035: 40575 | E1035: 221.309
A1036: CUUR0000SA0 | B1036: 2011 | C1036: M03 | D1036: 40603 | E1036: 223.467
A1037: CUUR0000SA0 | B1037: 2011 | C1037: M04 | D1037: 40634 | E1037: 224.906
A1038: CUUR0000SA0 | B1038: 2011 | C1038: M05 | D1038: 40664 | E1038: 225.964
A1039: CUUR0000SA0 | B1039: 2011 | C1039: M06 | D1039: 40695 | E1039: 225.722
A1040: CUUR0000SA0 | B1040: 2011 | C1040: M07 | D1040: 40725 | E1040: 225.922
A1041: CUUR0000SA0 | B1041: 2011 | C1041: M08 | D1041: 40756 | E1041: 226.545
A1042: CUUR0000SA0 | B1042: 2011 | C1042: M09 | D1042: 40787 | E1042: 226.889
A1043: CUUR0000SA0 | B1043: 2011 | C1043: M10 | D1043: 40817 | E1043: 226.421
A1044: CUUR0000SA0 | B1044: 2011 | C1044: M11 | D1044: 40848 | E1044: 226.23
A1045: CUUR0000SA0 | B1045: 2011 | C1045: M12 | D1045: 40878 | E1045: 225.672
A1046: CUUR0000SA0 | B1046: 2012 | C1046: M01 | D1046: 40909 | E1046: 226.665 | F1046: 2.9
A1047: CUUR0000SA0 | B1047: 2012 | C1047: M02 | D1047: 40940 | E1047: 227.663 | F1047: 2.9
A1048: CUUR0000SA0 | B1048: 2012 | C1048: M03 | D1048: 40969 | E1048: 229.392 | F1048: 2.7
A1049: CUUR0000SA0 | B1049: 2012 | C1049: M04 | D1049: 41000 | E1049: 230.085 | F1049: 2.3
A1050: CUUR0000SA0 | B1050: 2012 | C1050: M05 | D1050: 41030 | E1050: 229.815 | F1050: 1.7
A1051: CUUR0000SA0 | B1051: 2012 | C1051: M06 | D1051: 41061 | E1051: 229.478 | F1051: 1.7
A1052: CUUR0000SA0 | B1052: 2012 | C1052: M07 | D1052: 41091 | E1052: 229.104 | F1052: 1.4
A1053: CUUR0000SA0 | B1053: 2012 | C1053: M08 | D1053: 41122 | E1053: 230.379 | F1053: 1.7
A1054: CUUR0000SA0 | B1054: 2012 | C1054: M09 | D1054: 41153 | E1054: 231.407 | F1054: 2
A1055: CUUR0000SA0 | B1055: 2012 | C1055: M10 | D1055: 41183 | E1055: 231.317 | F1055: 2.2
A1056: CUUR0000SA0 | B1056: 2012 | C1056: M11 | D1056: 41214 | E1056: 230.221 | F1056: 1.8
A1057: CUUR0000SA0 | B1057: 2012 | C1057: M12 | D1057: 41244 | E1057: 229.601 | F1057: 1.7
A1058: CUUR0000SA0 | B1058: 2013 | C1058: M01 | D1058: 41275 | E1058: 230.28
A1059: CUUR0000SA0 | B1059: 2013 | C1059: M02 | D1059: 41306 | E1059: 232.166
A1060: CUUR0000SA0 | B1060: 2013 | C1060: M03 | D1060: 41334 | E1060: 232.773
A1061: CUUR0000SA0 | B1061: 2013 | C1061: M04 | D1061: 41365 | E1061: 232.531
A1062: CUUR0000SA0 | B1062: 2013 | C1062: M05 | D1062: 41395 | E1062: 232.945
A1063: CUUR0000SA0 | B1063: 2013 | C1063: M06 | D1063: 41426 | E1063: 233.504
A1064: CUUR0000SA0 | B1064: 2013 | C1064: M07 | D1064: 41456 | E1064: 233.596
A1065: CUUR0000SA0 | B1065: 2013 | C1065: M08 | D1065: 41487 | E1065: 233.877
A1066: CUUR0000SA0 | B1066: 2013 | C1066: M09 | D1066: 41518 | E1066: 234.149
A1067: CUUR0000SA0 | B1067: 2013 | C1067: M10 | D1067: 41548 | E1067: 233.546
A1068: CUUR0000SA0 | B1068: 2013 | C1068: M11 | D1068: 41579 | E1068: 233.069
A1069: CUUR0000SA0 | B1069: 2013 | C1069: M12 | D1069: 41609 | E1069: 233.049
A1070: CUUR0000SA0 | B1070: 2014 | C1070: M01 | D1070: 41640 | E1070: 233.916 | F1070: 1.6
A1071: CUUR0000SA0 | B1071: 2014 | C1071: M02 | D1071: 41671 | E1071: 234.781 | F1071: 1.1
A1072: CUUR0000SA0 | B1072: 2014 | C1072: M03 | D1072: 41699 | E1072: 236.293 | F1072: 1.5
A1073: CUUR0000SA0 | B1073: 2014 | C1073: M04 | D1073: 41730 | E1073: 237.072 | F1073: 2
A1074: CUUR0000SA0 | B1074: 2014 | C1074: M05 | D1074: 41760 | E1074: 237.9 | F1074: 2.1
A1075: CUUR0000SA0 | B1075: 2014 | C1075: M06 | D1075: 41791 | E1075: 238.343 | F1075: 2.1
A1076: CUUR0000SA0 | B1076: 2014 | C1076: M07 | D1076: 41821 | E1076: 238.25 | F1076: 2
A1077: CUUR0000SA0 | B1077: 2014 | C1077: M08 | D1077: 41852 | E1077: 237.852 | F1077: 1.7
A1078: CUUR0000SA0 | B1078: 2014 | C1078: M09 | D1078: 41883 | E1078: 238.031 | F1078: 1.7
A1079: CUUR0000SA0 | B1079: 2014 | C1079: M10 | D1079: 41913 | E1079: 237.433 | F1079: 1.7
A1080: CUUR0000SA0 | B1080: 2014 | C1080: M11 | D1080: 41944 | E1080: 236.151 | F1080: 1.3
A1081: CUUR0000SA0 | B1081: 2014 | C1081: M12 | D1081: 41974 | E1081: 234.812 | F1081: 0.8
A1082: CUUR0000SA0 | B1082: 2015 | C1082: M01 | D1082: 42005 | E1082: 233.707
A1083: CUUR0000SA0 | B1083: 2015 | C1083: M02 | D1083: 42036 | E1083: 234.722
A1084: CUUR0000SA0 | B1084: 2015 | C1084: M03 | D1084: 42064 | E1084: 236.119
A1085: CUUR0000SA0 | B1085: 2015 | C1085: M04 | D1085: 42095 | E1085: 236.599
A1086: CUUR0000SA0 | B1086: 2015 | C1086: M05 | D1086: 42125 | E1086: 237.805
A1087: CUUR0000SA0 | B1087: 2015 | C1087: M06 | D1087: 42156 | E1087: 238.638
A1088: CUUR0000SA0 | B1088: 2015 | C1088: M07 | D1088: 42186 | E1088: 238.654
A1089: CUUR0000SA0 | B1089: 2015 | C1089: M08 | D1089: 42217 | E1089: 238.316
A1090: CUUR0000SA0 | B1090: 2015 | C1090: M09 | D1090: 42248 | E1090: 237.945
A1091: CUUR0000SA0 | B1091: 2015 | C1091: M10 | D1091: 42278 | E1091: 237.838
A1092: CUUR0000SA0 | B1092: 2015 | C1092: M11 | D1092: 42309 | E1092: 237.336
A1093: CUUR0000SA0 | B1093: 2015 | C1093: M12 | D1093: 42339 | E1093: 236.525
A1094: CUUR0000SA0 | B1094: 2016 | C1094: M01 | D1094: 42370 | E1094: 236.916 | F1094: 1.4
A1095: CUUR0000SA0 | B1095: 2016 | C1095: M02 | D1095: 42401 | E1095: 237.111 | F1095: 1
...

Sheet Inflation
C4: Table of Historical Inflation Rates in Percent
C5: (1914-2025)
C7: Year | D7: Jan | E7: Feb | F7: Mar | G7: Apr | H7: May | I7: Jun | J7: Jul | K7: Aug | L7: Sep | M7: Oct | N7: Nov | O7: Dec | P7: Ave
C8: 1914 | D8: 2 | E8: 1 | F8: 1 | G8: 0 | H8: 2.1 | I8: 1 | J8: 1 | K8: 3 | L8: 2 | M8: 1 | N8: 1 | O8: 1 | P8: 1
C9: 1915 | D9: 1 | E9: 1 | F9: 0 | G9: 2 | H9: 2 | I9: 2 | J9: 1 | K9: -1 | L9: -1 | M9: 1 | N9: 1 | O9: 2 | P9: 1
C10: 1916 | D10: 3 | E10: 4 | F10: 6.1 | G10: 6 | H10: 5.9 | I10: 6.9 | J10: 6.9 | K10: 7.9 | L10: 9.9 | M10: 10.8 | N10: 11.7 | O10: 12.6 | P10: 7.9
C11: 1917 | D11: 12.5 | E11: 15.4 | F11: 14.3 | G11: 18.9 | H11: 19.6 | I11: 20.4 | J11: 18.5 | K11: 19.3 | L11: 19.8 | M11: 19.5 | N11: 17.4 | O11: 18.1 | P11: 17.4
C12: 1918 | D12: 19.7 | E12: 17.5 | F12: 16.7 | G12: 12.7 | H12: 13.3 | I12: 13.1 | J12: 18 | K12: 18.5 | L12: 18 | M12: 18.5 | N12: 20.7 | O12: 20.4 | P12: 18
C13: 1919 | D13: 17.9 | E13: 14.9 | F13: 17.1 | G13: 17.6 | H13: 16.6 | I13: 15 | J13: 15.2 | K13: 14.9 | L13: 13.4 | M13: 13.1 | N13: 13.5 | O13: 14.5 | P13: 14.6
C14: 1920 | D14: 17 | E14: 20.4 | F14: 20.1 | G14: 21.6 | H14: 21.9 | I14: 23.7 | J14: 19.5 | K14: 14.7 | L14: 12.4 | M14: 9.9 | N14: 7 | O14: 2.6 | P14: 15.6
C15: 1921 | D15: -1.6 | E15: -5.6 | F15: -7.1 | G15: -10.8 | H15: -14.1 | I15: -15.8 | J15: -14.9 | K15: -12.8 | L15: -12.5 | M15: -12.1 | N15: -12.1 | O15: -10.8 | P15: -10.5
C16: 1922 | D16: -11.1 | E16: -8.2 | F16: -8.7 | G16: -7.7 | H16: -5.6 | I16: -5.1 | J16: -5.1 | K16: -6.2 | L16: -5.1 | M16: -4.6 | N16: -3.4 | O16: -2.3 | P16: -6.1
C17: 1923 | D17: -0.6 | E17: -0.6 | F17: 0.6 | G17: 1.2 | H17: 1.2 | I17: 1.8 | J17: 2.4 | K17: 3 | L17: 3.6 | M17: 3.6 | N17: 3 | O17: 2.4 | P17: 1.8
C18: 1924 | D18: 3 | E18: 2.4 | F18: 1.8 | G18: 0.6 | H18: 0.6 | I18: 0 | J18: -0.6 | K18: -0.6 | L18: -0.6 | M18: -0.6 | N18: -0.6 | O18: 0 | P18: 0
C19: 1925 | D19: 0 | E19: 0 | F19: 1.2 | G19: 1.2 | H19: 1.8 | I19: 2.9 | J19: 3.5 | K19: 4.1 | L19: 3.5 | M19: 2.9 | N19: 4.7 | O19: 3.5 | P19: 2.3
... C118: 2024 | D118: 3.1 | E118: 3.2 | F118: 3.5 | G118: 3.4 | H118: 3.3 | I118: 3 | J118: 2.9 | K118: 2.5 | L118: 2.4 | M118: 2.6 | N118: 2.7 | O118: 2.9 | P118: 2.9
C119: 2025 | D119: 3 | E119: 2.8 | F119: 2.4 | G119: 2.3 | H119: 2.4 | I119: 2.7 | J119: 2.7 | K119: 2.9 | L119: 3 | M119: – (*) | N119: 2.7 | O119: Avail.
O120: Jan.
O121: 13
P123: =(SUM(P8:P118)/111)/100 -> 0.03263964

Sheet Sheet1
B3: todays $1000
B5: future amout | C5: years | D5: discount rate | E5: PV
B6: 1000 | C6: 5 | D6: 0.0326 | E6: =PV(D6,C6,B6,B6) -> -5397.7098
C9: =B6/(1+D6)^C6 -> 851.80345

Sheet Sheet2

Sheet index test
A1: CPI
B3: Base year | C3: Test Year | D3: Factor | E3: base price | H3: Equivalent cost
B4: =Cpi_index_inflation_montly_1925!E1154 -> 261.582 | C4: =Cpi_index_inflation_montly_1925!E1166 -> 281.148 | D4: =B4/C4 -> 0.93040676 | E4: 1000 | F4: =E4*D4 -> 930.40676 | H4: =C4/B4 -> 1.0747987 | I4: =E4*H4 -> 1074.7987

Sheet Salarys 2024
C2: State | D2: Average Salary | E2: Median Salary | F2: color
C3: Alabama | D3: 53400 | E3: 41350 | F3: R
C4: Alaska | D4: 69880 | E4: 56140 | F4: R
C5: Arizona | D5: 63040 | E5: 47680 | F5: R
C6: Arkansas | D6: 51250 | E6: 39060 | F6: R
C7: California | D7: 76960 | E7: 54030 | F7: B
C8: Colorado | D8: 71960 | E8: 54050 | F8: B
C9: Connecticut | D9: 73740 | E9: 56130 | F9: B
C10: Delaware | D10: 65990 | E10: 49280 | F10: B
C11: Florida | D11: 60210 | E11: 45070 | F11: R
C12: Georgia | D12: 61250 | E12: 45480 | F12: R
C13: Hawaii | D13: 65030 | E13: 50510 | F13: B
C14: Idaho | D14: 55640 | E14: 44240 | F14: R
... C20: Louisiana | D20: 53440 | E20: 41320 | F20: R
C21: Maine | D21: 60000 | E21: 47590
C22: Maryland | D22: 73620 | E22: 55810
C23: Massachusetts | D23: 80330 | E23: 60690
C24: Michigan | D24: 60600 | E24: 46940 | F24: R
C25: Minnesota | D25: 66700 | E25: 50880
C26: Mississippi | D26: 47570 | E26: 37500 | F26: R
C27: Missouri | D27: 57580 | E27: 45080 | F27: R
C28: Montana | D28: 55920 | E28: 45690 | F28: R
C29: Nebraska | D29: 58080 | E29: 46440 | F29: R
C30: Nevada | D30: 58900 | E30: 44810 | F30: R
C31: New Hampshire | D31: 66110 | E31: 49980
C32: New Jersey | D32: 73980 | E32: 54860
C33: New Mexico | D33: 57520 | E33: 43620
C34: New York | D34: 78620 | E34: 56840
C35: North Carolina | D35: 59730 | E35: 45440 | F35: R
C36: North Dakota | D36: 59050 | E36: 48830 | F36: R
C37: Ohio | D37: 59890 | E37: 46690 | F37: R
C38: Oklahoma | D38: 53450 | E38: 41480 | F38: R
C39: Oregon | D39: 66710 | E39: 50010
C40: Pennsylvania | D40: 61920 | E40: 47430 | F40: R
C41: Rhode Island | D41: 66610 | E41: 50970
C42: South Carolina | D42: 54250 | E42: 42220 | F42: R
C43: South Dakota | D43: 53230 | E43: 43680 | F43: R
C44: Tennessee | D44: 56030 | E44: 43820 | F44: R
C45: Texas | D45: 61240 | E45: 45970 | F45: R
C46: Utah | D46: 61070 | E46: 47020 | F46: R
C47: Vermont | D47: 62780 | E47: 49630
C48: Virginia | D48: 70050 | E48: 49920
C49: Washington | D49: 78130 | E49: 59920
C50: West Virginia | D50: 52200 | E50: 39770 | F50: R
C51: Wisconsin | D51: 59500 | E51: 47590 | F51: R
C52: Wyoming | D52: 57930 | E52: 47250 | F52: R
C54: Source: Bureau of Labor Statistics, “Occupational Employment and Wage Statistics,” May 2023.

Sheet s&p_returns
B1: Year | C1: Return in %
B2: Column1 | C2: Column2
B3: 2024 | C3: 25.02
B4: 2023 | C4: 26.29
B5: 2022 | C5: -18.11
B6: 2021 | C6: 28.71
B7: 2020 | C7: 18.4
B8: 2019 | C8: 31.49
B9: 2018 | C9: -4.38
B10: 2017 | C10: 21.83
B11: 2016 | C11: 11.96
B12: 2015 | C12: 1.38
B13: 2014 | C13: 13.69
B14: 2013 | C14: 32.39
... B101: 1926 | C101: 11.62

Sheet SSI cola for the year
B3: Social Security Cost-Of-Living Adjustments
B4: Year | C4: COLA
B5: 1975 | C5: 8 | E5: Average | F5: =SUM(C5:C55)/((B55-B5)+1) -> 3.7294118
B6: 1976 | C6: 6.4
B7: 1977 | C7: 5.9
B8: 1978 | C8: 6.5
B9: 1979 | C9: 9.9
B10: 1980 | C10: 14.3
B11: 1981 | C11: 11.2
B12: 1982 | C12: 7.4
B13: 1983 | C13: 3.5
B14: 1984 | C14: 3.5
B15: 1985 | C15: 3.1
B16: 1986 | C16: 1.3
B17: 1987 | C17: 4.2
... B28: 1998 | C28: 1.3
B29: 1999 a | C29: 2.5
B30: 2000 | C30: 3.5
B31: 2001 | C31: 2.6
B32: 2002 | C32: 1.4
B33: 2003 | C33: 2.1
B34: 2004 | C34: 2.7
B35: 2005 | C35: 4.1
B36: 2006 | C36: 3.3
B37: 2007 | C37: 2.3
B38: 2008 | C38: 5.8
B39: 2009 | C39: 0
B40: 2010 | C40: 0
B41: 2011 | C41: 3.6
... B55: 2025 | C55: 2.8
